Workbook

Sheet Exercices
B1: Elément | C1: Niv1 | D1: Niv2 | E1: Niv3 | F1: Niv4 | G1: Phases
A3: 1.1 | B3: Sol | C3: Vérif/Ctrl | D3: Voile | E3: ------------------ | F3: ------------------
A4: 1.2 | B4: Sol | C4: Vérif/Ctrl | D4: Sellette | E4: ------------------ | F4: ------------------
A5: 1.3 | B5: Sol | C5: Vérif/Ctrl | D5: Secours | E5: ------------------ | F5: ------------------
A6: 1.4 | B6: Sol | C6: Gonflage | D6: Sans vent | E6: Pente école | F6: Dos Voile
A7: 1.5 | B7: Sol | C7: Gonflage | D7: Sans vent | E7: Pente école | F7: Face voile
A8: 1.6 | B8: Sol | C8: Gonflage | D8: Avec vent | E8: Terrain plat | F8: Face voile
A11: 2.1 | B11: Air | C11: Pilotage | D11: Tangage | E11: Non accel. | G11: Ressource/Abattée/Accélération
A12: 2.2 | B12: Air | C12: Pilotage | D12: Wings over | E12: Non accel.
A13: 2.3 | B13: Air | C13: Pilotage | D13: Oreille 1 suspente | E13: Non accel. | G13: Avec maintien du cap
A14: 2.4 | B14: Air | C14: Pilotage | D14: Oreille 1 suspente | E14: Accéléré | G14: Avec maintien du cap
A15: 2.5 | B15: Air | C15: Pilotage | D15: Oreille 2 suspentes | E15: Non accel. | G15: Avec maintien du cap
A16: 2.6 | B16: Air | C16: Pilotage | D16: Oreille 2 suspentes | E16: Accéléré | G16: Avec maintien du cap
A17: 2.7 | B17: Air | C17: Pilotage | D17: Oreille élévateur | E17: Non accel. | G17: Avec maintien du cap
A18: 3.1 | B18: Air | C18: Incidents | D18: Ferm Asy 1 suspente | E18: Non accel.
A19: 3.11 | B19: Air | C19: Incidents | D19: Ferm Asy 1 suspente | E19: Accéléré 1er barr.
A20: 3.12 | B20: Air | C20: Incidents | D20: Ferm Asy 1 suspente | E20: Accéléré 2ième barr.
A21: 3.13 | B21: Air | C21: Incidents | D21: Ferm Asy 2 suspentes | E21: Non accel.
A22: 3.14 | B22: Air | C22: Incidents | D22: Ferm Asy 2 suspentes | E22: Accéléré 1er barr.
A23: 3.15 | B23: Air | C23: Incidents | D23: Ferm Asy 2 suspentes | E23: Accéléré 2ième barr.
A24: 3.16 | B24: Air | C24: Incidents | D24: Ferm Asy élévateur | E24: Non accel.
A25: 3.17 | B25: Air | C25: Incidents | D25: Ferm Asy élévateur | E25: Accéléré 1er barr.
A26: 3.18 | B26: Air | C26: Incidents | D26: Ferm Asy élévateur | E26: Accéléré 2ième barr.
A27: 3.19 | B27: Air | C27: Incidents | D27: Frontale | E27: Non accel.
A28: 3.2 | B28: Air | C28: Incidents | D28: Frontale | E28: Accéléré 1er barr.
A29: 3.21 | B29: Air | C29: Incidents | D29: Frontale | E29: Accéléré 2ième barr.
A30: 3.22 | B30: Air | C30: Incidents | D30: Décrochage | E30: ------------------
A33: 4.1 | B33: Air | C33: Descente | D33: 360°
A34: 4.1 | B34: Air | C34: Descente | D34: B
B39: Documentation
B40: Dossier PP 161, 162, 163
B41: Manuel voile Golden
B42: Internet
B43: Stage

Sheet Comparatif voile
A1: Marque | B1: Modèle | C1: Année | D1: Taille | F1: PTV | G1: Class. | H1: Surf. à plat | I1: CH. Alaire à plat | J1: Surf. Proj. | K1: CH. Alaire proj | L1: Aplat. | M1: Allongement | N1: Allongement projeté | O1: Poids | P1: Nbre cellule | Q1: Nbre lignes | R1: Longueur cône | S1: Mettrage suspente | T1: prix | U1: Rmqs | V1: Essai
A2: Air Cross | B2: U Cruise | C2: 2016 | D2: M | E2: =CONCATENATE(A2, " - ",B2," - ",D2) -> Air Cross - U Cruise - M | F2: 75 / 100 | G2: B | H2: 26.67 | I2: =Matériel!$G$14/H2 -> #VALUE! | J2: 22.86 | K2: =Matériel!$G$14/J2 -> #VALUE! | L2: =(H2-J2)/H2*100 -> 14.285714 | M2: 5.6 | N2: 4.19 | O2: 5.8 | P2: 65 | Q2: 3 / 4 / 3 | R2: 7.58 | T2: 3900
A3: Mac Para | B3: Elan | C3: 2014 | D3: 26 | E3: =CONCATENATE(A3, " - ",B3," - ",D3) -> Mac Para - Elan - 26 | F3: 80 / 100 | G3: C | H3: 26.1 | I3: =Matériel!$G$14/H3 -> #VALUE! | M3: 6.2 | N3: 4.52 | O3: 5.7 | P3: 63 | Q3: 2+1 / 4 / 3 | R3: 6.77 | S3: 252 | T3: 3500 | U3: V light 4,5kg
A4: NOVA | B4: Mentor 4 | C4: 2015 | D4: S | E4: =CONCATENATE(A4, " - ",B4," - ",D4) -> NOVA - Mentor 4 - S | F4: 80 / 100 | G4: B | H4: 26 | I4: =Matériel!$G$14/H4 -> #VALUE! | M4: 5.43 | O4: 5.3 | P4: 55 | Q4: 2+1 / 4 / 3 | R4: 6.87 | S4: 237 | T4: 3800 | U4: V light 3,75 kg
A5: Ozone | B5: Delta | C5: 2010 | D5: M | E5: =CONCATENATE(A5, " - ",B5," - ",D5) -> Ozone - Delta - M | F5: 80/100 | G5: C | H5: 26 | I5: =Matériel!$G$14/H5 -> #VALUE! | J5: 22.4 | K5: =Matériel!$G$14/J5 -> #VALUE! | L5: =(H5-J5)/H5*100 -> 13.846154 | M5: 5.85 | N5: 4.4 | O5: 5.6 | P5: 58 | Q5: 3 / 3 / 4 | R5: 7.59 | S5: 308 | T5: 3650 | V5: Essai Ozone Delta 1 de Claire, En C, taille M (PTV 80 -100) du coup avec mon PTV de 91 kg, ça fait une charge alaire de 3,46 kg/m², Allongement à plat 5,8 / Poids 5,6 kg, Avant le vol, j'ai trouvé les branches des élévateurs difficile à manier, car trop fins par rapport à ceux de la Golden, d'ailleur je décolle avec les freins qui passent entre les A et B. Face voile, ça gonfle bien,peut-être un peu lentement. Je retrouve les sensations de la Jedi2, tout en douceur, des commandes assez légères, comme quoi mon à priori des commandes ozones physique était eronné. En terme de prise de commande, d'effort physique et de retour d'info, c'est la meilleur que j'ai essayé jusqu'à maintenant. Le virage est moins bon que celui des autres voiles essayées, plus proche de celui de la Golden, avec une tendance à engager de l'extèrieur, à piloter avec la commande ext. Elle semble très stable en tangage, elle donne les infos qui vont bien en roulis. Elle m'a semblé un peu lente, j'ai pplus suvent vu sur le GPS des vitesses entre 33 et 35 qu'au dessus. Je pense que du fait de la faible charge alaire ... et peut-être aussi des 350 heures de vol de la voile, elle manque de réactivité, de vivacité, de vitesse. Et comme avec la Diamir2, je trouve ces voiles classées EN C, bien facile à piloter, plus que ma Golden4 en tout cas et tr-s rassurante, plus que l'Apolo par exemple. Je vais demander à Thierry de me préter sa delta 2 pour voir ....
A6: Mac Para | B6: Elan 2 | C6: 2017 | D6: 26 | E6: =CONCATENATE(A6, " - ",B6," - ",D6) -> Mac Para - Elan 2 - 26 | F6: 80 / 100 | G6: C | H6: 25.8 | I6: =Matériel!$G$14/H6 -> #VALUE! | J6: 21.9 | K6: =Matériel!$G$14/J6 -> #VALUE! | L6: =(H6-J6)/H6*100 -> 15.116279 | M6: 6.27 | N6: 4.72 | O6: 4.9 | P6: 63 | Q6: 2+1 / 4 / 3 | R6: 7.39
A7: Mac Para | B7: Eden 6 | C7: 2016 | D7: 26 | E7: =CONCATENATE(A7, " - ",B7," - ",D7) -> Mac Para - Eden 6 - 26 | F7: 78 / 100 | G7: B | H7: 25.6 | I7: =Matériel!$G$14/H7 -> #VALUE! | J7: 21.95 | K7: =Matériel!$G$14/J7 -> #VALUE! | L7: =(H7-J7)/H7*100 -> 14.257813 | M7: 5.91 | N7: 4.41 | O7: 5.2 | P7: 56 | Q7: 2+1 / 4 / 3 | R7: 7.13 | S7: 238 | T7: 3400 | U7: V light 4,3kg
A8: Triple seven | B8: Queen | C8: 2013 | D8: M | E8: =CONCATENATE(A8, " - ",B8," - ",D8) -> Triple seven - Queen - M | F8: 80 / 100 | G8: C | H8: 25.5 | I8: =Matériel!$G$14/H8 -> #VALUE! | J8: 21.4 | K8: =Matériel!$G$14/J8 -> #VALUE! | L8: =(H8-J8)/H8*100 -> 16.078431 | M8: 6.2 | N8: 4.64 | O8: 5 | P8: 62 | Q8: 1+1 / 3 /2 | T8: 3700
A9: Gradient | B9: Aspen 5 | C9: 2014 | D9: 26 | E9: =CONCATENATE(A9, " - ",B9," - ",D9) -> Gradient - Aspen 5 - 26 | F9: 85 / 103 | G9: C | H9: 25.5 | I9: =Matériel!$G$14/H9 -> #VALUE! | J9: 21.49 | K9: =Matériel!$G$14/J9 -> #VALUE! | L9: =(H9-J9)/H9*100 -> 15.72549 | M9: 6.25 | N9: 4.54 | O9: 5.1 | P9: 64 | Q9: 2 / 3 / 2 | R9: 7.3 | S9: 233 | T9: 3750
A10: Advance | B10: Sigma 9 | C10: 2014 | D10: 25 | E10: =CONCATENATE(A10, " - ",B10," - ",D10) -> Advance - Sigma 9 - 25 | F10: 75 / 100 | G10: C | H10: 25.1 | I10: =Matériel!$G$14/H10 -> #VALUE! | J10: 20.9 | K10: =Matériel!$G$14/J10 -> #VALUE! | L10: =(H10-J10)/H10*100 -> 16.733068 | M10: 5.85 | N10: 4.1 | O10: 4.9 | P10: 59 | Q10: 2+1 / 3 / 4 | R10: 7.5 | T10: 3800
A11: ITV | B11: Jedi 2 | C11: 2015 | D11: M | E11: =CONCATENATE(A11, " - ",B11," - ",D11) -> ITV - Jedi 2 - M | F11: 80 / 100 | G11: B | H11: 25 | I11: =Matériel!$G$14/H11 -> #VALUE! | J11: NC | M11: 5.7 | N11: NC | O11: 4.5 | P11: 55 | Q11: 2 / 3 / 2 | R11: 6.53 | T11: 3350 | V11: Essai ITV JEDI 2, En B, taille L (PTV 95 -120) du coup avec mon PTV de 91 kg, ça fait une charge alaire de 3,27 kg/m², Allongement à plat 5,7 / Allongement projeté 4,5 / Longueur cône suspentage 6,5m / Metrage suspentes ? m / 55 cellules / Suspentage en 2 / 3 / 2. Poids 4,5 kg, Toutes les caractéristiques techniques sont pour moi au vert, sauf le PTV suite erreur de l'importateur à qui nous avions demandé une M. Je ne m'en rendrais compte qu'une fois posé au moment de plier avec l'aide de Pierre ou on s'est dit qu'elle ressemblé à un Bi place... Avant le vol, j'ai trouvé les élévateurs un peu compliqué avec 2 "A" à 1 suspente, je suppose pour les oreilles. Mais après quelques "noeuds" je finis par m'en sortir. Les suspentes sont gainés jusqu'en haut, on se demande pourquoi, habituellement seules les basses sont gainées. Ca gonfle très bien, très facilement. Alors que je ne savais pas que C T une L, je me souvien bien m'eêtre dit qu'elle étais très douce, trés veloutée. Je me suis aussi dit qu'lle n'avançait pas beaucoup mais que les conditions du jour ne permettais pas de certutitude, avec du N et une bonne tendeuse orageuse sur la chaine qui se confirmera. En fait je me suis régalé, une véritable monde de douceur. En plus un vautour m'a montré la voie du coté du Col de Larrieu, je l'ai vivement remercié en vol, suis pas sur qu'il est vraiment compris ma gratitude ... que du plaisir. Au retour d'Herbes blanche, le ciel devenat menaçant, j'ai forcé l'allure, accéléré o fond, certs ça n'allait pas très vite, mais encore une fois, le ciel était bien noir derrière moi. Du cou, j'en ai profité pour essayer oreilles + acc., elles flappent ppas mal, mais c'est tenable, contrairement à la Diamir 2. Arrivé haut au dessu sd'Arbas, j'ai envoyé de bon 350 ... enfin à mo niveau, waouh la sortie, comment dit on "aérienne". Mais en tout instant du vol, elle m'a donné confiance, aucune fermeture, RAS sur toute la ligne. Si Thierry se debourille avec ITV, j'essaireai bien la M (PTV 80-100), je suis à 91. Mais je crains que les commandes deviennnet trop physique, là avec la L c'était limite pour moi. A suivre avec une M ???
A12: Swing | B12: Nyos | C12: 2015 | D12: M | E12: =CONCATENATE(A12, " - ",B12," - ",D12) -> Swing - Nyos - M | F12: 80 / 100 | G12: B | H12: 25 | I12: =Matériel!$G$14/H12 -> #VALUE! | J12: 21.6 | K12: =Matériel!$G$14/J12 -> #VALUE! | L12: =(H12-J12)/H12*100 -> 13.6 | M12: 5.8 | N12: 4.4 | O12: 5 | P12: 59 | Q12: 2+1 / 3 / 4 | R12: 6.74 | T12: 3900
A13: UP | B13: Kibo | C13: 2016 | D13: SM | E13: =CONCATENATE(A13, " - ",B13," - ",D13) -> UP - Kibo - SM | F13: 75 / 95 | G13: B | H13: 24.9 | I13: =Matériel!$G$14/H13 -> #VALUE! | M13: 5.7 | O13: 4.7 | P13: 49 | Q13: 2+1 / 4 / 3 | R13: 6.75 | S13: 268 | T13: 3600
A14: U-Turn | B14: Blacklight 2 | C14: 2016 | D14: S | E14: =CONCATENATE(A14, " - ",B14," - ",D14) -> U-Turn - Blacklight 2 - S | F14: 65 / 90 | G14: B | H14: 24.8 | I14: =Matériel!$G$14/H14 -> #VALUE! | J14: 21.55 | K14: =Matériel!$G$14/J14 -> #VALUE! | L14: =(H14-J14)/H14*100 -> 13.104839 | M14: 5.61 | N14: 4.24 | O14: 4.7 | P14: 59 | Q14: 2+1 / 4 / 3 | R14: 7.2 | S14: 239
A15: Sky Paragliders | B15: Antéa 2 | C15: 2011 | D15: M | E15: =CONCATENATE(A15, " - ",B15," - ",D15) -> Sky Paragliders - Antéa 2 - M | F15: 75 / 95 | G15: C | H15: 24.6 | I15: =Matériel!$G$14/H15 -> #VALUE! | J15: 21.83 | K15: =Matériel!$G$14/J15 -> #VALUE! | L15: =(H15-J15)/H15*100 -> 11.260163 | M15: 5.5 | N15: 4.24 | O15: 4.9 | P15: 59 | Q15: 3 / 4 / 3 / 2 | T15: 3450
A16: Niviuk | B16: Ikuma | C16: 2015 | D16: 25 | E16: =CONCATENATE(A16, " - ",B16," - ",D16) -> Niviuk - Ikuma - 25 | F16: 80 / 100 | G16: B | H16: 24.5 | I16: =Matériel!$G$14/H16 -> #VALUE! | J16: 20.75 | K16: =Matériel!$G$14/J16 -> #VALUE! | L16: =(H16-J16)/H16*100 -> 15.306122 | M16: 5.7 | N16: 4.26 | O16: 4.9 | P16: 57 | Q16: 2 / 2 / 3 | R16: 7.2 | S16: 238 | T16: 3800
A17: Sky Paragliders | B17: Apollo | C17: 2015 | D17: M | E17: =CONCATENATE(A17, " - ",B17," - ",D17) -> Sky Paragliders - Apollo - M | F17: 74 / 94 | G17: B | H17: 24.5 | I17: =Matériel!$G$14/H17 -> #VALUE! | J17: 21.56 | K17: =Matériel!$G$14/J17 -> #VALUE! | L17: =(H17-J17)/H17*100 -> 12 | M17: 5.45 | N17: 4.2 | O17: 4.6 | P17: 55 | Q17: 2+1 / 4 / 3 | R17: 6.94 | T17: 3750 | V17: Essai Sky paragliders Apolo, En B, taille M (PTV 74-94), Allongement à plat 5,5 / Allongement projeté 4,2 / Longueur cône suspentage 6,9m / Metrage suspentes ? m / 55 cellules / Suspentage en 2+1 / 4 / 3. Poids 4,6 kg, Toutes les caractéristiques techniques sont pour moi au vert. Le 09/05, essai en // avec Thierry qui vole sous la Diamir2. Un premier très bon point, le poids, 4,4 kg, c'est 300g de moins que ma Golden et pareil que la Diamir2. Elle est livrée avec un sac chaussette, c'est la première fois que j'en utilise un, c'est vrai que c'est bien cool à utiliser. 1er contact ok avec la voile, suspentes basses gainées, les élévateurs sont quand même bien fins… dommage qui ne s'élargisse pas au niveau des maillons. Les poignées de freins sont accrochées par une pression, la prise en mains des commandes ne pose pas de problème. Il s'agit de poignée souple, mais avec un gadget qui va s'avéré interressant en vol, une petite palette rigide basculante qui se cale entre pouce et index et qui donne une prise de commande précise. Par contre ça fait plus travailler les mains, d'ou fatigue, mais rien n'empêche alors de reprendre la position dragonne. Coté suspentage, le démélage est fluide et simple. Déco face voile trés facile, très léger, presque aérien. Je me permets même de temporiser la voile au dessus de ma tête après m'être retourné, du caviar... quoique je n'en ai jamais gouté... En sortie de déco, grosse surprise, j'ai l'impression d'avoir un gun au dessus de la tête quoique je n'en ai jamais piloté non plus, mais elle réagit très vite, elle est d'une légèreté aux commandes que je n'avais pas rencontré sur les voiles essayées précédemment. Beaucoup de mvts de roulis retransmis à la sellette. Tout le début du vol a été assez perturbé à cause de ça. Puis peu à peu, je ne le ai plus senti comme une gène, au profit d'une qualité de virage et d'une précision de commandes assez génial. Aucune fermeture à signaler pendant les 1h40 de vol. C'est bien la conception de la voile qui donne des bouts d'ailes sensibles qui donnent bcp d'infos (peut-être trop...) mais qui permettent certainement la qualité de virage et la "délicatesse" des commandes. Avec du recul ça me rappelle les commandes de mon Aspen 1er du nom. En thermique, j'ai fait aussi bien que Thierry ou qu'une delta 2 ou que Tim avec sa Mantra, et comme ils sont tous bien meilleur pilote que moi, c'est que l'aile est facile. En transistion, on a fait 3/4 bonne longueur de comparaison, la Diamir2 est mieux, il me semble en particulier dés qu'il faut un chouilla de vitesse en plus en début d'accélérateur ou quand c'est un peu turbulent... le fameux "floating" ? Coté accélérateur, c'est très, très doux également, la course est plutot faible, en tout cas plus que sur ma Gilden ou que la Diamir. Il me semble que dés qu'on accélere, la finess se dégrade, je pense que cest moins bon que la Diamir2. Mais il faut bien que 0,6 points de finesse fassent la différence quelque part. Pour l'instant à choisir je resterai sur la Diamir2, un peu pour les perfs mais surtouts par la gestion globale plus facile en vol, je suis sûr que sur plusieurs heures de vols, la Diamir2 est moins exigeante.
A18: Advance | B18: Sigma 10 | C18: 2017 | D18: 25 | E18: =CONCATENATE(A18, " - ",B18," - ",D18) -> Advance - Sigma 10 - 25 | F18: 80 / 100 | G18: C | H18: 24.5 | I18: =Matériel!$G$14/H18 -> #VALUE! | J18: 20.96 | K18: =Matériel!$G$14/J18 -> #VALUE! | L18: =(H18-J18)/H18*100 -> 14.44898 | M18: 6.16 | N18: 4.6 | O18: 4.9 | P18: 66 | Q18: 2+1 / 4 / 3 | R18: 7.46 | T18: 4250
A19: Niviuk | B19: Artik 4 | C19: 2014 | D19: 25 | E19: =CONCATENATE(A19, " - ",B19," - ",D19) -> Niviuk - Artik 4 - 25 | F19: 75 / 95 | G19: C | H19: 24.5 | I19: =Matériel!$G$14/H19 -> #VALUE! | M19: 6.1 | N19: 4.56 | O19: 5.2 | P19: 63 | Q19: 1+1 / 2 / 3 | R19: 7.5 | S19: 245 | T19: 3800 | U19: V light 4kg
A20: Gradient | B20: Golden 4 | C20: 2013 | D20: 24 | E20: =CONCATENATE(A20, " - ",B20," - ",D20) -> Gradient - Golden 4 - 24 | F20: 75 / 90 | G20: B | H20: 24.4 | I20: =Matériel!$G$14/H20 -> #VALUE! | J20: 21.02 | K20: =Matériel!$G$14/J20 -> #VALUE! | L20: =(H20-J20)/H20*100 -> 13.852459 | M20: 5.3 | N20: 4.16 | O20: 4.9 | P20: 51 | Q20: 2+1 / 4 / 3 | R20: 6.57 | S20: 241 | T20: 3340
A21: Ozone | B21: Delta 2 | C21: 2013 | D21: MS | E21: =CONCATENATE(A21, " - ",B21," - ",D21) -> Ozone - Delta 2 - MS | F21: 75 / 95 | G21: C | H21: 24.4 | I21: =Matériel!$G$14/H21 -> #VALUE! | J21: 20.5 | K21: =Matériel!$G$14/J21 -> #VALUE! | L21: =(H21-J21)/H21*100 -> 15.983607 | M21: 6 | N21: 4.4 | O21: 5 | P21: 62 | Q21: 2+1 / 3 / 4 | T21: 3800 | V21: Essai Ozone Delta 2 En C, taille S (PTV 65-85), Charge alaire 3,9kg/m² à plat et 4,6 projeté. Allongement à plat 6 / Allongement projeté 4,4 / 62 cellules / Suspentage en 2+1 / 3 / 4. Poids 4,7 kg. La voile est celle de Thierry Damian, elle a 450 heures de vols, je ne sais évidemment pas comment elle était neuve, mais franchement, à part son état ext., impossible de détecter son "âge". Déco impossible à juger, j'ai décoler face voile et twister, trés nul. Je n'ai jamais eu l'impression d'être au dessus du PTV (+5kg), la voile est douce, réagit aux commandes sur 20 à 30 cms sans beaucoup d'effort, du même niveau que la Diamir 2, je suppose qu'en apprenant la voile, elle est très très bien en thermique. Pas de mouvement de lacet, pas d'engagement du coté ext. comme avec la Golden ou l'Apolo. Par contre moins d'informatrions pertinentes pour centrer le thermique. En transition y'a pas photo, ça plane, peut-être mieux que la Diamir 2, mais par contre elle tangue régulièrement, j'ai cru que CT de ma faute, mais Thierry me l'a ensuite confirmé, alors que la Diamir2 est extrèmement stable. Sur essai d'oreille asymétrique, elle part nettement du coté ... ouvert, comme la Golden, comme quoi y'a vraiment un truc étarnge, ou alors c'est moi qui contre involontairement. J'ai essayé qque tangages, elle a comportement étonnant, dans l'abatée, elle semble faire une pause quand elle passe à la vertivale, puis repartir vers l'avant. Mais le tangage est équivalent à la Golden, peut-être plus dynamique que la Diamir2. Par contre elle semble vive en roulis, faudrait ré essayer. Du coup, la Diamir 2 reste m'a favorite, il faudrait essayer une delta 3, mais elle est encore plus chère que la Diamir ... alors...
A22: Sky Paragliders | B22: Argos | C22: 2014 | D22: M | E22: =CONCATENATE(A22, " - ",B22," - ",D22) -> Sky Paragliders - Argos - M | F22: 75 / 90 | G22: C | H22: 24.15 | I22: =Matériel!$G$14/H22 -> #VALUE! | M22: 5.5 | O22: 4.4 | P22: 59 | Q22: 3 / 4 / 3 | R22: 7.11
A23: Air Design | B23: Rise 2 | C23: 2014 | D23: S | E23: =CONCATENATE(A23, " - ",B23," - ",D23) -> Air Design - Rise 2 - S | F23: 70 / 90 | G23: B | H23: 24 | I23: =Matériel!$G$14/H23 -> #VALUE! | M23: 5.65 | O23: 5.2 | P23: 49 | Q23: 2+1 / 3 / 3 | S23: 252 | T23: 3500 | U23: V light 3,9kg
A24: Nervures | B24: Diamir 2 | C24: 2016 | D24: S | E24: =CONCATENATE(A24, " - ",B24," - ",D24) -> Nervures - Diamir 2 - S | F24: 70 / 90 | G24: C | H24: 24 | I24: =Matériel!$G$14/H24 -> #VALUE! | J24: 20.6 | K24: =Matériel!$G$14/J24 -> #VALUE! | L24: =(H24-J24)/H24*100 -> 14.166667 | M24: 6.1 | N24: 4.74 | O24: 4.5 | P24: 63 | Q24: 2+1 / 4 / 3 | R24: 6.93 | S24: 291 | T24: 4150 | U24: V light 3,7kg | V24: Essai Nervures Diamir 2, En C, taille S (PTV 70-90), Allongement à plat 6,1 / Allongement projeté 4,74 / Longueur cône suspentage 6,9 m / Metrage suspentes 271 m / 63 cellules / Suspentage en 2+1 / 4 / 3. Poids 4,5 kg, Les caractéristiques techniques sont pour moi au vert, je suis étonné de la longueur totale de suspentes ... sauf le prix. Le 23/04, gros vol de 75 kms A/R Arbas-Sacon. Manquant terriblement de référence, je dirai que la voile est parfaite sauf les élévateurs/poignées de freins qui ne me conviennent pas du tout et les oreilles qui battent beaucoup et s'ouvrent difficilement. Le gonflage est facile, confirmé par Thierry Damian qui a bcp plus d'expérience que moi. On sent bien que ça plane et que ça avance, un peu mieux légèrement accéléré, et qu'elle est utilisable à fond d'accélérateur. L'effort aux commandes est plus élevé que sur la Golden, mais peut-être faudrait-il la laisser plus voler en thermique avec plus d'appui sellette ? Tjrs T Damian dit que c'est équivalent à la delta 2. Mais là j'avais la ventrale plutot serré, je sentais bien que je n'avais quasiment pas d'efficacité sellette. Peut-être aussi que je la charge trop ? L'utilisation de l'accélérateur est dans la limite haute pour l'effort demandé. Les + comme ça viteuf : La légèreté, les suspentes gainées en parties basses, l'utilisation de l'accélérateur, à priori la gestion des incidents, j'ai pris une grosse aymétrique accéléré à fond, j'ai à peine eu le temps de réagir en lachant l'accélérateur qu'elle avait fait un quart de tour coté fermé et qu'elle été déjà réouverte et quelques bouts d'ailes insignifiants. idem pour des dégonflages/regonflage instantannée du BA. Par contre elle est chère ! A réessayer après d'autres essais ? Et ben justement 2d essai le 18/07, avec 2 vols. Au premier grosse connerie de ma part au déco, je la laisse me dépasser et elle ferme, je suis à 2 doigts du crash. Du coup je passe la suite du vol à me calmer dans des petits thermique du coté de Bourrus. Elle troune bien, mais moins que l'Apolo ou la Nevada et ses commandes demandent plus d'effort, ça confirme bien mon 1er ressenti. En fait je suis presque sûr que c'est une machine à cross, facile, peu de mouvement parasites sauf peut-e^tre des petits coup de "raquettes" en roulis. Le 2d vols m'a juste servi à décoller sans vent, voir cul d'ailleur, en m'appliquant pour remonter mon moral. Chose faite. J'ai enchainé qques essais dont des petits wings en freinant des 2 cotés, je pense que je finirai par y arriver. Cette voile est vraiment super, mais j'achète la Nevada2, plus facile à piloter, moins physique et moins cher !!!
A25: Swing | B25: Nexus | C25: 2015 | D25: S | E25: =CONCATENATE(A25, " - ",B25," - ",D25) -> Swing - Nexus - S | F25: 74 / 98 | G25: C | H25: 24 | I25: =Matériel!$G$14/H25 -> #VALUE! | M25: 6.1 | N25: 4.7 | O25: 5.2 | P25: 64 | Q25: 2+1 / 3 / 4 | R25: 7.13
A26: Gradient | B26: Nevada 2 | C26: 2016 | D26: 24 | E26: =CONCATENATE(A26, " - ",B26," - ",D26) -> Gradient - Nevada 2 - 24 | F26: 75 / 90 | G26: B | H26: 23.2 | I26: =Matériel!$G$14/H26 -> #VALUE! | J26: 19.61 | K26: =Matériel!$G$14/J26 -> #VALUE! | L26: =(H26-J26)/H26*100 -> 15.474138 | M26: 5.75 | N26: 4.14 | O26: 4.7 | P26: 56 | Q26: 2 / 3 / 2 | R26: 7.07 | S26: 215 | T26: 3750 | U26: V light 3,8 kg, meme ^prix | V26: J'écris ce CR après achat, c'est donc encore un peu plus subjectif. 7 heures d'essai + 2 heures de gonflage. C'est l'une des moins ambitieuse des voiles que j'envisageai, du coup complètement dans mon cahier des charges, EN B, Allongement à plat 5,75 / Allongement projeté 4,14 / Longueur cône suspentage 7 m / Metrage suspentes 214 m / 56 cellules / Suspentage en 2 / 3 / 2. Poids 3,9 kg en light, ce sont donc des caractériqtiques très proche de la Golden, l'allongement projeté est même inférieure. Le supsentage est minimaliste, mais idéale en terme de gainage pour les parties basses. Elélvateurs très facile à manier, par contre les poignées sont trop raide en gants fins, il faudra que j'ajoute une poignée type pilotage. La longueur totale de suspentes des super étonnantes, certainement la plus basse dans cette catégorie. A noter la simplicité globale de la voile, des joncs très fins, ce qui fait que je la plie à l'ancienne, pas de prise de tête excessif. Le gonflage est délicat, si on ne l'a met pas sufisamment en corole, elle gonfle par les bouts d'aile. c'est du aux 2 suspentes reliées au même maillon d'élélvateur. Face voile, il vaut mieux prendre les 2 suspents centrales au dessus du maillon. Ensuite elle monte doucement et semble marquer un point d'arret 10/20° avant d'arriver en haut. Certainement des atouts par vent fort, je n'ai pas pu tester, mais une réelle attention par vent faible ou nul. Je l'ai quand même décoller par très léger vent de cul au PLanot, et tout c'est bien passé. En vol, 2 caractéristiques majeurs : La 1ere, elle va vite, au feeling la plus rapide de toutes celle essayé, et accéléré c'est encore plus impressionnant. J'ai lu au GPS des vitesses que je n'avais jamais vu en air calme. La 2d, elle tourne dans un mouchoir de poche avec très peu d'effort aux commandes. Inversion de virage hyper facile, une grande joueuse. Par contre en haut de fourchette comme je suis, le tau de chute est certainement un peu plus important que d'autres voiles, faudra se battre en petites conditions. Les oreilles sont parfaites, accélérés on est vite à -3, -4 m/s. Excellent. Par contre y'a que 2 suspentes sur chacun des élévateurs en A, B et C + une de stabilo sur C, du coup aux oreilles, ben y'a plus que 2 suspentes en A.... J'ai essayé 2 fernture asymétrique avec un élévateur complet, ça part vite et le contre est sensible à la commande, il faudra le travailler pour ne pas surpiloter le jour venu. En fait j'ai pris une belle grosse fermeture asymétrique lors de l'un des vols, j'ai été vraiment limite et rès près du sur pilotage. Mais bon, c'est une EN B, je suppose qu'ele le mérite. J'ai fait plusieurs approches d'attéro en basses vitesses, elle a l'air très tolérente, elle reprend vite de la vitesse en remontant les mains. Le prix a aussi été un facteur d'achat, 400 euros de moins que la Diamir2 en prix publique, ça compte.
A27: Ozone | B27: Delta 3 | C27: 2017 | D27: MS | E27: =CONCATENATE(A27, " - ",B27," - ",D27) -> Ozone - Delta 3 - MS | F27: 75 / 95 | G27: C | H27: 23.1 | I27: =Matériel!$G$14/H27 -> #VALUE! | J27: 19.6 | K27: =Matériel!$G$14/J27 -> #VALUE! | L27: =(H27-J27)/H27*100 -> 15.151515 | M27: 6 | N27: 4.4 | O27: 5.3 | P27: 66 | Q27: 2+1 / 3 / 4 | R27: 7.27
A28: Gradient | B28: Aspen 6 | C28: 2017 | D28: 24 | E28: =CONCATENATE(A28, " - ",B28," - ",D28) -> Gradient - Aspen 6 - 24 | F28: 70-90 | G28: C | H28: 22.73 | I28: =Matériel!$G$14/H28 -> #VALUE! | J28: 18.93 | K28: =Matériel!$G$14/J28 -> #VALUE! | L28: =(H28-J28)/H28*100 -> 16.717994 | M28: 6.46 | N28: 4.99 | O28: 4.5 | P28: 66 | Q28: 3 / 3 / 4 | R28: 7 | S28: 244 | T28: 3950
A29: Sky Paragliders | B29: Exos | C29: 2017 | D29: M | E29: =CONCATENATE(A29, " - ",B29," - ",D29) -> Sky Paragliders - Exos - M | F29: 70 / 95 | G29: C | H29: 22.12 | I29: =Matériel!$G$14/H29 -> #VALUE! | J29: 19.42 | K29: =Matériel!$G$14/J29 -> #VALUE! | L29: =(H29-J29)/H29*100 -> 12.206148 | M29: 6.4 | N29: 4.92 | O29: 4 | P29: 65 | Q29: 2+1 / 3 / 2 / 2 | R29: 7.68 | S29: NC | T29: 4150
A30: Advance | B30: Sigma 11 | C30: 2021 | D30: 24 | E30: =CONCATENATE(A30, " - ",B30," - ",D30) -> Advance - Sigma 11 - 24 | F30: 85 / 97 | G30: C | H30: 23.6 | J30: 20.1 | L30: =(H30-J30)/H30*100 -> 14.830508 | M30: 6.07 | N30: 4.48 | O30: 4.5 | P30: 67 | Q30: 3/4/3

Sheet Matériel
A1: Marque | B1: Modèle | C1: Année | D1: Taille | E1: Historique | F1: Contrôle | G1: PTV | H1: Class. | I1: Surface à plat | J1: CH. Alaire à plat | K1: Surface projetée | L1: CH. Alaire proj | M1: Allongement | N1: Allongement projeté | O1: Poids | P1: Nbre cellule | Q1: Nbre lignes | R1: Longueur cône | S1: Mettrage suspente | T1: prix | U1: Rmqs | V1: Essai
A3: Swing | B3: Astral (1999-50h) | C3: 1998 | D3: M | G3: 75/100 | H3: DHV 2 | I3: 29.2 | M3: 5.15 | O3: 6.2 | P3: 54 | Q3: 2 + 1 /4 / 3 / 2 | R3: 7.5 | T3: 3000
A4: Advance | B4: Epsilon 3 (2000-75h) | C4: 1999 | D4: 28 | G4: 90/107 | H4: DHV 1-2 | I4: 27.4 | M4: 4.8 | O4: 6.3 | P4: 37 | Q4: 3 / 4 / 3 / 2 | R4: 7.94 | T4: 2900
A5: Windtech | B5: Quarx (2001-2002 - 65h) | C5: 1999 | D5: 27 | G5: 85/105 | H5: DHV 2 | I5: 27.1 | M5: 5.41 | O5: 6.8 | P5: 67 | Q5: 3 / 3 / 4 / 2 | R5: 7.7 | T5: 3000
A6: Windtech | B6: Serak (2003 - 35h/an) | C6: 2001 | D6: M | G6: 85/105 | H6: DHV 1-2 | I6: 27.55 | M6: 5.05 | O6: 7.2 | P6: 54 | Q6: 3 / 3 / 3 / 3 | R6: 7.2
A7: Gradient | B7: Aspen 1 (2004-2010 - 30h/an) | C7: 2003 | D7: 26 | G7: 80/100 | H7: DHV 2 | I7: 26.34 | M7: 5.58 | O7: 5.5 | P7: 52 | Q7: 3 / 3 / 4 / 2 | R7: 7.38 | S7: 360 | T7: 3050
A8: Gradient | B8: Golden 4 (2015-2017 - 50h/an) | C8: 2013 | D8: 24 | E8: Volé 100 heures en 17 mois, acheté 1800 € + 150 € de contrôle, vendu 1200 €, ça fait 7,5 €/h. Vendu à Olivier HERAULT de St Lary. Il a fait un vol avec et a été enchanté. | G8: 75 / 90 | H8: B | I8: 24.4 | K8: 21 | M8: 5.3 | N8: 4.16 | O8: 4.9 | P8: 51 | Q8: 2 +1 / 4 / 3 | R8: 6.57 | S8: 241 | T8: 3340
A9: Gradient | B9: Névada 2 - 24 Light | C9: 2017 | D9: 24 | E9: Acheté neuve 3000€ en 07/2017 | F9: Révision déc 2018 après 140h. Quelques retouches de calage. Drisses inferieures de frein changées. Durée de vie, 72% restant. ----------------------------- Révision 30/06/2020 à 210h. Tout en TBE, Porosité >300s, Déplacement global du centre d'attache de 39mm. Recalage léger de quelques suspentes. Durée de vie restante 75% ou 300h. ---------------------- Révision chez Jean-Marc en janvier 2022, à 300 heures. RAS. Porosité > 300s Tissus impeccable, quelques retouches de calage. Par contre, le constructeur préconise le remplacement du suspentage au bout de 5 ans ou 350heures. A voir en fin de saisosn. Durée de vie restante 70% ----------------------- Révision chez Jean-Marc le 30/09/2023 à 340 h avec test rupture suspente. tout est ok, la voile est bonne pour encore longtemps | G9: 75/90 | H9: B | I9: 23.2 | J9: 3.8 | K9: 19.61 | L9: 4.5 | M9: 5.8 | N9: 4.14 | O9: 4 | P9: 56 | Q9: 2 / 3 / 2
A10: 777 | B10: Queen 2 | C10: 2018 | D10: MS | E10: Acheté 2400€ en fin d'année avec 10h de vol. Volé 13h avec, vendu suite gros vrac à 1900€ | F10: Révision 1 mai 2019 après 20 h de vol. Pour revente chez Ripair. | G10: 80/100 | H10: C | I10: 25.3 | J10: 3.75 | K10: 21.4 | L10: 4.44 | M10: 6.3 | N10: 4.6 | O10: 5.1 | P10: 73 | Q10: 2+1 / 4 / 3
A11: Gradient | B11: BI Golden 2 - 38 | C11: 2013 | D11: 38 | E11: Acheté à Fabien Pratviel qui avait fait une cinnquantaine de ploufs du matin avec. Chanagement des élélvateurs solo pour des bi neufs. | F11: Révision Déc 2018 après envrion 50 heures de vol. Jugée en très bon état, Reste plus de 80% de durée de vie.
A12: Supair | B12: Extralight | C12: 2016 | E12: Secours sellette Swing puis Supair Evolite | F12: Aéré, replié le 08/03/2020 Aéré, replié le 05/03/2023 | G12: Max 105
A13: Supair | B13: Montagne | C13: 2019 | E13: Secours avec conteneur ventral pour montagne | F13: Aéré, replié le 08/03/2020 Aéré et replié le 05/03/2023 | G13: Max 85
A14: Mcc Aviation | B14: Secours SOS Bi | C14: 2013 | D14: Max 200 kg | E14: N° Certification PS 037.0101 1354-32-05'11 Produit en avril 2013 Acheté à Thierry Struxiano Surfair en 2017. | F14: Aéré, replié le 03/05/2020 Lancé sous tyrolienne et replié le 15/03/2021 Aéré et replié le 05/03/2023. Les panneaux de fermeture du conteneur restaient adhérents au Pod. Réformé et remplacé par modèlme identique. | G14: 135-180 Max 200
A15: Supair | B15: Walibi Lite biplace | C15: 2017 | D15: ML | E15: Acheté d'occasion 400€ début 2018. N° série 2167.ML.11.28Dtae fab 30;11;2017 | F15: Contrôle tous les 2 ans Ok le 03/05/2020 Ok le 15/03/2021 | G15: Max 120
A16: Supair | B16: VIP2 - Passager biplace | C16: 2020 | E16: Acheté neuve à Surfair à 515 € en 07/2020 | G16: Max 120
A17: Kortel | B17: Kruyer 3 | C17: 2020 | D17: M | E17: Achetée neuve à Surfair le14/08/2020 à 288€TTC N° série 19197-KR-M-29
A18: Supair | B18: Casque School | C18: 2020 | D18: 56-62 | E18: Acheté neuf à Surfair pour 76€ le 14/08/2020
A19: Supair | B19: Ecarteur rigide | C19: 2020 | E19: Achetés neuf à Surfair pour 80 €TTC le 14/08/2020
A20: BGD | B20: Dual 41 | C20: 2018 | E20: Acheté à Mumu en octobre 2020 avec environ 140 vols en très très bon état. Révision chez jean-Marc en jenvier 2022, état général excellent, sauf certaines couleurs de tissus qui sont un peu plus poreuses (rouge). Porosité > 300 sec. Durée restante 70%
A21: Advance | B21: Sigma 11 | C21: 2022 | D21: 24 | E21: Achetée neuve à Surfair en sept 2022, 4070 euros, un sacré joli cadeau ! | F21: 2022 21h de vol. 2023 112 h de vol Révision 30/09/2023 chez Jean-Marc. Tout ok, sauf une suspente abimée (par frottement ?) qu'il a changé. | G21: 80/100 | H21: En C | I21: 23.6 | J21: 3.8 | K21: 20.1 | L21: 4.48 | M21: 6.01 | N21: 4.48 | O21: 4.45 | P21: 65 | Q21: 3/3/2
A22: MCC Aviation | B22: SOS micro BI | C22: 2023 | D22: Bi | E22: Neuf acheté chez Surfair 932 € SN 2855-32-0659 | G22: Max 210 kg
A23: Supair | B23: Casque Pilot cosmos | C23: 2023 | E23: Acheté neuf chez Surfair 115 €
A24: Niviuk | B24: Ikuma 3 P | C24: 2024 | D24: 24 | E24: Achetée neuve chez Surfair 3534 € (-23%) | F24: Révision chez Vairiféo le 20/05/2025 après un peu plus de 200 h de vol. Tout va bien. Calage fin 2025 à 340h, stab rallongé sinon ok Retour Colombie début mars, elle a 434h | G24: 75/95 | H24: En B
A25: Kortel | B25: Kuik 3 | C25: 2024 | D25: M | E25: Achetée neuve chez Surfair 1550 € (-11%)

Sheet Synthèse
A1: Année | C1: Nbre de vols | D1: Nbre d'heures | E1: Durée moy / vol | F1: Distance en cross | G1: Nbre de cross | H1: Dist moy par cross | I1: Durée moy / an (15 ans)
B2: TOTAL | C2: =SUM(C3:C28) -> 1574 | D2: =SUM(D3:D28) -> 1628.9828 | E2: =C2/D2 -> 0.96624717 | F2: =SUM(F3:F267) -> 8160.38 | G2: =SUM(G3:G28) -> 230 | H2: =F2/G2 -> 35.479913 | I2: =D2/15 -> 108.59885
A3: 96-98 | B3: Stages | C3: =SUM('Vols 96 au 01_06_2000'!A2:A74) -> 67 | D3: =SUM('Vols 96 au 01_06_2000'!N2:N74)/60 -> 18.241667
A4: 99 | B4: Astral 1 | C4: =SUM('Vols 96 au 01_06_2000'!A75:A174) -> 90 | D4: =SUM('Vols 96 au 01_06_2000'!N60:N174)/60 -> 49.25 | E4: =D4/C4 -> 0.54722222 | F4: =SUM('Vols 96 au 01_06_2000'!P71:P174) -> 68
A5: 2000 | B5: Epsilon 3-28 | C5: =SUM('Vols 96 au 01_06_2000'!A175:A224)+SUM('2000'!A2:A57) -> 106 | D5: =(SUM('2000'!K:K)+SUM('Vols 96 au 01_06_2000'!N175:N224))/60 -> 77.35 | E5: =D5/C5 -> 0.72971698 | F5: =SUM('2000'!M:M)+SUM('Vols 96 au 01_06_2000'!P175:P224) -> 349.58 | G5: =COUNTA('2000'!M:M)-1 -> 12 | H5: =F5/G5 -> 29.131667
A6: 2001 | B6: Quarx 1-M | C6: =SUM('2001'!A:A) -> 95 | D6: =SUM('2001'!K:K)/60 -> 66.15 | E6: =D6/C6 -> 0.69631579 | F6: =SUM('2001'!M:M) -> 223 | G6: =COUNTA('2001'!M:M)-1 -> 11 | H6: =F6/G6 -> 20.272727
A7: 2002 | B7: Quarx puis Sérak M | C7: =SUM('2002'!A:A) -> 47 | D7: =SUM('2002'!K:K)/60 -> 36.25 | E7: =D7/C7 -> 0.7712766 | F7: =SUM('2002'!L:L) -> 188 | G7: =COUNTA('2002'!L:L)-1 -> 9 | H7: =F7/G7 -> 20.888889
A8: 2003 | B8: Sérak | C8: =SUM('2003'!A:A) -> 48 | D8: =SUM('2003'!K:K)/60 -> 37.8 | E8: =D8/C8 -> 0.7875 | F8: =SUM('2003'!L:L) -> 282.5 | G8: =COUNTA('2003'!L:L)-1 -> 9 | H8: =F8/G8 -> 31.388889
A9: 2004 | B9: Sérak puis Aspen 1-26 | C9: =SUM('2004'!A:A) -> 38 | D9: =SUM('2004'!K:K)/60 -> 34.683333 | E9: =D9/C9 -> 0.9127193 | F9: =SUM('2004'!L:L) -> 217 | G9: =COUNTA('2004'!L:L)-1 -> 7 | H9: =F9/G9 -> 31
A10: 2005 | B10: Aspen 26 | C10: =SUM('2005'!A:A) -> 45 | D10: =SUM('2005'!K:K)/60 -> 32.816667 | E10: =D10/C10 -> 0.72925926 | F10: =SUM('2005'!L:L) -> 209 | G10: =COUNTA('2005'!L:L)-1 -> 5 | H10: =F10/G10 -> 41.8
A11: 2006 | B11: Aspen , Golden puis Stream | C11: =SUM('2006'!A:A) -> 34 | D11: =SUM('2006'!K:K)/60 -> 32.32 | E11: =D11/C11 -> 0.95058824 | F11: =SUM('2006'!L:L) -> 104 | G11: =COUNTA('2006'!L:L)-1 -> 3 | H11: =F11/G11 -> 34.666667
A12: 2007 | B12: Stream 26 | C12: =SUM('2007'!A:A) -> 28 | D12: =SUM('2007'!K:K)/60 -> 25.179444 | E12: =D12/C12 -> 0.89926587 | F12: =SUM('2007'!L:L) -> 139.5 | G12: =COUNTA('2007'!L:L)-1 -> 8 | H12: =F12/G12 -> 17.4375
A13: 2008 | B13: Stream 26 | C13: =SUM('2008'!A:A) -> 23 | D13: =SUM('2008'!K:K)/60 -> 26.433333 | E13: =D13/C13 -> 1.1492754 | F13: =SUM('2008'!L:L) -> 129.5 | G13: =COUNTA('2008'!L:L)-1 -> 5 | H13: =F13/G13 -> 25.9
A14: 2009 | B14: Stream 26 | C14: =SUM('2009'!A:A) -> 15 | D14: ='2009'!K18 -> 24.05 | E14: =D14/C14 -> 1.6033333 | F14: =SUM('2009'!L:L) -> 22.9 | G14: =COUNTA('2009'!L:L)-1 -> 1 | H14: =F14/G14 -> 22.9
A15: 2010 | B15: Stream 26 | C15: 1 | D15: 2
A16: ='2015'!A2 -> 5 ans sont passés, j'ai fait 3 saisons de planeurs, mais trop d'éléments me repoussent du VV. Je décide de ré essayer le parapente, à Arbas avec Surfair (Thierry et Richard), retour en pente école, nouveau premier grand vol, je n'ai pas perdu le fond, comme en vélo parait il, on oublie pas les fondamentaux... de là à dire que je vais vraiment m'y remettre .... Inch'Allah.
A17: Année | C17: Nbre de vols | D17: Nbre d'heures | E17: Durée moy / vol | F17: Distance en cross | G17: Nbre de cross | H17: Dist moy par cross
A18: 2015 | B18: Golden 4 26-Location | C18: 20 | D18: 15.5 | E18: =D18/C18 -> 0.775 | I18: Reprise en grande sérénité sous la houlette de Thierry et Richard.
A19: 2016 | B19: Golden 4 24 | C19: =SUM('2016'!A:A) -> 58 | D19: =SUM('2016'!N:N)/60 -> 59.266667 | E19: =D19/C19 -> 1.0218391 | F19: =SUM('2016'!P:P) -> 176 | G19: =COUNTA('2016'!P:P)-1 -> 7 | H19: =F19/G19 -> 25.142857 | I19: Peu à peu je (re)trouve de bonnes sensations malgré des météos pas très favorables. Entre autre je n'ai jamais eu de vraiment bonnes condictions à Arbas pour partir en cross. J'ai su prendre mon temps, pour accumuler des heures et de l'entrainement. Les apports du livre de David Eyraud sont importants, il faut continuer dans ce sens. Les derniers cross de St Lary et Val Louron ont été magnifiques. J'espère pourvoir très vite retrouver de telles conditions.
A20: 2017 | B20: Golden 4 24 puis Névada 2 light | C20: =SUM('2017'!A:A) -> 87 | D20: =SUM('2017'!L:L)/60 -> 100.6 | E20: =D20/C20 -> 1.1563218 | F20: =SUM('2017'!N:N) -> 255 | G20: =COUNTA('2017'!N:N)-1 -> 10 | H20: =F20/G20 -> 25.5
A21: 2018 | B21: Névada 2 24 light | C21: =SUM('2018'!A:A) -> 140 | D21: =SUM('2018'!N:N)/60 -> 129.06667 | E21: =D21/C21 -> 0.92190476 | F21: =SUM('2018'!P:P) -> 517 | G21: =COUNTA('2018'!P:P)-1 -> 14 | H21: =F21/G21 -> 36.928571 | I21: Année géniale, déplacements dans les Alpes, Maroc, Espagne, 1 compet au revard… Superrrr
A22: 2019 | B22: Névada 2 24 light | C22: =SUM('2019'!A:A) -> 77 | D22: =SUM('2019'!N:N)/60 -> 85.066667 | E22: =D22/C22 -> 1.1047619 | F22: =SUM('2019'!P:P) -> 451 | G22: =COUNTA('2019'!P:P)-1 -> 10 | H22: =F22/G22 -> 45.1 | I22: Année horibilis, en espérant que 2020 soit plus clémente et agréable
A23: 2020 | B23: Névada 2 24 light | C23: =SUM('2020'!A:A) -> 52 | D23: =SUM('2020'!N:N)/60 -> 82.716667 | E23: =D23/C23 -> 1.5907051 | F23: =SUM('2020'!P:P) -> 138 | G23: =COUNTA('2020'!P:P)-1 -> 4 | H23: =F23/G23 -> 34.5 | I23: Année du début du Covid et de ses limitations et autres confinements… Bref pas la super année pour voler.
A24: 2021 | B24: Névada 2 24 light | C24: =SUM('2021'!A:A) -> 54 | D24: =SUM('2021'!N:N)/60 -> 55.483333 | E24: =D24/C24 -> 1.0274691 | F24: =SUM('2021'!P:P) -> 78 | G24: =COUNTA('2021'!P:P)-1 -> 3 | H24: =F24/G24 -> 26 | I24: Encore une année de transition, que des vols à Arbas, mais la vie change, maison à Mancioux, arrivée de Natalia et Miguel en avril puis de Réjane en octobre. Pas de voyage… une année pauvre pour le parapente, riche pour notre vie.
A25: 2022 | B25: Névada 2 24 light | C25: =SUM('2022'!A:A) -> 55 | D25: =SUM('2022'!N:N)/60 -> 58.666667 | E25: =D25/C25 -> 1.0666667 | F25: =SUM('2022'!P:P) -> 181 | G25: =COUNTA('2022'!P:P)-1 -> 8 | H25: =F25/G25 -> 22.625 | I25: Beaucoup de travaux à la maison de Mancioux avec l'aménagement de l'appartement de Réjane. Je me suis bien rattrapé après l'été mais il a manqué de vols mémorables.
A26: 2023 | B26: Sigma 11 24 | C26: =SUM('2023'!A:A) -> 120 | D26: =SUM('2023'!N:N)/60 -> 153.83333 | E26: =D26/C26 -> 1.2819444 | F26: =SUM('2023'!P:P) -> 801.4 | G26: =COUNTA('2023'!P:P)-1 -> 24 | H26: =F26/G26 -> 33.391667 | I26: Enfin dégagé des travaux, j'étais fin près au début du printemps pour une grosse année …. Raté, météo pourri. Je décroche quand même un beau Arbas-Foix, un peu par hasard, 2 passage de la Garonne mais pas géniaux et par contre, le vol de l'année, 70 kms en triangle FAI au départ de Val Louron avec des plafs à plus de 4000. énooooorme. Le 7 décembre Réjane meurt, ça par contre c'est la grande douleur !
A27: 2024 | B27: Sigma 11 24 puis Ikuma 3P 3P 24 | C27: =SUM('2024'!A:A) -> 137 | D27: =SUM('2024'!N:N)/60 -> 162.70833 | E27: =D27/C27 -> 1.1876521 | F27: =SUM('2024'!P:P) -> 699 | G27: =COUNTA('2024'!P:P)-1 -> 18 | H27: =F27/G27 -> 38.833333 | I27: Un SIV avec Soaring en mai me montre une carence de retard de tempo sur les abatées. Je change donc de voile pour "sous traiter" ce défaut.
A28: 2025 | B28: Ikuma 3 P 24 | C28: =SUM('2025'!A:A) -> 137 | D28: =SUM('2025'!N:N)/60 -> 263.55 | E28: =D28/C28 -> 1.9237226 | F28: =SUM('2025'!P:P) -> 2931 | G28: =COUNTA('2025'!P:P)-1 -> 62 | H28: =F28/G28 -> 47.274194
A29: 2026 | B29: Ikuma 3 P 24

Sheet 2026
A1: Compt | B1: N° Vol | C1: Date | D1: Voile | E1: Région | F1: Déco | G1: Acc. | H1: Dén. | I1: Attéro | J1: Type de vol | K1: Météo | L1: A1 max | M1: Heure décollage (locale) | N1: Durée | O1: Durée cumulée | P1: Dist | Q1: Rmq
A2: 29 | B2: =1562+29 -> 1591 | C2: Janv. Fevr. | D2: Ikuma 3P - 24 | E2: Colombie | N2: =(94*60)+50 -> 5690 | O2: =N2/60 -> 94.833333 | P2: 1650
A3: 1 | B3: 1592 | C3: 46090 | D3: Ikuma 3P - 24 | E3: Pyrénées | F3: Planot | I3: Arbas | J3: Local | N3: 99 | O3: =O2+N3/60 -> 96.483333
A4: 1 | B4: 1593 | C4: 46094 | D4: Ikuma 3P - 24 | E4: Pyrénées | F4: Planot | I4: Aspect | J4: Cross | N4: 135 | O4: =O3+N4/60 -> 98.733333 | P4: 30
A5: 1 | B5: 1594 | C5: 46097 | D5: Ikuma 3P - 24 | E5: Pyrénées | F5: Planot | I5: Arbas | J5: Local | N5: 100 | O5: =O4+N5/60 -> 100.4
A6: 1 | B6: 1595 | C6: 46098 | D6: Ikuma 3P - 24 | E6: Pyrénées | F6: Planot | I6: Arbas | J6: Local | N6: 99 | O6: =O5+N6/60 -> 102.05
A7: 1 | B7: 1596 | C7: 46101 | D7: essai Alpina5 | E7: Pyrénées | F7: Planot | I7: Arbas | J7: Local | N7: 30 | O7: =O6+N7/60 -> 102.55
A8: 1 | B8: 1597 | C8: 46101 | D8: essai Alpina5 | E8: Pyrénées | F8: Planot | I8: Urau | J8: Local | N8: 82 | O8: =O7+N8/60 -> 103.91667
A9: 1 | B9: 1598 | C9: 46102 | D9: essai Alpina5 | E9: Pyrénées | F9: Planot | I9: Arbas | J9: Cross | N9: 240 | O9: =O8+N9/60 -> 107.91667 | P9: 50
A10: 1 | B10: 1599 | C10: 46104 | D10: Ikuma 3P - 24 | E10: Pyrénées | F10: Planot | I10: St Girons | J10: Cross | N10: 100 | O10: =O9+N10/60 -> 109.58333 | P10: 36
A11: 1 | B11: 1600 | C11: 46105 | D11: Ikuma 3P - 24 | E11: Pyrénées | F11: Planot | I11: Arbas | J11: Cross | N11: 188 | O11: =O10+N11/60 -> 112.71667 | P11: 31
A12: 1 | B12: 1601 | O12: =O11+N12/60 -> 112.71667

Sheet 2025
A1: Compt | B1: N° Vol | C1: Date | D1: Voile | E1: Région | F1: Déco | G1: Acc. | H1: Dén. | I1: Attéro | J1: Type de vol | K1: Météo | L1: A1 max | M1: Heure décollage (locale) | N1: Durée | O1: Durée cumulée | P1: Dist | Q1: Rmq
A2: 1 | B2: 1428 | C2: 45658 | D2: Ikuma 3P - 24 | E2: Pyrénées | F2: Cornudère | G2: Rando | H2: 400 | I2: Arbas | J2: Local | K2: Flux de sud, veille d'arrivée de perturb | L2: 3145 | M2: 0.54652778 | N2: 85 | O2: =N2/60 -> 1.4166667 | P2: 40
A3: 1 | B3: 1429 | C3: 45667 | D3: Ikuma 3P - 24 | E3: Colombie | F3: Piedechinche | J3: Cross | N3: 140 | O3: =O2+N3/60 -> 3.75 | P3: 27
A4: 1 | B4: 1430 | C4: 45668 | D4: Ikuma 3P - 24 | E4: Colombie | F4: Piedechinche | J4: Local | N4: 104 | O4: =O3+N4/60 -> 5.4833333
A5: 1 | B5: 1431 | C5: 45669 | D5: Ikuma 3P - 24 | E5: Colombie | F5: Piedechinche | J5: Cross | N5: 45 | O5: =O4+N5/60 -> 6.2333333 | P5: 56
A6: 1 | B6: 1432 | C6: 45670 | D6: Ikuma 3P - 24 | E6: Colombie | F6: Piedechinche | J6: Cross | N6: 198 | O6: =O5+N6/60 -> 9.5333333 | P6: 43
A7: 1 | B7: 1433 | C7: 45671 | D7: Ikuma 3P - 24 | E7: Colombie | F7: Piedechinche | J7: Cross | N7: 184 | O7: =O6+N7/60 -> 12.6 | P7: 98
A8: 1 | B8: 1434 | C8: 45672 | D8: Ikuma 3P - 24 | E8: Colombie | F8: Roldanillo | J8: Cross | N8: 310 | O8: =O7+N8/60 -> 17.766667 | P8: 85
A9: 1 | B9: 1435 | C9: 45673 | D9: Ikuma 3P - 24 | E9: Colombie | F9: Roldanillo | J9: Cross | N9: 287 | O9: =O8+N9/60 -> 22.55 | P9: 64
A10: 1 | B10: 1436 | C10: 45674 | D10: Ikuma 3P - 24 | E10: Colombie | F10: Roldanillo | J10: Cross | N10: 198 | O10: =O9+N10/60 -> 25.85 | P10: 114
A11: 1 | B11: 1437 | C11: 45675 | D11: Ikuma 3P - 24 | E11: Colombie | F11: Roldanillo | J11: Cross | N11: 348 | O11: =O10+N11/60 -> 31.65 | P11: 55
A12: 1 | B12: 1438 | C12: 45676 | D12: Ikuma 3P - 24 | E12: Colombie | F12: Roldanillo | J12: Cross | N12: 198 | O12: =O11+N12/60 -> 34.95 | P12: 65
A13: 1 | B13: 1439 | C13: 45677 | D13: Ikuma 3P - 24 | E13: Colombie | F13: Ansermanuevo | J13: Cross | N13: 266 | O13: =O12+N13/60 -> 39.383333 | P13: 50
A14: 1 | B14: 1440 | C14: 45678 | D14: Ikuma 3P - 24 | E14: Colombie | F14: Ansermanuevo | J14: Cross | N14: 175 | O14: =O13+N14/60 -> 42.3 | P14: 83
A15: 1 | B15: 1441 | C15: 45679 | D15: Ikuma 3P - 24 | E15: Colombie | F15: Ansermanuevo | J15: Local | N15: 305 | O15: =O14+N15/60 -> 47.383333
A16: 1 | B16: 1442 | C16: 45681 | D16: Ikuma 3P - 24 | E16: Colombie | F16: Piedechinche | J16: Local | N16: 109 | O16: =O15+N16/60 -> 49.2
A17: 1 | B17: 1443 | C17: 45682 | D17: Ikuma 3P - 24 | E17: Colombie | F17: Piedechinche | J17: Local | N17: 163 | O17: =O16+N17/60 -> 51.916667
A18: 1 | B18: 1444 | C18: 45683 | D18: Ikuma 3P - 24 | E18: Colombie | F18: Piedechinche | J18: Cross | N18: 50 | O18: =O17+N18/60 -> 52.75 | P18: 11
A19: 1 | B19: 1445 | C19: 45684 | D19: Ikuma 3P - 24 | E19: Colombie | F19: Roldanillo | J19: Cross | N19: 184 | O19: =O18+N19/60 -> 55.816667 | P19: 59
A20: 1 | B20: 1446 | C20: 45685 | D20: Ikuma 3P - 24 | E20: Colombie | F20: Ansermanuevo | J20: Cross | N20: 228 | O20: =O19+N20/60 -> 59.616667 | P20: 73
A21: 1 | B21: 1447 | C21: 45687 | D21: Ikuma 3P - 24 | E21: Colombie | F21: Jerico | J21: Cross | N21: 118 | O21: =O20+N21/60 -> 61.583333 | P21: 24
A22: 1 | B22: 1448 | C22: 45694 | D22: Ikuma 3P - 24 | E22: Colombie | F22: Ansermanuevo | J22: Cross | N22: 182 | O22: =O21+N22/60 -> 64.616667 | P22: 57
A23: 1 | B23: 1449 | C23: 45695 | D23: Ikuma 3P - 24 | E23: Colombie | F23: Ansermanuevo | J23: Cross | N23: 253 | O23: =O22+N23/60 -> 68.833333 | P23: 73
A24: 1 | B24: 1450 | C24: 45696 | D24: Ikuma 3P - 24 | E24: Colombie | F24: Ansermanuevo | J24: Cross | N24: 112 | O24: =O23+N24/60 -> 70.7 | P24: 30
A25: 1 | B25: 1451 | C25: 45697 | D25: Ikuma 3P - 24 | E25: Colombie | F25: Ansermanuevo | J25: Cross | N25: 127 | O25: =O24+N25/60 -> 72.816667 | P25: 30
A26: 1 | B26: 1452 | C26: 45698 | D26: Ikuma 3P - 24 | E26: Colombie | F26: Ansermanuevo | J26: Cross | N26: 211 | O26: =O25+N26/60 -> 76.333333 | P26: 58
A27: 1 | B27: 1453 | C27: 45700 | D27: Ikuma 3P - 24 | E27: Colombie | F27: Ansermanuevo | J27: Cross | N27: 265 | O27: =O26+N27/60 -> 80.75 | P27: 71
A28: 1 | B28: 1454 | C28: 45708 | D28: Ikuma 3P - 24 | E28: Pyrénées | F28: Planot | G28: Navette | I28: Arbas | J28: Cross | L28: 2700 | M28: 0.51388889 | N28: 115 | O28: =O27+N28/60 -> 82.666667 | P28: 32
A29: 1 | B29: 1455 | C29: 45711 | D29: Ikuma 3P - 24 | E29: Pyrénées | F29: Cornudère | G29: Rando | H29: 400 | I29: Arbas | J29: Cross | L29: 1800 | M29: 0.52777778 | N29: 178 | O29: =O28+N29/60 -> 85.633333 | P29: 35
A30: 1 | B30: 1456 | C30: 45716 | D30: Ikuma 3P - 24 | E30: Pyrénées | F30: Planot | G30: Navette | I30: Sengouagnet | J30: Cross | L30: 1700 | M30: 0.50416667 | N30: 51 | O30: =O29+N30/60 -> 86.483333 | P30: 10
A31: 1 | B31: 1457 | C31: 45717 | D31: Ikuma 3P - 24 | E31: Pyrénées | F31: Planot | G31: Navette | I31: Arbas | J31: Local | N31: 21 | O31: =O30+N31/60 -> 86.833333 | Q31: Essai sellette Advance ligtness4 de Jeanseb. Pas assez amorti, trop coucvhé
A32: 1 | B32: 1458 | C32: 45717 | D32: Ikuma 3P - 24 | E32: Pyrénées | F32: Cier de Rivière | G32: Rando | H32: 250 | I32: Cier de rivière | J32: Local | N32: 65 | O32: =O31+N32/60 -> 87.916667
A33: 1 | B33: 1459 | C33: 45719 | D33: Ikuma 3P - 24 | E33: Pyrénées | F33: Planot | G33: Rando | H33: 500 | I33: Arbas | J33: Local | N33: 21 | O33: =O32+N33/60 -> 88.266667
A34: 1 | B34: 1460 | C34: 45720 | D34: Ikuma 3P - 24 | E34: Pyrénées | F34: Planot | G34: Navette | I34: Arbas | J34: Local | N34: 123 | O34: =O33+N34/60 -> 90.316667
A35: 1 | B35: 1461 | C35: 45721 | D35: Ikuma 3P - 24 | E35: Pyrénées | F35: Planot | G35: Navette | I35: Arbas | J35: Local | M35: 0.47777778 | N35: 180 | O35: =O34+N35/60 -> 93.316667
A36: 1 | B36: 1462 | C36: 45734 | D36: Ikuma 3P - 24 | E36: Pyrénées | F36: Planot | G36: Navette | I36: Bize | J36: Cross | L36: 1644 | M36: 0.51527778 | N36: 99 | O36: =O35+N36/60 -> 94.966667 | P36: 36
A37: 1 | B37: 1463 | C37: 45746 | D37: Ikuma 3P - 24 | E37: Pyrénées | F37: Planot | J37: Local | N37: 97 | O37: =O36+N37/60 -> 96.583333
A38: 1 | B38: 1464 | C38: 45747 | D38: Ikuma 3P - 24 | E38: Pyrénées | F38: Planot | J38: Local | N38: 50 | O38: =O37+N38/60 -> 97.416667
A39: 1 | B39: 1465 | C39: 45752 | D39: Ikuma 3P - 24 | E39: Pyrénées | F39: Cier de Rivière | G39: Rando | H39: 200 | J39: Local | N39: 40 | O39: =O38+N39/60 -> 98.083333
A40: 1 | B40: 1466 | C40: 45753 | D40: Ikuma 3P - 24 | E40: Pyrénées | F40: Cier de Rivière | G40: Rando | H40: 250 | J40: Local | N40: 52 | O40: =O39+N40/60 -> 98.95
A41: 1 | B41: 1467 | C41: 45754 | D41: Ikuma 3P - 24 | E41: Pyrénées | F41: Planot | G41: Navette | I41: Arbas | J41: Local | N41: 131 | O41: =O40+N41/60 -> 101.13333
A42: 1 | B42: 1468 | C42: 45755 | D42: Ikuma 3P - 24 | E42: Pyrénées | F42: Planot | G42: Rando | H42: 700 | I42: Cornu | J42: Local | N42: 68 | O42: =O41+N42/60 -> 102.26667 | Q42: Monté avec Jean Seb, début de vol un peu trop tonique, posé à Cornu histoir de challenge
A43: 1 | B43: 1469 | C43: 45755 | D43: Ikuma 3P - 24 | E43: Pyrénées | F43: Cornudère | G43: vol | I43: Arbas | J43: Cross | N43: 170 | O43: =O42+N43/60 -> 105.1 | P43: 47 | Q43: Voyant que les plafs étaient nettement montés, A/RE Pic du Gar - Estelas en compagnie de David Epinat et Sammy Galego
A44: 1 | B44: 1470 | C44: 45756 | D44: Ikuma 3P - 24 | E44: Pyrénées | F44: Planot | G44: Navette | I44: Moulis | J44: Cross | N44: 119 | O44: =O43+N44/60 -> 107.08333 | P44: 15 | Q44: Après un passage par la Husse et le constat que l'ouest est bien là, je pars vers l'Est. Bloqué à Herbes blanches je reviens sur mes pas, Piscatelle, Mountagnat, Hérégades et j'arrive enfin à passer au nord de l'Estelas. Ensuite plus compliqué, je ne trove plus grand chose, trop de vent, pas d'aide des oiseaux....
A45: 1 | B45: 1471 | C45: 45757 | D45: Ikuma 3P - 24 | E45: Pyrénées | F45: Planot | G45: Navette | I45: Aspect | J45: Cross | N45: 198 | O45: =O44+N45/60 -> 110.38333 | P45: 35 | Q45: cette fois c'est de l'Est qui souffle, au coldu Hoo, je n'arrive pas à m'extraire, du coup je tente le retour.Je bloque au Picon en face Nord Ouest de Paloumère. Complétement arrété. Je décide d'aller me poser vers Aspect
A46: 1 | B46: 1472 | C46: 45759 | D46: Ikuma 3P - 24 | E46: Pyrénées | F46: Planot | G46: Navette | J46: Local | N46: 25 | O46: =O45+N46/60 -> 110.8
A47: 1 | B47: 1473 | C47: 45759 | D47: Ikuma 3P - 24 | E47: Pyrénées | F47: Planot | G47: Navette | J47: Local | N47: 100 | O47: =O46+N47/60 -> 112.46667
A48: 1 | B48: 1474 | C48: 45765 | D48: Ikuma 3P - 24 | E48: Pyrénées | F48: Planot | G48: Navette | I48: Saléchan | J48: Cross | N48: 254 | O48: =O47+N48/60 -> 116.7 | P48: 64 | Q48: Du vent dans tous les sens, brises en basse couche, de l'ENE jusqu'à 1500 environ et du SSE plus haut.
A49: 1 | B49: 1475 | C49: 45776 | D49: Ikuma 3P - 24 | E49: Pyrénées | F49: Planot | G49: Navette | I49: Escarchein | J49: Cross | N49: 150 | O49: =O48+N49/60 -> 119.2 | Q49: Dans un flux d'Est, en compagnie de Thierry Annah, Théo et Couzinier, dommage que je rate le vol avec Thierry qui va vers Pau 120kms. Retour avec David Epinat et làa je rate le retour enb voulant le suivre face sud de Cornu. Remontée à pieds à Herran
A50: 1 | B50: 1476 | C50: 45776 | D50: Ikuma 3P - 24 | E50: Pyrénées | F50: Michel Bellaygues | G50: Rando | H50: 450 | I50: Arbas | J50: Local | N50: 15 | O50: =O49+N50/60 -> 119.45 | Q50: Etrange vol ou ça monte tout le temps dans un fort flux de NE.
A51: 1 | B51: 1477 | C51: 45778 | D51: Ikuma 3P - 24 | E51: Pyrénées | F51: Planot | G51: Navette | I51: Arbas | J51: Local | N51: 35 | O51: =O50+N51/60 -> 120.03333
A52: 1 | B52: 1478 | C52: 45778 | D52: Dual | E52: Pyrénées | F52: Planot | G52: Navette | I52: Arbas | J52: Local | N52: 80 | O52: =O51+N52/60 -> 121.36667 | Q52: re^rise Biplace avec Quenfin
A53: 1 | B53: 1479 | C53: 45780 | D53: Ikuma 3P - 24 | E53: Pyrénées | F53: Planot | G53: Navette | I53: Arbas | J53: Local | N53: 56 | O53: =O52+N53/60 -> 122.3
A54: 1 | B54: 1480 | C54: 45784 | D54: Ikuma 3P - 24 | E54: Pyrénées | F54: Planot | G54: Navette | I54: Ribon | J54: Cross | N54: 162 | O54: =O53+N54/60 -> 125 | P54: 52 | Q54: A^rès un début difficile, jolie cross en compganie de Jean Marc
A55: 1 | B55: 1481 | C55: 45785 | D55: Ikuma 3P - 24 | E55: Pyrénées | F55: Planot | G55: Navette | I55: Suaveterre | J55: Cross | N55: 70 | O55: =O54+N55/60 -> 126.16667 | P55: 20 | Q55: cette fois on va vers l'Ouest plutot sympas, dommage de ne pas avoir réussi à porsuivre
A56: 1 | B56: 1482 | C56: 45786 | D56: Sigma 12 DLS | E56: Pyrénées | F56: Planot | G56: Navette | I56: Arbas | J56: Local | N56: 118 | O56: =O55+N56/60 -> 128.13333 | Q56: essaie de la Sigma 12 DLS taille 22 de Thierry. Probablement une très bonne voile, mais ej suis 3 kg au dessus du PTV Max et l'aile est trop puissante, à l'image d'un biplace
A57: 1 | B57: 1483 | C57: 45790 | D57: Ikuma 3P - 24 | E57: Centre | F57: Puncho d'Agast | G57: Navette | I57: Millau | J57: Local | N57: 62 | O57: =O56+N57/60 -> 129.16667
A58: 1 | B58: 1484 | C58: 45792 | D58: Ikuma 3P - 24 | E58: Centre | F58: Douelle | G58: Navette | I58: Douelle | J58: Local | N58: 6 | O58: =O57+N58/60 -> 129.26667
A59: 1 | B59: 1485 | C59: 45793 | D59: Ikuma 3P - 24 | E59: Centre | F59: Douelle | G59: Navette | I59: Septfonds | J59: Cross | N59: 100 | O59: =O58+N59/60 -> 130.93333 | P59: 40
A60: 1 | B60: 1486 | C60: 45794 | D60: Ikuma 3P - 24 | E60: Centre | F60: Puncho d'Agast | G60: Navette | I60: Millau | J60: Local | N60: 46 | O60: =O59+N60/60 -> 131.7
A61: 1 | B61: 1487 | C61: 45794 | D61: Ikuma 3P - 24 | E61: Centre | F61: Brunas | G61: Navette | I61: Brunas | J61: Local | N61: 17 | O61: =O60+N61/60 -> 131.98333
A62: 1 | B62: 1488 | C62: 45795 | D62: Ikuma 3P - 24 | E62: Centre | F62: Puncho d'Agast | G62: Navette | I62: Aguessac | J62: Cross | N62: 77 | O62: =O61+N62/60 -> 133.26667 | P62: 14
A63: 1 | B63: 1489 | C63: 45798 | D63: Ikuma 3P - 24 | E63: Pyrénées | F63: Cier de Rivière | G63: Rando | H63: 220 | I63: Cier de rivière | J63: Local | N63: 7 | O63: =O62+N63/60 -> 133.38333
A64: 1 | B64: 1490 | C64: 45801 | D64: Ikuma 3P - 24 | E64: Pyrénées | F64: Planot | G64: Navette | I64: Arbas | J64: Cross | N64: 170 | O64: =O63+N64/60 -> 136.21667 | P64: 31
A65: 1 | B65: 1491 | C65: 45802 | D65: Dual | E65: Pyrénées | F65: Planot | G65: Navette | I65: Arbas | J65: Local | N65: 10 | O65: =O64+N65/60 -> 136.38333
A66: 1 | B66: 1492 | C66: 45802 | D66: Dual | E66: Pyrénées | F66: Planot | G66: Navette | I66: Arbas | J66: Local | N66: 13 | O66: =O65+N66/60 -> 136.6
A67: 1 | B67: 1493 | C67: 45802 | D67: Dual | E67: Pyrénées | F67: Planot | G67: Rando | H67: 400 | I67: Arbas | J67: Local | N67: 14 | O67: =O66+N67/60 -> 136.83333
A68: 1 | B68: 1494 | C68: 45806 | D68: Ikuma 3P - 24 | E68: Pyrénées | F68: Ager | G68: Navette | I68: Ager | J68: Cross | L68: 2283 | M68: 0.5 | N68: 185 | O68: =O67+N68/60 -> 139.91667 | P68: 56
A69: 1 | B69: 1495 | C69: 45807 | D69: Ikuma 3P - 24 | E69: Pyrénées | F69: Ager | G69: Navette | I69: Benavent de la Conqua | J69: Cross | L69: 3134 | M69: 0.53611111 | N69: 220 | O69: =O68+N69/60 -> 143.58333 | P69: 60 | Q69: Beau cross malgré une lon,gue attente sur l'ouest de la barre, ensuite très bien par Tremp.
A70: 1 | B70: 1496 | C70: 45808 | D70: Ikuma 3P - 24 | E70: Pyrénées | F70: Planot | G70: Navette | I70: Arbas | J70: Cross | L70: 1743 | M70: 0.62916667 | N70: 173 | O70: =O69+N70/60 -> 146.46667 | Q70: Enfin des vrais belles conditions, l'impression de pouvoir aller partout, génial.
A71: 1 | B71: 1497 | C71: 45813 | D71: Ikuma 3P - 24 | E71: Pyrénées | F71: Tuchan | G71: Rando | H71: 440 | I71: Tuchan | J71: Local | M71: 0.58680556 | N71: 11 | O71: =O70+N71/60 -> 146.65 | Q71: Début de ma balade vers les Alpes du sud. Du vent partout d'annoncé sauf en Languedoc, j'en profite pour découvrir ce site;
A72: 1 | B72: 1498 | C72: 45814 | D72: Ikuma 3P - 24 | E72: Hérault/Gard | F72: La Séranne | G72: Navette | I72: Brissac | J72: Cross | M72: 0.54166667 | N72: 145 | O72: =O71+N72/60 -> 149.06667 | P72: 36 | Q72: Décuverte de la Séranne, magnifique, vu vers la mer et les Cévennes, dommage qu'il y ait eu le nuage des fumées des incendies du Canada.
A73: 1 | B73: 1499 | C73: 45815 | D73: Ikuma 3P - 24 | E73: Hérault/Gard | F73: Mont bouquet | G73: Navette | I73: Barjac | J73: Compete | L73: 1100 | M73: 0.57847222 | N73: 113 | O73: =O72+N73/60 -> 150.95 | P73: 30 | Q73: Enfin au départ d'un compété ! Parti dans les derniers, après é ou 3 remontées quasi du sol, je finis 3ème de la manche, évidemment sans faire exprès … mon heure de gloire !
A74: 1 | B74: 1500 | C74: 45816 | D74: Ikuma 3P - 24 | E74: Hérault/Gard | F74: Saint Sébastien | G74: Navette | I74: Saint Sébastien | J74: Compete | N74: 5 | O74: =O73+N74/60 -> 151.03333 | Q74: 1ere tentative ratée
A75: 1 | B75: 1501 | C75: 45816 | D75: Ikuma 3P - 24 | E75: Hérault/Gard | F75: Saint Sébastien | G75: Navette | I75: St André de Cruzières | M75: 0.52777778 | N75: 50 | O75: =O74+N75/60 -> 151.86667 | Q75: Cette fois je réussi à m'xtraire, mais il y a trop de vent de nord pour moi, et après 2 thermiques j'échoue lamentablement. Retiur au sol et à la réalité du classeement
A76: 1 | B76: 1502 | C76: 45819 | D76: Ikuma 3P - 24 | E76: Alpes du sud | F76: Banon | G76: Rando | H76: 400 | I76: L'Hospitalet | J76: Cross | L76: 1600 | M76: 0.52777778 | N76: 70 | O76: =O75+N76/60 -> 153.03333 | Q76: Découverte deBanon, enfin après toutes ces années ou on est venu au Bleuet ! Beau site, toujours le nuage de fumées canadienne, dommage que je rate l'extraction en dessous de "Le Contras". J'aurai du partir au vent.
A77: 1 | B77: 1503 | C77: 45820 | D77: Ikuma 3P - 24 | E77: Alpes du sud | F77: St André les Alpes | G77: Navette | I77: St André les Alpes | J77: Cross | L77: 3457 | M77: 0.46805556 | N77: 297 | O77: =O76+N77/60 -> 157.98333 | P77: 108 | Q77: Mon graal à moi enfin réussi ! L'extraction du Cheval Blanc à l'aller à été épique, idem au Trauma sous l'Estrop, là carrément en mode "survie", la Blanche A/R c'est vrimenty donné, ensuite j'ai pris l'option retour par le Cheval Blanc et j'ai bien fait même si je suis arrivé assez bas, mais ensuite c'était du gateau.
A78: 1 | B78: 1504 | C78: 45822 | D78: Ikuma 3P - 24 | E78: Alpes du sud | F78: St André les Alpes | G78: Navette | I78: St André les Alpes | J78: Local | L78: 3000 | M78: 0.54166667 | N78: 91 | O78: =O77+N78/60 -> 159.5 | Q78: Dés l'attete au déco, les feux oranges d'allument, pas de brise, un petit dust, après le déco, conditiosn merdiques à cause du SudOuest, je réussi enfin à m'extraire devant le déco dans un thermique violent, une parapentiste dans les arbres suite fermeture et retour pente et enfin du coté de Lambruisse, Une autre parapentiste qui dit avoir eu la peur de sa vie, du coup je décide de rentrer me poser, mais j'ai failli de pas raccrocher aux antennes, vraipent des conditions pourries;
A79: 1 | B79: 1505 | C79: 45824 | D79: Ikuma 3P - 24 | E79: Alpes du sud | F79: Ceillac | G79: Rando | H79: 250 | I79: Ceillac | J79: Local | L79: 4087 | M79: 0.46805556 | N79: 168 | O79: =O78+N79/60 -> 162.3 | Q79: Sécr tour de bocal perché à des hauteurs et au dessus de reliefs dont je n'ai absolument pas l'habitude. Dommage ressenti gaché par des remarques des locaux comme quoi j'étais "imprévisible" dans la grappe devant le déco.
A80: 1 | B80: 1506 | C80: 45826 | D80: Ikuma 3P - 24 | E80: Alpes du sud | F80: Mt Guillaume | G80: Rando | H80: 550 | I80: Mt Guillaume | J80: Local | N80: 11 | O80: =O79+N80/60 -> 162.48333 | Q80: Quel beau coin. Je décolle probablement un peu tôt, ey je b'arrive pas à m'extraire. Pas grave, ensuite la brise de Durance est tellement forte que j'aurai eu du mal à me poser.
A81: 1 | B81: 1507 | C81: 45827 | D81: Ikuma 3P - 24 | E81: Alpes du sud | F81: Vallouise - Puy Aillaud | G81: Rando | H81: 600 | I81: Vallouise | J81: Cross | L81: 3621 | M81: 0.48333333 | N81: 269 | O81: =O80+N81/60 -> 166.96667 | P81: 62 | Q81: En gros le parc ours d'une manche classique à Vallouise puisque j'étais là pour ça, sacrés passage au dessus des reliefs, impressionnants, contré par la brise de Durance à plus de 2000, le passage du coté de St Crépin a été très dur.
A82: 1 | B82: 1508 | C82: 45828 | D82: Ikuma 3P - 24 | E82: Alpes du sud | F82: Vallouise - Puy Aillaud | G82: Rando | H82: 600 | I82: Vallouise | J82: Local | N82: 20 | O82: =O81+N82/60 -> 167.3 | Q82: Impossible de m'extraire. Pas grave, la météo du jour ne s'annonce pas super. La compete du xe à suivre est annulée.
A83: 1 | B83: 1509 | C83: 45829 | D83: Ikuma 3P - 24 | E83: Aveyron | F83: La Puncho | G83: Navette | I83: Millau | J83: Local | N83: 7 | O83: =O82+N83/60 -> 167.41667 | Q83: Impossible de trouver quoi que ce soit ! Etonnant
A84: 1 | B84: 1510 | C84: 45829 | D84: Ikuma 3P - 24 | E84: Aveyron | F84: La Puncho | G84: Navette | I84: Rivière sur Tarn | J84: Cross | L84: 3166 | M84: 0.58541667 | N84: 315 | O84: =O83+N84/60 -> 172.66667 | P84: 96 | Q84: Cette fois je sord facilement et on part pour un A/R à Mende. Il me manque 8 kms pour boucler, mais vraiment pas grave, le retour face au sud-ouest à été épîque. 2h l'aller, 3 h le retour.
A85: 1 | B85: 1511 | C85: 45830 | D85: Ikuma 3P - 24 | E85: Aveyron | F85: La Puncho | G85: Rando | H85: 550 | I85: Millau | J85: Cross | L85: 1900 | M85: 0.60416667 | N85: 130 | O85: =O84+N85/60 -> 174.83333 | P85: 25 | Q85: 25 kms en 2 h quand les meilleurs du championnat de France qui a lieu en même temps, font 60 ou 70 kms. A part le &er thermique, je n'ai plus réussi à sortir des gorges.
A86: 1 | B86: 1512 | C86: 45835 | D86: Ikuma 3P - 24 | E86: Pyrénées | F86: Planot | G86: Navette | I86: Arbas | J86: Local | N86: 89 | O86: =O85+N86/60 -> 176.31667
A87: 1 | B87: 1513 | C87: 45836 | D87: Ikuma 3P - 24 | E87: Pyrénées | F87: Planot | G87: Navette | I87: Arbas | J87: Cross | L87: 2041 | M87: 0.53888889 | N87: 267 | O87: =O86+N87/60 -> 180.76667 | P87: 65 | Q87: Un sacré triangle FAI, Col du Ho - Cazavet - Figarol. Très très beau
A88: 1 | B88: 1514 | C88: 45837 | D88: Ikuma 3P - 24 | E88: Pyrénées | F88: Planot | G88: Navette | I88: Arbas | J88: Cross | L88: 2280 | M88: 0.52152778 | N88: 448 | O88: =O87+N88/60 -> 188.23333 | P88: 90 | Q88: Un autre sacré bea vol, risque de rentrer dans mon top 5, avec Vincent Daoulas, on va à l'entrée de la Garonne et retour avec une pointe à Herbe sblanche. Pas de afute tactique, en sécu tout le temps dont le retour par Mt de Galié. Une référence.
A89: 1 | B89: 1515 | C89: 45838 | D89: Ikuma 3P - 24 | E89: Pyrénées | F89: Planot | G89: Navette | I89: Arbas | J89: Cross | L89: 2378 | M89: 0.50694444 | N89: 242 | O89: =O88+N89/60 -> 192.26667 | P89: 45 | Q89: Pas la même chanson, pourtant sur le même parcours, mais j'échoue au retour sur la traverséée de la Garonne, La météo prétique n'a pas rjoint lé météo théorique.
A90: 1 | B90: 1516 | C90: 45839 | D90: Ikuma 3P - 24 | E90: Pyrénées | F90: Planot | G90: Navette | I90: Arbas | J90: Cross | L90: 2472 | M90: 0.5375 | N90: 147 | O90: =O89+N90/60 -> 194.71667 | P90: 27 | Q90: Une météo très limite border line. Avec de 'est, un passage étonnant ou on passe de 2200 à 2500 en ligen droite sur la crête de Piscat à herbes blanches. Vol avec Vincent Coburn, très agréable de voler avec lui.
A91: 1 | B91: 1517 | C91: 45842 | D91: Ikuma 3P - 24 | E91: Pyrénées | F91: Planot | G91: Navette | I91: Arbas | J91: Local | M91: 0.53194444 | N91: 44 | O91: =O90+N91/60 -> 195.45
A92: 1 | B92: 1518 | C92: 45849 | D92: Ikuma 3P - 24 | E92: Pyrénées | F92: Planot | G92: Navette | I92: Arbas | J92: Cross | L92: 2160 | M92: 0.51111111 | N92: 174 | O92: =O91+N92/60 -> 198.35
A93: 1 | B93: 1519 | C93: 45851 | D93: Ikuma 3P - 24 | E93: Pyrénées | F93: Planot | G93: Navette | I93: Arbas | J93: Local | M93: 0.40694444 | N93: 16 | O93: =O92+N93/60 -> 198.61667 | Q93: Vol du matin pour que Quentin test une sellette
A94: 1 | B94: 1520 | C94: 45851 | D94: Ikuma 3P - 24 | E94: Pyrénées | F94: Planot | G94: Navette | I94: Arbas | M94: 0.45972222 | N94: 60 | O94: =O93+N94/60 -> 199.61667 | Q94: idem
A95: 1 | B95: 1521 | C95: 45851 | D95: Ikuma 3P - 24 | E95: Pyrénées | F95: Planot | G95: Navette | I95: Arbas | L95: 1628 | M95: 0.56458333 | N95: 110 | O95: =O94+N95/60 -> 201.45 | Q95: Pas beaucoup de plaf et une tendance NO, mais je réussi quand même à aller à Cazavet.
A96: 1 | B96: 1522 | C96: 45854 | D96: Ikuma 3P - 24 | E96: Pyrénées | F96: Planot | G96: Navette | I96: Arbas | J96: Local | N96: 117 | O96: =O95+N96/60 -> 203.4 | Q96: Essai Niviuk Artik R. Ca vole sacrément bien un bon cran au dessus de la mienne, mais c'est raide, l'impression d'être assis sur un banc en bois et on a pas du tout envie de la prendre sur la tête…
A97: 1 | B97: 1523 | C97: 45855 | D97: Ikuma 3P - 24 | E97: Pyrénées | F97: Planot | G97: Navette | I97: Arbas | J97: Local | N97: 100 | O97: =O96+N97/60 -> 205.06667
A98: 1 | B98: 1524 | C98: 45860 | D98: Ikuma 3P - 24 | E98: Pyrénées | F98: Planot | G98: Rando | H98: 700 | I98: Izault de l'Hotel | J98: Cross | L98: 1530 | M98: 0.47916667 | N98: 45 | O98: =O97+N98/60 -> 205.81667 | Q98: Je pars vraiment bas, pour voir, je rate l'ascendance du coté du Puech, et ensuite c'est une lente dégrngolade
A99: 2 | B99: 1525 | C99: 45871 | D99: Ikuma 3P - 24 | E99: Pyrénées | F99: Cier de Rivière | G99: Rando | H99: 440 | I99: Cier de rivière | J99: Local | N99: 38 | O99: =O98+N99/60 -> 206.45 | Q99: 2 vols un peu identque, trop de vent pour moi.
A100: 1 | B100: 1526 | C100: 45872 | D100: Ikuma 3P - 24 | E100: Pyrénées | F100: Planot | G100: Navette | I100: Arbas | J100: Cross | L100: 1844 | M100: 0.53472222 | N100: 160 | O100: =O99+N100/60 -> 209.11667 | Q100: C'était bien parti avec un A/R au Gar, mais au retour je bloque aux Hérégades et je n'arrive pas à continuer vers l'Est. Dommage.
...

Sheet 2024
A1: Compt | B1: N° Vol | C1: Date | D1: Voile | E1: Région | F1: Déco | G1: Acc. | H1: Dén. | I1: Attéro | J1: Type de vol | K1: Météo | L1: A1 max | M1: Heure décollage (locale) | N1: Durée | O1: Durée cumulée | P1: Dist | Q1: Rmq
A2: 1 | B2: 1292 | C2: 45295 | D2: Névada 2 -24 | E2: Pyrénées | F2: Planot | G2: Rando | H2: 700 | I2: Arbas | J2: Local | K2: Léger flux d'Ouest | M2: 0.54305556 | N2: 25 | O2: =25/60 -> 0.41666667
A3: 1 | B3: 1293 | C3: 45296 | D3: Névada 2 -24 | E3: Pyrénées | F3: Cornudère | G3: Rando | H3: 400 | I3: Arbas | J3: Cross | L3: 1825 | M3: 0.53472222 | N3: 118 | O3: =O2+N3/60 -> 2.3833333 | P3: 24
A4: 1 | C4: 45306 | D4: Névada 2 -24 | E4: Mancioux | O4: =O3+N4/60 -> 2.3833333 | Q4: Gonflage à Paris les Près 1h envron
A5: 1 | B5: 1294 | C5: 45301 | D5: Névada 2 -24 | E5: Pyrénées | F5: Roquefort / Garonne | H5: 220 | I5: Roquefort / Garonne | J5: Local | M5: 0.675 | N5: 4 | O5: =O4+N5/60 -> 2.45
A6: 1 | B6: 1295 | C6: 45304 | D6: Sigma 11-24 | E6: Pyrénées | F6: Le relais | G6: Navette | I6: Arbas | J6: Local | M6: 0.54513889 | N6: 6 | O6: =O5+N6/60 -> 2.55
A7: 1 | B7: 1296 | C7: 45304 | D7: Sigma 11-24 | E7: Pyrénées | F7: Planot | G7: Rando | H7: 700 | I7: Arbas | J7: Local | M7: 0.58263889 | N7: 15 | O7: =O6+N7/60 -> 2.8
A8: 1 | B8: 1297 | C8: 45312 | D8: Sigma 11-24 | E8: Pyrénées | F8: Cornudère | G8: Rando | H8: 400 | I8: Arbas | J8: Cross | K8: Léger SO | L8: 1785 | M8: 0.56458333 | N8: 120 | O8: =O7+N8/60 -> 4.8 | P8: 20 | Q8: Le vol est super chouette, mais …. Aujourd'hui j'ai merdé. Déco sud de Cornudere, je me fais arracher, un peu traîner au sol, la voile fini dans la keke. C'était craignos, absolument pas maîtrisé, je sais à peu près pourquoi, mais ... passons. Je mets la voile en boule, je vais au deco Sud Ouest, grand Mitch et Jean Marc m'aident à remettre de l'ordre, ils me demandent si j'ai debouclé les cuissardes et ventral, Ras, je gonfle, je décolle, je vole 2h avec grand plaisir et, à l'atterro, je constate que j'aurai très bien pu faire secours en automatique, une des aiguilles de la poignée est défaite. Voir photo. La prochaine fois que ça m'arrive, je reprends tout à zéro, prévol et tout le reste !
A9: 1 | B9: 1298 | C9: 45315 | D9: Névada 2 -24 | E9: Pyrénées | F9: Cornudère | G9: Rando | H9: 400 | I9: Arbas | J9: Local | L9: 1550 | M9: 0.58611111 | N9: 54 | O9: =O8+N9/60 -> 5.7
A10: 1 | B10: 1299 | C10: 45318 | D10: Sigma 11-24 | E10: Pyrénées | F10: Superbagnères | G10: Télécabine | I10: Luchon | J10: Local | M10: 0.45694444 | N10: 16 | O10: =O9+N10/60 -> 5.9666667
A11: 1 | B11: 1300 | C11: 45318 | D11: Sigma 11-24 | E11: Pyrénées | F11: Superbagnères | G11: Télécabine | I11: Luchon | J11: Local | M11: 0.51041667 | N11: 18 | O11: =O10+N11/60 -> 6.2666667
A12: 1 | B12: 1301 | C12: 45318 | D12: Sigma 11-24 | E12: Pyrénées | F12: Superbagnères | G12: Télécabine | I12: Luchon | J12: Local | M12: 0.55902778 | N12: 20 | O12: =O11+N12/60 -> 6.6
A13: 1 | B13: 1302 | C13: 45319 | D13: Névada 2 -24 | E13: Pyrénées | F13: Cornudère | G13: Rando | H13: 400 | I13: Bas de cornu sud | J13: Local | L13: 1800 | M13: 0.53958333 | N13: 51 | O13: =O12+N13/60 -> 7.45
A14: 1 | B14: 1303 | C14: 45319 | D14: Névada 2 -24 | E14: Pyrénées | F14: Michel Bellaygues | G14: Rando | H14: 350 | I14: Arbas | J14: Local | M14: 0.62916667 | N14: 10 | O14: =O13+N14/60 -> 7.6166667
A15: 1 | B15: 1304 | C15: 45336 | D15: Sigma 11-24 | E15: Pyrénées | F15: Cornudère | G15: Rando | H15: 400 | I15: Arbas | J15: Cross | L15: 1750 | M15: 0.525 | N15: 98 | O15: =O14+N15/60 -> 9.25 | P15: 24 | Q15: Des bonnes sensations dans de bons thermiques, m'anènent jusqu'à l'ouest de Paloumère, puis par les faces sud jusqu'à Herbzq blanches, puis relais et attéro. J'aurai peut-être du patienter à la BA110, plus tard, certains on pu en sortir pour aller à l'Estelas. Mais pas grave, vol parfait !
A16: 1 | B16: 1305 | C16: 45343 | D16: Sigma 11-24 | E16: Pyrénées | F16: Planot | G16: Rando | H16: 700 | I16: Arbas | M16: 0.51666667 | N16: 66 | O16: =O15+N16/60 -> 10.35 | Q16: Essai de la sellette de Vincent Daoulas, une Supair Strike 2. pour une fois j'ai réussi à rentrer dedans assez facilement. Probablement pas très bien régler, mais le problème c'est surtout le manque d'amorti qui je suppose est du à la faible hauteur plateau/maillons. D'ailleurs s'en est génant pour la hauteur des mains pour les commandes. Je me retrouve à piloter mains très basses, coudes très pliés, et donc fatigant. Je la rend à Vincent sans regret ni envie d'achat.
A17: 1 | B17: 1306 | C17: 45351 | D17: Sigma 11-24 | E17: Pyrénées | F17: Planot | G17: Navette | I17: Arbas | J17: Cross | L17: 1700 | M17: 0.52777778 | N17: 113 | O17: =O16+N17/60 -> 12.233333 | Q17: Belles conditions d'hiver, bien tonique avec un mélange de couche de vent pas toujours agréable. Mais au gloabl un très bon vol.
A18: 1 | B18: 1307 | C18: 45357 | D18: Sigma 11-24 | E18: Pyrénées | F18: Planot | G18: Navette | I18: Arbas | J18: Cross | L18: 1575 | M18: 0.50347222 | N18: 135 | O18: =O17+N18/60 -> 14.483333
A19: 1 | B19: 1308 | C19: 45358 | D19: Sigma 11-24 | E19: Pyrénées | F19: Planot | G19: Navette | I19: Arbas | J19: Local | L19: 1400 | M19: 0.5375 | N19: 129 | O19: =O18+N19/60 -> 16.633333 | Q19: Il ne fallait pas plus de vent ! Retour d'Est, Su fort en altitude, 20/40 à Cornu 70 au Pic du Midi.
A20: 1 | B20: 1309 | C20: 45363 | D20: Sigma 11-24 | E20: Pyrénées | F20: Cier de Rivière | G20: Rando | H20: 250 | I20: Cier de Rivière | J20: Local | M20: 0.65972222 | N20: 5.5 | O20: =O19+N20/60 -> 16.725 | Q20: Un plouf de Cier après être passé pour rien à Soueich, On en rit encore !
A21: 1 | B21: 1310 | C21: 45364 | D21: Sigma 11-24 | E21: Pyrénées | F21: Planot | G21: Rando | H21: 700 | I21: Arbas | J21: Local | M21: 0.51944444 | N21: 35 | O21: =O20+N21/60 -> 17.308333 | Q21: Très énervé par Olivier Grimoux que j'insulte parcequ'il me dérange 2 fois de suite après avoir déranger Thierry D. sans jamais changé d'attitude. Du coup j'ai pété un cable et je l'ai insulté. | R21: yer d
A22: 1 | B22: 1311 | C22: 45365 | D22: Sigma 11-24 | E22: Pyrénées | F22: Planot | G22: Rando | H22: 700 | I22: Aspect | J22: Cross | L22: 2025 | M22: 0.51736111 | N22: 88 | O22: =O21+N22/60 -> 18.775 | Q22: Parti pour faire un plouf sous un voile épais de cirrus, en afit ça sortait tout seul. Passage à Paloumère pour le challenge, retour difficile à la Husse et comme un con, j'essaie d'(aller tourner Caoubech et je me fait enterrer au retour face au NE trop fort pour moi. Je ressort par miracle sur les coteaux du coté de chez Luis et j'échoue à l'entrée d'Aspect. Je retrouve ma sellette après les 2 vols précédents avec la Delight 3. C'est pas fait pour moi !
A23: 1 | B23: 1312 | C23: 45366 | D23: Sigma 11-24 | E23: Pyrénées | F23: Planot | G23: Rando | H23: 700 | I23: Arbas | J23: Cross | L23: 2023 | M23: 0.49513889 | N23: 112 | O23: =O22+N23/60 -> 20.641667 | Q23: La journée était annoncé mauvaise, elle fut excellente. On se retrouve 4 au déco. E iront à la vallée de la Barousse, Thierry Strux, fait demi tout au Col des Ares, repasse à Arbas et finit apès St Girons. Mois, je fais les 2 1eres balises de mon triangle, mais j'échoue vers le relais sans plus rien trouver.
A24: 1 | B24: 1313 | C24: 45367 | D24: Sigma 11-24 | E24: Pyrénées | F24: Planot | G24: Navette | I24: Ural | J24: Compete | L24: 1508 | M24: 0.51944444 | N24: 118 | O24: =O23+N24/60 -> 22.608333 | P24: 25 | Q24: 1e manche de la compete d'Arbas, bon début de parcours, mais je merder du coté du relais ou je n'assure pas la plaf et je rate le retour de la pente école.*
A25: 1 | B25: 1314 | C25: 45368 | D25: Sigma 11-24 | E25: Pyrénées | F25: Planot | G25: Navette | I25: Arbas | J25: Compete | L25: 1889 | M25: 0.51180556 | N25: 203 | O25: =O24+N25/60 -> 25.991667 | P25: 40 | Q25: 2ieme manche. Cettef ois je boucle, c'est bien satisfaisant, mais je fais quasiment la même erreur que la veille, pour aller fire la dernière balise de Castelbiague, il aurait fallu fair le plaf au Mountagnat et taper un A/R express. Seule excuse, c'est le moment o^est rentré un voile épais. D'ailleurs de retour de Castelbiague, le soleil revenu, je suis ressorti de la pointe du massif derrière le relais avec facilité.
A26: 1 | B26: 1315 | C26: 45381 | D26: Sigma 11-24 | E26: Pyrénées | F26: Planot | G26: Navette | I26: Arbas | L26: 1543 | M26: 0.56041667 | N26: 109 | O26: =O25+N26/60 -> 27.808333
A27: 1 | B27: 1316 | C27: 45383 | D27: Sigma 11-24 | E27: Pyrénées | F27: Planot | G27: Navette | I27: Arbas | M27: 0.48333333 | N27: 36 | O27: =O26+N27/60 -> 28.408333
A28: 1 | B28: 1317 | C28: 45383 | D28: Sigma 11-24 | E28: Pyrénées | F28: Planot | G28: Navette | I28: Pt de Prades | J28: Cross | L28: 2600 | M28: 0.53333333 | N28: 113 | O28: =O27+N28/60 -> 30.291667 | P28: 27 | Q28: Flux d'ouest trop fort, limite pas volable. Sauf sous 1500 où c'était plus calme.*
A29: 1 | B29: 1318 | C29: 45385 | D29: Sigma 11-24 | E29: Pyrénées | F29: Planot | G29: Navette | I29: St Girons | J29: Cross | L29: 2074 | M29: 0.51041667 | N29: 136 | O29: =O28+N29/60 -> 32.558333 | P29: 37 | Q29: un peu pareil qe le vol précédent, trop d'ouest … NO mais cette fois volable. Après un bon plaf à l'Estelas, je tente de traverser la vallée su Salat par l'ouest de St Girons, mais je suis trop contré. Du coup je me retrouve entre Moulis et St Girons à l'endroit habituel ou ça monte, mais c'est trop NO et je ne veux pas partir dans le relief. Du coup, posé sécure à l'Est de St Girons.
A30: 1 | B30: 1319 | C30: 45386 | D30: Sigma 11-24 | E30: Pyrénées | F30: Planot | G30: Navette | I30: Cornudère | J30: Local | M30: 0.51041667 | N30: 30 | O30: =O29+N30/60 -> 33.058333
A31: 1 | B31: 1320 | C31: 45386 | D31: Sigma 11-24 | E31: Pyrénées | F31: Cornudère | I31: Arbas | J31: Cross | L31: 2125 | M31: 13 | N31: 199 | O31: =O30+N31/60 -> 36.375 | P31: 45
A32: 1 | B32: 1321 | C32: 45387 | D32: Sigma 11-24 | E32: Pyrénées | F32: Planot | G32: Navette | I32: Arbas | J32: Local | L32: 1485 | N32: 68 | O32: =O31+N32/60 -> 37.508333
A33: 1 | B33: 1322 | C33: 45393 | D33: Sigma 11-24 | E33: Pyrénées | F33: Planot | G33: Navette | I33: Arbas | J33: Cross | L33: 2125 | M33: 0.51805556 | N33: 252 | O33: =O32+N33/60 -> 41.708333 | P33: 46 | Q33: Pic du Gar, Herbes Blanches, Le relais. Beaucoup plus facil que la précédent car peu de vent.
A34: 1 | B34: 1323 | C34: 45394 | D34: Sigma 11-24 | E34: Pyrénées | F34: Val Louron 700 | G34: Navette | I34: Campan | J34: Cross | L34: 2878 | M34: 0.51736111 | N34: 166 | O34: =O33+N34/60 -> 44.475 | P34: 38 | Q34: Ca me renvoie 20 ans en arrière quand avec Jo et Réjane en CC, j'étais allé d'Arbas à Aregels Gasost en 3 vols. 2ième passage à l'Arbizon en 25 ans de parapente, c'est peu, mais c'est mon everest à moi. Par con,tre s'il y a une prochaine fois, il faudra que j'évite les ZSM.
A35: 1 | B35: 1324 | C35: 45395 | D35: Sigma 11-24 | E35: Pyrénées | F35: Val Louron 700 | G35: Navette | I35: Loudenvielle | J35: Compete | L35: 3366 | M35: 0.52083333 | N35: 198 | O35: =O34+N35/60 -> 47.775 | Q35: 1er manche, un vrai grand régale, on boucle presque tous, et tout le monde est content.
A36: 1 | B36: 1325 | C36: 45396 | D36: Sigma 11-24 | E36: Pyrénées | F36: Val Louron 700 | G36: Navette | I36: Loudenvielle | J36: Compete | L36: 3302 | M36: 0.50277778 | N36: 242 | O36: =O35+N36/60 -> 51.808333 | Q36: 2ème manche, plus difficile, je ne suis pas le groupe, et je fais mon bonhomme de chemin de mon coté. Je boucle, avant dernier mais c'est une belle réussite.
A37: 1 | B37: 1326 | C37: 45401 | D37: Sigma 11-24 | E37: Pyrénées | F37: Planot | G37: Navette | I37: Arbas | J37: Cross | M37: 0.53680556 | N37: 162 | O37: =O36+N37/60 -> 54.508333 | P37: 30 | Q37: Je boucle enfin un triangle FAI de 29 kms pour atteindre les 40pts CFD pour le challenge Profil.
A38: 1 | B38: 1327 | C38: 45402 | D38: BGD Dual 41 | N38: 21 | O38: =O37+N38/60 -> 54.858333
A39: 1 | B39: 1328 | C39: 45408 | D39: Sigma 11-24 | E39: Espagne | F39: Lac de la Pobla de Segur | N39: 12 | O39: =O38+N39/60 -> 55.058333 | Q39: SIV à la Pobla de Segur avec Marc Boyer
A40: 1 | B40: 1329 | C40: 45412 | D40: Sigma 11-24 | E40: Espagne | F40: Lac de la Pobla de Segur | N40: 16 | O40: =O39+N40/60 -> 55.325
A41: 1 | B41: 1330 | C41: 45412 | D41: Sigma 11-24 | E41: Espagne | F41: Lac de la Pobla de Segur | N41: 16 | O41: =O40+N41/60 -> 55.591667
A42: 1 | B42: 1331 | C42: 45412 | D42: Sigma 11-24 | E42: Espagne | F42: Lac de la Pobla de Segur | N42: 12 | O42: =O41+N42/60 -> 55.791667
A43: 1 | B43: 1332 | C43: 45413 | D43: Sigma 11-24 | E43: Espagne | F43: Lac de la Pobla de Segur | N43: 12 | O43: =O42+N43/60 -> 55.991667
A44: 1 | B44: 1333 | C44: 45413 | D44: Sigma 11-24 | E44: Espagne | F44: Lac de la Pobla de Segur | N44: 12 | O44: =O43+N44/60 -> 56.191667
A45: 1 | B45: 1334 | C45: 45414 | D45: Sigma 11-24 | E45: Espagne | F45: Lac de la Pobla de Segur | N45: 12 | O45: =O44+N45/60 -> 56.391667
A46: 1 | B46: 1335 | C46: 45414 | D46: Sigma 11-24 | E46: Espagne | F46: Lac de la Pobla de Segur | N46: 12 | O46: =O45+N46/60 -> 56.591667
A47: 1 | B47: 1336 | C47: 45420 | D47: BGD Dual 41 | E47: Pyrénées | F47: Val Louron 700 | I47: Loudenvielle | N47: 10 | O47: =O46+N47/60 -> 56.758333 | Q47: Bi pour le Plaf avec Vincent un gars de l'éclairage
A48: 1 | B48: 1337 | C48: 45420 | D48: BGD Dual 41 | E48: Pyrénées | F48: Val Louron 700 | I48: Loudenvielle | N48: 20 | O48: =O47+N48/60 -> 57.091667 | Q48: Bi pour le Plaf avec un enfant de 12 ans 40 kgs
A49: 1 | B49: 1338 | C49: 45421 | D49: BGD Dual 41 | E49: Pyrénées | F49: Val Louron 700 | I49: Loudenvielle | N49: 145 | O49: =O48+N49/60 -> 59.508333 | Q49: Bi avec Quentin, tour du bocale
A50: 1 | B50: 1339 | C50: 45422 | D50: BGD Dual 41 | E50: Pyrénées | F50: Val Louron 700 | I50: Loudenvielle | N50: 173 | O50: =O49+N50/60 -> 62.391667 | Q50: Bi avec Quentin, Espiaube - Céciré - Loudenvielle
A51: 1 | B51: 1340 | C51: 45423 | D51: BGD Dual 41 | E51: Pyrénées | F51: Val Louron 700 | G51: Rando | H51: 700 | I51: Loudenvielle | N51: 110 | O51: =O50+N51/60 -> 64.225 | Q51: Bi avec Aurelie (de Sylvain) beaucoup plus facile que la veille, dommage qu'on s'arrete pour cause pipi …
A52: 1 | B52: 1341 | C52: 45429 | D52: Névada 2 -24 | E52: Pyrénées | F52: Planot | G52: Rando | H52: 700 | I52: Arbas | N52: 8 | O52: =O51+N52/60 -> 64.358333
A53: 1 | B53: 1342 | C53: 45434 | D53: Phi Maestro 2 | E53: Pyrénées | F53: Planot | I53: Arbas | N53: 75 | O53: =O52+N53/60 -> 65.608333 | Q53: Certainement une bonne voilr, mais certainement pas une vraie B !!!
A54: 1 | B54: 1343 | C54: 45437 | D54: Sigma 11-24 | E54: Pyrénées | F54: Planot | I54: Arbas | N54: 9 | O54: =O53+N54/60 -> 65.758333 | Q54: Dernier vol avec la Sigma, après contrôle et calage par Certika, tout va bien. Et 1er vol avec la sellette Kortel Kuik3. Que je décide d'acheter.
A55: 1 | B55: 1344 | C55: 45437 | D55: Névada 2 -24 | E55: Pyrénées | F55: Michel Bellaygues | G55: Rando | H55: 850 | I55: Arbas | N55: 50 | O55: =O54+N55/60 -> 66.591667 | Q55: Une bien belle moontée assez facile, dommage qu'ensuite j'ai eu mal au genoux
A56: 1 | B56: 1345 | C56: 45441 | D56: Névada 2 -24 | E56: Pyrénées | F56: Cier de Rivière | G56: Rando | H56: 250 | I56: Cier de Rivière | N56: 71 | O56: =O55+N56/60 -> 67.775 | Q56: Je n'aime pas ces sites de plaine, mais là c'étaity plutot bien même si je dois prendre confiance dans ce nouveau montage sellette Kuik et Névada. La poignée du secours s'est en partie détaché, il va falloir trouver des solutions !
A57: 1 | B57: 1346 | C57: 45443 | D57: Névada 2 -24 | E57: Pyrénées | F57: Cier de Rivière | G57: Rando | H57: 250 | I57: Arbas | J57: Cross | K57: O-NO | L57: 2040 | M57: 0.53333333 | N57: 112 | O57: =O56+N57/60 -> 69.641667 | Q57: Ca fait un beau vol, Cier-Arbas, mais pas vraiment plaisant. Certaines zones, peut-être sous le vent des thermiques étaient désagréable, à pas savoir quoi faire, enrouler, se barrer ??? Je fais une erreur sur la fin en pensant trouvé quelque chose au nord du Touas, alors qu'il fallait passer par le col de Larrieu. Pas bien grave, ça fait un beau vol, ou nous sommes 6 à faire le parcours, Mitch moyen, Hervé Belloc, Vince, Jean-Marc et Vincent Raja.
A58: 1 | B58: 1347 | C58: 45446 | D58: Névada 2 -24 | E58: Pyrénées | F58: Planot | I58: Arbas | J58: Local | M58: 0.5625 | N58: 82 | O58: =O57+N58/60 -> 71.008333
A59: 1 | B59: 1348 | C59: 45447 | D59: Névada 2 -24 | E59: Pyrénées | F59: Planot | I59: Arbas | J59: Local | M59: 0.43958333 | N59: 30 | O59: =O58+N59/60 -> 71.508333
A60: 1 | B60: 1349 | C60: 45448 | D60: Névada 2 -24 | E60: Pyrénées | F60: Planot | I60: Arbas | J60: Local | M60: 0.54166667 | N60: 41 | O60: =O59+N60/60 -> 72.191667
A61: 1 | B61: 1350 | C61: 45448 | D61: Névada 2 -24 | E61: Pyrénées | F61: Planot | I61: Arbas | J61: Cross | M61: 0.58680556 | N61: 180 | O61: =O60+N61/60 -> 75.191667 | P61: 25
A62: 1 | B62: 1351 | C62: 45449 | D62: Névada 2 -24 | E62: Pyrénées | F62: Planot | I62: Arbas | J62: Local | M62: 0.54513889 | N62: 102 | O62: =O61+N62/60 -> 76.891667
A63: 1 | B63: 1352 | C63: 45456 | D63: Névada 2 -24 | E63: Pyrénées | F63: Planot | G63: Rando | H63: 700 | I63: Arbas | J63: Cross | K63: Vent de NE faible | L63: 1750 | M63: 0.53125 | N63: 165 | O63: =O62+N63/60 -> 79.641667 | P63: 38 | Q63: Pris à froid, gros thermique en sortie de déco, la suite sera du même gabarit, 2/4 sur mon échelle du rock and vol. La Husse et Herbes blanche facile, plus compliqué pour revenir de Cazavet, il faudra soigner le retour la rpochaine fois.
A64: 1 | B64: 1353 | C64: 45457 | D64: Névada 2 -24 | E64: Pyrénées | F64: Cornudère | G64: Rando | H64: 1300 | I64: Arbas | J64: Local | M64: 0.56458333 | N64: 40 | O64: =O63+N64/60 -> 80.308333 | Q64: Belle montée par le Planot, Roc et Pie et les crêtes de Cornu
A65: 1 | B65: 1354 | C65: 45459 | D65: Ikuma 3P - 24 | E65: Pyrénées | F65: Planot | G65: Navette | I65: Arbas | J65: Cross | K65: Flux de NE | L65: 2068 | M65: 0.51875 | N65: 249 | O65: =O64+N65/60 -> 84.458333 | P65: 50 | Q65: 1er vol avec l'Ikuma, Beau virage, de bonnes sensations dessous mais les conditions de vols étaient difficile pour bien juger. Il me semble qu'elle est un peu lente, à revoir et à associer à l'usage de l'accelarateur. Début du vol difficile au Planot, passage facile au Cagire et au Gar, je repars un peu bas du Cagire et raccroche difficilement au Picon, par contre, belle ascendence pour en sortir et passer Paloumère par le haut et aborder les faces sud de Cornu très mal pavées. Bellea ascendence de nouveau à Herbes blanches en compagnie d'un planeur, passage rapide à l'Estelas et retour par le relais ou de nouveau je n'arrive pas à retrouver unnthermique.
A66: 1 | B66: 1355 | C66: 45460 | D66: Ikuma 3P - 24 | E66: Pyrénées | F66: Planot | G66: Navette | I66: Arbas | N66: 44 | O66: =O65+N66/60 -> 85.191667 | Q66: De bien mauvaises conditions pour essayer cette voile, mais je trouve qu'elle n'avance pas bien vite
A67: 1 | B67: 1356 | C67: 45467 | D67: Ikuma 3P - 24 | E67: Pyrénées | F67: Planot | G67: Navette | I67: Arbas | J67: Cross | K67: Léger flux de NE | L67: 1930 | M67: 0.50972222 | N67: 258 | O67: =O66+N67/60 -> 89.491667 | P67: 71 | Q67: Un beau vol pour un beau cross. Je pensais d'abord aller droit vers l'Est, mais au Saqueton, j'ai trouvé le début de la transition bien difficile face à un peu d'Ouest, du coup j'ai tenté le retour. Passage délicat pour re^rendre au NO du col du Oo, sinon plutot facile. Pour la voile, il suffit de l'accélérer.
A68: 1 | B68: 1357 | C68: 45468 | D68: Ikuma 3P - 24 | E68: Pyrénées | F68: Planot | G68: Navette | I68: Arbas | J68: Cross | K68: Léger flux de NE | L68: 2278 | M68: 0.53125 | N68: 251 | O68: =O67+N68/60 -> 93.675 | P68: 59 | Q68: On y croyait et pourtant le conditions ont été moins bonnes que la veille. Dommage. Du coup, étrange aérologie du coté du Cagire, Plutot agréable en face NE du Gar, retour difficile de nouveau au Cagire par la face NO probablement sous le vent, puis mieux coté NE, compliqué aussi coté Paloumère. Par contre le passage Cazavet/Estelas, un vrai régal.
A69: 1 | B69: 1358 | C69: 45469 | D69: Ikuma 3P - 24 | E69: Pyrénées | F69: Planot | G69: Navette | I69: Arbas | J69: Local | M69: 0.50694444 | N69: 82 | O69: =O68+N69/60 -> 95.041667
A70: 1 | B70: 1359 | C70: 45478 | D70: Ikuma 3P - 24 | E70: Pyrénées | F70: Planot | G70: Navette | I70: Arbas | J70: Local | M70: 0.57569444 | N70: 47 | O70: =O69+N70/60 -> 95.825 | Q70: Echange de voile avec JL Nozières. J'essaie sa Air Design Soar. Ca confirme mes sensations de l'Ikuma, la Soar est plus rapide, je sens tout de suite, le vent relatif qui manque sur l'Ikuma. Ar contre, très physique aux commandes.
B71: 1360 | C71: 45481 | D71: Ikuma 3P - 24 | E71: Pyrénées | F71: Cornudère | G71: Rando | H71: 400 | I71: Milhas | J71: Local | L71: 1953 | M71: 0.54722222 | N71: 56 | O71: =O70+N71/60 -> 96.758333
A72: 1 | B72: 1361 | C72: 45483 | D72: Ikuma 3P - 24 | E72: Pyrénées | F72: Cornudère | G72: Navette | H72: 0 | I72: Arbas | J72: Local | L72: 1753 | M72: 0.52638889 | N72: 194 | O72: =O71+N72/60 -> 99.991667
A73: 1 | B73: 1362 | C73: 45484 | D73: Ikuma 3P - 24 | E73: Pyrénées | F73: Cornudère | G73: Rando | H73: 1100 | I73: Arbas | J73: Local | L73: 1708 | M73: 0.55694444 | N73: 102 | O73: =O72+N73/60 -> 101.69167
A74: 1 | B74: 1363 | C74: 45396 | D74: Ikuma 3P - 24 | E74: Pyrénées | F74: Cier de Rivière | G74: Rando | H74: 220 | I74: Aspect | J74: Cross | L74: 1620 | M74: 0.59444444 | N74: 125 | O74: =O73+N74/60 -> 103.775 | P74: 20 | Q74: 1ere heure en local avec Quentin qui en ai à son 5 vols avec sa nouvelle Théta. Puis au plaf à 1550, je pars vers le Sud-Est, trop vers le relief et j'échoue à Aspect. Le coté cocasse c'est que je suis parti avec les clés de la C15. Du coup retour en stop en .... 30 minutes. La classe, Quentin même pâs encore posé !
A75: 1 | B75: 1364 | C75: 45490 | D75: Ikuma 3P - 24 | E75: Pyrénées | F75: Planot | G75: Rando | H75: 700 | I75: Arbas | J75: Local | L75: 1450 | M75: 0.53194444 | N75: 97 | O75: =O74+N75/60 -> 105.39167 | Q75: Vario encore égaré… décodemment ! Duc oup je vole sans, plutot pas mal. Finalement quelqu'un le retrouve au déco et Thierry me le rémène
A76: 1 | B76: 1365 | C76: 45491 | D76: Ikuma 3P - 24 | E76: Pyrénées | F76: Planot | G76: Navette | I76: Cornudère | L76: 1780 | M76: 0.54166667 | N76: 136 | O76: =O75+N76/60 -> 107.65833 | Q76: Sacrément difficile au début, je tiens vaille que vaille. Ca s'arrange peu à peu jusqu'à trouver une ascendence étonnante au dessus de Labaderque qui me monte à presque 1800 et qui me permet d'aller poser à Cornu.
A77: 1 | B77: 1366 | C77: 45491 | D77: Ikuma 3P - 24 | E77: Pyrénées | F77: Cornudère | I77: Arbas | L77: 1850 | M77: 0.65277778 | N77: 76 | O77: =O76+N77/60 -> 108.925 | Q77: Beauocup plus facile, décoidemmeny il faut prendre son temps en ce moment. Trop bien au dessus du Plan de Liet.
A78: 1 | B78: 1367 | C78: 45492 | D78: Ikuma 3P - 24 | E78: Pyrénées | F78: Planot | G78: Navette | I78: Castelbiague | N78: 65 | O78: =O77+N78/60 -> 110.00833
A79: 1 | B79: 1368 | C79: 45497 | D79: Ikuma 3P - 24 | E79: Pyrénées | F79: Planot | G79: Navette | I79: Arbas | N79: 13 | O79: =O78+N79/60 -> 110.225
A80: 1 | B80: 1369 | C80: 45497 | D80: Ikuma 3P - 24 | E80: Pyrénées | F80: Planot | G80: Rando | H80: 700 | I80: Arbas | N80: 13 | O80: =O79+N80/60 -> 110.44167
A81: 1 | B81: 1370 | C81: 45498 | D81: Ikuma 3P - 24 | E81: Pyrénées | F81: Planot | G81: Rando | H81: 700 | I81: Arbas | N81: 37 | O81: =O80+N81/60 -> 111.05833
A82: 1 | B82: 1371 | C82: 45499 | D82: Ikuma 3P - 24 | E82: Pyrénées | F82: Planot | G82: Navette | I82: Arbas | N82: 21 | O82: =O81+N82/60 -> 111.40833
A83: 1 | B83: 1372 | C83: 45499 | D83: Ikuma 3P - 24 | E83: Pyrénées | F83: Planot | G83: Navette | I83: Arbas | N83: 53 | O83: =O82+N83/60 -> 112.29167
A84: 1 | B84: 1373 | C84: 45502 | D84: Ikuma 3P - 24 | E84: Pyrénées | F84: L'Espone | G84: Rando | H84: 200 | I84: Luchon | J84: Cross | L84: 4411 | M84: 0.48402778 | N84: 324 | O84: =O83+N84/60 -> 117.69167 | P84: 80 | Q84: Enfin un vol de référence dans les Pyrénées. Bien insppiré de décoller de l'Espone, j'ai un mal fou à m'extarire. Mais une fois sur la chaine, à part la puissance, quasi violente des thermiques, c'est tout du facile. C'est un gros, gros vol, mais pas tellement plaisant, par 2 fois, je suis au niveau 3 et je fuis les thermiques. Je pense les 2 fois qu'ils déclanchent en face sud, une fois à l'Estos et une fois au dessus du Plat d'Adet.
A85: 1 | B85: 1374 | C85: 45504 | D85: Ikuma 3P - 24 | F85: Planot | N85: 107 | O85: =O84+N85/60 -> 119.475
A86: 1 | B86: 1375 | C86: 45508 | D86: Ikuma 3P - 24 | F86: Planot | N86: 14 | O86: =O85+N86/60 -> 119.70833
A87: 1 | B87: 1376 | C87: 45509 | D87: Ikuma 3P - 24 | F87: Val Louron 700 | N87: 79 | O87: =O86+N87/60 -> 121.025
A88: 1 | B88: 1377 | C88: 45509 | D88: Ikuma 3P - 24 | F88: Michel Bellaygues | N88: 45 | O88: =O87+N88/60 -> 121.775
A89: 4 | B89: 1378 | C89: 45510 | D89: BGD Dual 41 | F89: Planot | N89: 43 | O89: =O88+N89/60 -> 122.49167 | Q89: Avec Paul et Margot des copains d'Hélène la fille de Colette
A90: 1 | B90: 1382 | C90: 45512 | D90: Ikuma 3P - 24 | F90: Planot | N90: 15 | O90: =O89+N90/60 -> 122.74167
A91: 1 | B91: 1383 | C91: 45513 | D91: Ikuma 3P - 24 | F91: Planot | N91: 13 | O91: =O90+N91/60 -> 122.95833
A92: 1 | B92: 1384 | C92: 45514 | D92: Ikuma 3P - 24 | E92: Massif Central | F92: Puncho d'Agast | G92: Fourgon | I92: Puncho d'Agast | J92: local | L92: 1512 | M92: 0.75486111 | N92: 105 | O92: =O91+N92/60 -> 124.70833 | Q92: Avec Quentin, Un bien beau vol du soir qui m'a renvoyé 20 ans en arrière en stage avec Roland Thurel que j'i d'ailleurs rencpn,tré après le vol. Pas grand-chose à se dire.Dommage
A93: 1 | B93: 1385 | C93: 45516 | D93: Ikuma 3P - 24 | E93: Alpes | F93: Passy-Plaine Joux | G93: Fourgon + Vélo | H93: 700 | I93: Passy | J93: Local | M93: 0.48958333 | N93: 22 | O93: =O92+N93/60 -> 125.075 | Q93: Rien trouvé que de tout petits thermiques
A94: 1 | B94: 1386 | C94: 45517 | D94: Ikuma 3P - 24 | E94: Alpes | F94: Passy -Varan | G94: Fourgon + Rando | H94: 600 | I94: Passy - Plaine Joux | J94: Local | M94: 0.50625 | N94: 68 | O94: =O93+N94/60 -> 126.20833 | Q94: Montée bien raide aux Chalets de Varan, dommage on arrive pas à s'extarire
A95: 1 | B95: 1387 | C95: 45517 | D95: Ikuma 3P - 24 | E95: Alpes | F95: Passy-Plaine Joux | G95: Fourgon | I95: Passy | J95: Local | M95: 0.65069444 | N95: 73 | O95: =O94+N95/60 -> 127.425 | Q95: Décoller de Plaine Joux, cette fois on sort bien, mais on abrège le vol à cause de l'approche des orages venant de l'Italie - MLt Blanc qui piègera pplus tard pas mal de pilote à Annecy.
A96: 1 | B96: 1388 | C96: 45519 | D96: Ikuma 3P - 24 | E96: Alpes | F96: Gd Bornand | G96: Remontée mécanique | I96: Gd Bornand | J96: Local | M96: 0.45833333 | N96: 48 | O96: =O95+N96/60 -> 128.225 | Q96: Magnifique site, trop bien les remontée mécanique, même si franchement cher.
A97: 1 | B97: 1389 | C97: 45519 | D97: Ikuma 3P - 24 | E97: Alpes | F97: Gd Bornand | G97: Remontée mécanique | I97: Gd Bornand | J97: Local | M97: 0.55902778 | N97: 60 | O97: =O96+N97/60 -> 129.225 | Q97: Pareil qu'à Passy, posé pour cause d'arrivée d'orages. L'attéro est délicat.
A98: 1 | B98: 1390 | C98: 45520 | D98: Ikuma 3P - 24 | E98: Alpes | F98: St Hilaire du Touvet | G98: Navette | I98: Lumbin | J98: Local | M98: 0.47916667 | N98: 56 | O98: =O97+N98/60 -> 130.15833 | Q98: Plafond bas, au niveau du plateau, mais balade A/R devant et c'est sympa
A99: 1 | B99: 1391 | C99: 45524 | D99: Mito 2 RS | E99: Pyrénées | F99: Planot | G99: Rando | I99: Arbas | J99: Local | N99: 10 | O99: =O98+N99/60 -> 130.325 | Q99: Essai de la voile de Quentin après révision, c'est un nouveau parapebnte que voilà, qui vole plutot vite !
A100: 1 | B100: 1392 | C100: 45524 | D100: Ikuma 3P - 24 | E100: Pyrénées | F100: Planot | G100: Rando | H100: 700 | I100: Arbas | J100: Local | M100: 0.57291667 | N100: 90 | O100: =O99+N100/60 -> 131.825
...

Sheet 2023
A1: Compt | B1: N° Vol | C1: Date | D1: Voile | E1: Région | F1: Déco | G1: Acc. | H1: Dén. | I1: Attéro | J1: Type de vol | K1: Météo | L1: A1 max | M1: Heure décollage (locale) | N1: Durée | O1: Durée cumulée | P1: Dist | Q1: Rmq
A2: 1 | B2: 1173 | C2: 44930 | D2: Névada 2 -24 | E2: Pyrénées | F2: Planot | G2: Rando | H2: 700 | I2: Arbas | J2: Local | K2: Léger flux d'Ouest | M2: 0.54305556 | N2: 25 | O2: =25/60 -> 0.41666667
A3: 1 | B3: 1174 | C3: 44931 | D3: Névada 2 -24 | E3: Pyrénées | F3: Cornudère | G3: Rando | H3: 400 | I3: Arbas | J3: Cross | L3: 1825 | M3: 0.53472222 | N3: 118 | O3: =O2+N3/60 -> 2.3833333 | P3: 24
A4: 1 | C4: 44941 | D4: Névada 2 -24 | E4: Mancioux | O4: =O3+N4/60 -> 2.3833333 | Q4: Gonflage à Paris les Près 1h envron
A5: 1 | B5: 1175 | C5: 44936 | D5: Névada 2 -24 | E5: Pyrénées | F5: Roquefort / Garonne | H5: 220 | I5: Roquefort / Garonne | J5: Local | M5: 0.675 | N5: 4 | O5: =O4+N5/60 -> 2.45
A6: 1 | B6: 1176 | C6: 44946 | D6: Névada 2 -24 | E6: Pyrénées | F6: Roquefort / Garonne | H6: 220 | I6: Roquefort / Garonne | M6: 0.69722222 | N6: 5 | O6: =O5+N6/60 -> 2.5333333
A7: 1 | B7: 1177 | C7: 44956 | D7: Sigma 11 | E7: Pyrénées | F7: Roquefort / Garonne | H7: 220 | I7: Roquefort / Garonne | L7: 590 | M7: 0.69375 | N7: 23 | O7: =O6+N7/60 -> 2.9166667 | Q7: Déco à 490
A8: 1 | B8: 1178 | C8: 44957 | D8: Sigma 11 | E8: Pyrénées | F8: Planot | G8: Rando | H8: 400 | I8: Arbas | J8: Local | L8: 1337 | M8: 0.52708333 | N8: 124 | O8: =O7+N8/60 -> 4.9833333 | Q8: Voiture laissée à Labaderque pour cause de route verglacée. Montée 2/3 à pied, 1/3 en stop. Déneigeage de 2 pistes de décollage. Seul montent Vincent Raja et Jean-Marc Duché. Pourtant belle journée pour voler. Petit thermique devant le déco, un peu mieux à Bourrus, transition à Soulan, difficile d'atteindre 1200, repassage à bourrus pour la pompe à Cham ou ç fonctionne bien, direction les Hirriguades, petit thermique, mieux sous le vent du relais et franchement bien à l'est du relais, plaf du jour à 1335m. du coup transition vers Le Thousas ou je dois m'y reprendre à 2 fois avec un point bas à 730 m pour réussir à remonter à 1100 environ, retour en passsant au dessus de Bataille puis le bas de Soulan. Evidemment il faisait froid, mais avec les chaufferettes dans les gants ça allait.
A9: 1 | B9: 1179 | C9: 44959 | D9: Névada 2 -24 | E9: Pyrénées | F9: Planot | G9: Rando | H9: 700 | I9: Arbas | J9: Cross | L9: 1280 | M9: 0.52291667 | N9: 116 | O9: =O8+N9/60 -> 6.9166667 | P9: 18 | Q9: Montée à pied en 1h20, pas mal avec de la neige sur le haut, mais pas la super forme;… l'impression de peser 2t… enfin76 kg !Vol assez classique mais turbulent. Content d'avoir réussi à aller jusqu'à Herbes Blanches.
A10: 1 | B10: 1180 | C10: 44963 | D10: Névada 2 -24 | E10: Pyrénées | F10: Le Relais | I10: Arbas | J10: Local | L10: 1000 | M10: 0.47916667 | N10: 30 | O10: =O9+N10/60 -> 7.4166667 | Q10: Une éternité que je n'avais pas volé du relais. Bien sympa de sortir avec le thermique de service. En plus sans vario … mais bien aidé par les zozios en tous genres dont les vautours dont on se demande d’où ils viennent ….
A11: 1 | B11: 1181 | C11: 44965 | D11: Névada 2 -24 | E11: Pyrénées | F11: Planot | I11: Arbas | J11: Local | L11: 1250 | M11: 0.53402778 | N11: 131 | O11: =O10+N11/60 -> 9.6 | Q11: Des nuages bas ont retardés le début de vol. Je décolle en 1er et atterrirai en dernier. Début bien difficile à Bourrus où je lets un temps fou à d'abord m'accrocher puis peu à peu à sortir. A 1000m, transition vers Soulan, à partir de là tout est plus simple.
A12: 1 | B12: 1182 | C12: 44967 | D12: Sigma 11 | E12: Pyrénées | F12: Planot | I12: Arbas | J12: Cross | L12: 1300 | M12: 0.51805556 | N12: 175 | O12: =O11+N12/60 -> 12.516667 | P12: 22 | Q12: Beau, beau vol. Cette fois, assez facile de sortir de Bourrus pour aller à Soulan. Plaf bas, je n'inssite pas, je reviens à Bourrus, de 1150 je transite vers Le Mountagnat, aux environs de 1200, transition vers les Iriguades. Remontée vers Herbes blanches où je m'en sorts bien, je commence à connaître les ascendances. Retour vers le relais où je finis par refare 1200. Le Thouas me semble inaccessible, du coup je retourne à Soulan où je fais le plaf de mon vol et du coup le Thouas est accessible. Je l'aborde par la crête Pène Nère/Col de Larieu, ça porte bien, par contre une fois au nors du Thoas ça dégringole et ça contre. Ce n'est qu'un fois le Thouas contourné que je retrouve de quoi me refaire et en 4 ascendances je suis de nouveau au Col de larieu. Le retour est laborieux par les vallons nord de Soulan, mais je finis par passer, refaire un bon gain, boucler sous la Husse et rentrer à l'attero par la face nord toute gelée de Pène Blanque. Mon 1er beau vol de l'année.
A13: 1 | B13: 1183 | C13: 44970 | D13: Sigma 11 | E13: Pyrénées | F13: Cornudère | G13: Rando | H13: 400 | I13: Arbas | J13: Local | M13: 0.54166667 | N13: 16 | O13: =O12+N13/60 -> 12.783333 | Q13: Jour funeste, vol balistique juste pour être en l'air ce jour là.
A14: 1 | B14: 1184 | C14: 44973 | D14: Sigma 11 | E14: Pyrénées | F14: Planot | I14: Millas | J14: Cross | K14: Anticyclonique | L14: 1980 | M14: 0.51388889 | N14: 116 | O14: =O13+N14/60 -> 14.716667 | P14: 31 | Q14: Tout de suite beau plaf à la Husse, Michel Delahuerta est déjç parti vers le Cagire, je suis. J'arrive à Plaède alors qu'il s'extrait, j'en profite. Il repart vers Arbas, je vais au col des Ares et retour. Dommage, on échoue tous au retour au Picon, il aurait fallu tenter de passer pas devant Sengouagnet pour tenter de raccrocher les faces nord de
A15: 1 | B15: 1185 | C15: 44974 | D15: Sigma 11 | E15: Pyrénées | F15: Planot | I15: Arbas | J15: Cross | K15: Anticyclonique | L15: 1750 | M15: 0.52083333 | N15: 155 | O15: =O14+N15/60 -> 17.3 | P15: 24 | Q15: Les plafonds baissent mais, une fois bien positionné à Herbes Blanches, je transite vers l'Estelas ou je réussi à percer la couche d'inversion et avec les 1750, je glisse jusqu'à Montastruc et retour à Soulan pour un dernier tour par Pènne Blanque. Un vrai plaisir ce vol... Les sensations reviennent peu à peu... Youpi.
A16: 1 | B16: 1186 | C16: 44981 | D16: Sigma 11 | E16: Pyrénées | F16: La tour d'Ausseing | G16: Rando | H16: 150 | M16: 0.62013889 | N16: 6 | O16: =O15+N16/60 -> 17.4 | Q16: 1er vol à Ausseing, il y a forcément du potentiel; mais c'est élitiste
A17: 1 | B17: 1187 | C17: 44990 | D17: BGD Dual 40 | E17: Pyrénées | F17: Planot | I17: Arbas | J17: Local | M17: 0.55347222 | N17: 35 | O17: =O16+N17/60 -> 17.983333 | Q17: Reprise du bi avec Quentin, Bon déco, bon attéro, conditions de vol trop remuante, Quentin est malade rpidement
A18: 1 | B18: 1188 | C18: 45005 | D18: Sigma 11 | E18: Pyrénées | F18: Planot | G18: Navette | I18: Arbas | J18: Local | M18: 0.52569444 | N18: 130 | O18: =O17+N18/60 -> 20.15 | Q18: Commencé sans trop de moral à cause du vent d'Ouest à Cornu, le vol se termine très bien avec un passage à la Husse, puis par le col de Larrieu.
A19: 1 | B19: 1189 | C19: 45007 | D19: Sigma 11 | E19: Pyrénées | F19: Planot | G19: Navette | I19: Vallée de Nistos | J19: Cross | K19: Flux d'Ouest avec vent de NE ? | L19: 2319 | M19: 0.48958333 | N19: 160 | O19: =O18+N19/60 -> 22.816667 | P19: 50 | Q19: 1er vrai cross depuis longtemps, il me semble à etre le seul à avoir réussi/osé sortir du site. Faut dire décollé avec Michel Delahuerta et Trhierry D. avant tout le monde, j'ai la chance de sortir direct du déco jusquà 2000? De là 2320 au sud de Paloumère et ça s'enchaine facilement et rapidement jusqu'au col des Ares. Bien aidé par de l'Est à 5/10 kmh. Un gros voil me fait hésiter à contrinuer vers l'Ouest mais le vent météo me fait rechigner à entamer le retour. Du coup, après un bon plein su coté de Galié / Mt de Galié, je traverse la Garonne et arrive jusqye à la bonne hauteursur le coté Est du Sacqueton/Tourroc. Ensuite Pic de Picarre, puis avant la vallée de la Neste, je fais demi tour à Pène Haute. L'autre coté est à l'ombre, le voile s'épaissit rapidement et d'aileurs me rattrapera rapidement alors que je tente le retour ... vainement, trop contrée, je ne trouve pas le thermique qui m'aurait peut-être permi de raccorcher au Sacqueton. Beau vol, rapide, efficace, peut-etre un peu trio rock and roll du coté du Pic de Picarre.Niveau 4/4 ! Au delmà je ne suis pas sûr de savoir maitriser ...*
A20: 1 | B20: 1190 | C20: 45008 | D20: Sigma 11 | E20: Pyrénées | F20: Planot | G20: Navette | I20: Arbas | J20: Local | L20: 1590 | M20: 0.49652778 | N20: 90 | O20: =O19+N20/60 -> 24.316667 | Q20: Entre 2 passages de voiles d'altitude. Plutot toniques en étant agréable. Beau passage de Piscatel à Herbes Blanches, dommage que je rate le retour. D'abord tenté par l'Estélas, je dévie rapidement vers la borne 110, ne trouvant iren j'ai pris la direction du relais. Mais un écobuage à Fougaron surveillé par des drones des pompiers m'inquiétant, j'ai forcé vers les Irriguades. Rapidement sous le vent et dans des dégueulantes j'ai bien failli ne pas reven,ir à Arbas. Heureusement que j'ai trouvé un petit quelque chose qui m'a permis de me refaire et de rentrer proprement...
A21: 1 | B21: 1191 | C21: 45014 | D21: Névada 2 -24 | E21: Pyrénées | F21: Cornudère | G21: Rando | H21: 400 | I21: Arbas | J21: Cross | K21: Flux en Sud Ouest avant arrivée dépression | L21: 3620 | M21: 0.54861111 | N21: 141 | O21: =O20+N21/60 -> 26.666667 | P21: 35 | Q21: J'ai voulu monté avec du lioght ppour la face sud de Cornu. Erreur. J'ai avorté un déco pas bien emmanché du tout coté sud, du temps de dégager la voile des kékés, de passer coté nord, j'étais en nage sous mes couches d'habits. Du coup j'ai fait le vol trempé et ... frigorifié. Par contre, j'ai un peu ouvert la route vers le sud, par kle col de Portet d'Aspet ver sle Puech (il y a un bassin pour l'eau sur le sommet. Une prochaine fois, il faudra tenter de continuer face au vent, pour essayer de rejoindre la crête Est/ouest de la Calabasse. Par contre avec un plaf à 3600m jai emplafonné la LTA Pyrénées qui est limitée à 3500. Retour vent de dos (SO) jusqu'à Cazavet puis de nouiveau vent de dos (NE) jusqu'à Relais/Arbas. | R21: yer d
A22: 1 | B22: 1192 | C22: 45021 | D22: Sigma 11 | E22: Pyrénées | F22: Planot | G22: Navette | I22: Arbas | K22: Flux de NO | L22: 1811 | M22: 0.53333333 | N22: 102 | O22: =O21+N22/60 -> 28.366667 | Q22: Pas très agréable, dominante ouest trop marquée
A23: 1 | B23: 1193 | C23: 45023 | D23: Sigma 11 | E23: Pyrénées | F23: Planot | G23: Rando | H23: 700 | I23: Arbas | J23: Cross | K23: Flux de NO | L23: 1871 | M23: 0.50625 | N23: 196 | O23: =O22+N23/60 -> 31.633333 | P23: 30 | Q23: Début très pénible, un premier point bas au pied de Bourrusse, quasi à se poser, un deuxième au bas de Soulan, ensuite je trouve le rythme et ça fait un beau vol quoique turbulent. Passage à Paloumère (j'aurai du partir vers le Cagire… tant pis), balise à l'Estelas, (j'aurai du partir plein ouest avec michel Delahuerta qui va à Labastide Sérou, mais je réalise quand même un beau triangle de 30 kms qui n'atait vraiment pas gagné au début du vol. Et puis cette tendans nord etait trop marquée pour que ce soit un vol plaissant. UN super bon point pour la Sigma 11 qui s'est bien fait secouer les plumes mais sans fermeture catastrophique. Décidément quelle voile !
A24: 1 | B24: 1194 | C24: 45024 | D24: Sigma 11 | E24: Pyrénées | F24: Planot | G24: Navette | I24: Foix | J24: Cross | K24: Flux de NO | L24: 2153 | M24: 0.50208333 | N24: 232 | O24: =O23+N24/60 -> 35.5 | P24: 68 | Q24: Comme la veille, mais pire, début catastrophique et je n'arrive à sortir à la Husse qu'après la 3ième tentative et 1h de vol. Pendant ce temps là, JeanSeb et Vince sont au pied du Cagire et ils y galèrent. Du coup, comme il y a de l'ouest, je pars pour un vol dans le bocal en direction de Cornudère ou il y a Eric, que je n'arrive jamais à rattraper, toujours plus haut, toujours devant. Finalement au Mountagnat, on est ensemble au plaf et lui repart vers Piscatelle, moi vers les Iriguades. Bien m'en a pris, une fois quitté le bocal, ce sera facile jusqu'à Foix. 1ere fois que je vais à Foix. Je pensais en vol être super prudent en restant sur les avants reliefs, toujours proche de la route St Girons-Foix, je verrai plus tard que tout le monde passe par là. Peut-être aurais-je du pour l'arrivée aller du coté de Ganac pour être au vent, la zone ou j'atteris étant sous le vent d'un relief, mais quand même assez loin et sans conséquence.7
A25: 1 | B25: 1195 | C25: 45025 | D25: BGD Dual 40 | E25: Pyrénées | F25: Planot | G25: Navette | I25: Arbas | J25: Local | K25: Flux de NO | L25: 1550 | M25: 0.58333333 | N25: 53 | O25: =O24+N25/60 -> 36.383333 | Q25: Une bonne reprise avec Quentin, grosse chance de partir en tout dernier, les copains s'étant quasi tous fait enterrés à cause de la tendance ouest. Dommage que ce soit trop trubulent, mais un bel A/R sueper facile à Herbes Blanches.
A26: 1 | B26: 1196 | C26: 45026 | D26: BGD Dual 40 | E26: Pyrénées | F26: Planot | G26: Rando | H26: 700 | I26: Arbas | J26: Local | K26: Flux de NO | M26: 0.54166667 | N26: 20 | O26: =O25+N26/60 -> 36.716667 | Q26: Cette fois, après un thermique à Bourrus, on est trop contré pour aller à Soulan. Vince et Jean (Surfair) ne restent pas longtemps en l'air non plus, ils trouvent la masse d'air un peu triop étrange.
A27: 1 | B27: 1197 | C27: 45155 | D27: Sigma 11 | E27: Pyrénées | F27: Planot | G27: Navette | I27: Arbas | J27: Local | K27: Flux de N 10/15 kmh | L27: 1900 | M27: 0.5 | N27: 125 | O27: =O26+N27/60 -> 38.8 | Q27: Vent de nord trop fort, vol turbulent en local uniquement, bloqué coté Cagire autant que coté Estelas. Pourtant Sammy Gallégo fait 110 kms de Gensac à Quillan, avec 15/30 aux balises environnantes…. Chapeau.
A28: 1 | B28: 1198 | C28: 45034 | D28: Sigma 11 | E28: Pyrénées | F28: Planot | G28: Navette | I28: Arbas | J28: Local | K28: Flux de nord faible | L28: 1700 | M28: 0.47916667 | N28: 37 | O28: =O27+N28/60 -> 39.416667 | Q28: Craigant que ça ce ferme rapidement je décolle tot et après un joli passage au nord de la Husse je m'enterre au Toas. Trop tot, Vincent, Thierry qui feront un second vol sur la plaine iront jusqu'à Mane.
A29: 1 | B29: 1199 | C29: 45035 | D29: Sigma 11 | E29: Pyrénées | F29: Planot | G29: Navette | I29: Izaourt | J29: Cross | K29: Vent d'Est en basse couche | L29: 2016 | M29: 0.5 | N29: 222 | O29: =O28+N29/60 -> 43.116667 | P29: 44 | Q29: Certes c'est un cross et même un parcours inusité pour moi, mais il y avait trop de vent d'Est et beaucoup trop de turbulences, j'atais à 4/4 dans mon échelle de rock and roll…. Vivement une journée plus calme et de belles conditions météo !
A30: 1 | B30: 1200 | C30: 45036 | D30: Sigma 11 | E30: Pyrénées | F30: Planot | G30: Navette | I30: Castagnède | J30: Cross | K30: Vent de SO fort au dessus de 2000, tendance NO en dessous | L30: 1965 | M30: 0.51180556 | N30: 53 | O30: =O29+N30/60 -> 44 | P30: 19 | Q30: Nous ne somme que 4 au déco, les prévis de SO ayant découragé tout le monde, pourtant les balises sont basses et en effet, à part de NO, les conditions sont bonnes et calmes. Après un plaf à 2000 à la Husse, j'ai tiré tout droit vers St Girons, mais je n'ai plus rien trouvé ... Vol agréable, doux après ceux du début de semaine ça fait du bien.
A31: 1 | B31: 1201 | C31: 45037 | D31: Sigma 11 | E31: Pyrénées | F31: Planot | G31: Navette | I31: Arbas | J31: Local | L31: 1644 | M31: 0.51111111 | N31: 202 | O31: =O30+N31/60 -> 47.366667 | Q31: Du vent de NE de nouveau, de nouveau turbulent, plafonds bas, beaucoup de copains se posent rapidement. Pourtant, peu à peu, les conditions s'améliorent et c'st en fin de vol que le dernier tour du bocal en compagnie de Thierry, donnc toute la substence de ce vol finalement très bien dont un beau thermique du coté du déco M. Belaygues qui ma fait dérivé un peu cotè sud. Très chouette.
A32: 1 | B32: 1202 | C32: 45043 | D32: Sigma 11 | E32: Pyrénées | F32: Planot | G32: Rando | H32: 700 | I32: Arbas | J32: Cross | L32: 1873 | M32: 0.53402778 | N32: 187 | O32: =O31+N32/60 -> 50.483333 | P32: 24 | Q32: Comme souvent c'est la fin du vol qui a été la plus plaisante avec une belle avancée jusqu'à la colline au dessus de la pente école de Surfair, …., peutèêtre qu'un jour je saurai aller à Mane ? Mais je suis content car il a fallu que je me refasse sur la crête au nord du relais pour pouvoir rentrer, pour une fois je suis sortie de la finesse du retour terrain. Je progresse ! Et après ce beau vol, j'ai eu l'énerfgie pour monter à pied et avec Rio chercher la C15 au déco. 1h15 ... doit mieux faire !
A33: 1 | B33: 1203 | C33: 45048 | D33: Sigma 11 | E33: Pyrénées | F33: Planot | G33: Navette | I33: Barrat | J33: Cross | K33: Léger flux de Nord | L33: 1670 | M33: 0.51319444 | N33: 172 | O33: =O32+N33/60 -> 53.35 | P33: 30 | Q33: A 1500 à la Husse, je ne me sens pas capabme de partir vers l'Ouest. Pourtant, Xavier Laporte le fait, passse par la Cagire, revientdu coté de Paloumère, file vers la chaine, passe au Vallier et boucle un triangle de 86 kms. On est nettement pas du même monde. Moi en local, j'ai trouvé les conditions turbulentes et encore une fois, quand je m'aventures vers Castalebiague/Montastruc, je ne trouve rien que je puisse exploiter. Vivement des conditions à mon niveau pour profiter d'un vrai beau vol !
A34: 1 | B34: 1204 | C34: 45050 | D34: Sigma 11 | E34: Pyrénées | F34: Planot | G34: Navette | I34: La Coume - Rocépy | J34: Cross | K34: Flux de NE | L34: 2000 | M34: 0.48541667 | N34: 180 | O34: =O33+N34/60 -> 56.35 | P34: 34.4 | Q34: Décidémment du vent toujours du vent. Du coup l'idé était de partir plein Ouest, mais au col du Ho, je suis très bas et je suis obligé de revenir vers l'Est pour me refaire. Ce que j'arrive à faire, mais je n'ai pas assez de motivation pour me lancer dans la traversée de la Garonne, du coup je tente le retour à Arbas. Ca ce passe à peu près bien sauf à partir de Paloumère ou je suis trop contré par l'Est et je pose àa la Coume ou Pas de l'Ane, le bien nommé. J'ai fais les 2 derniers kms depuis Paloumère à finesse 5 avec des varios plutot corrects, mais vraiment trop de vent. Thierry S. me voyant en difficulté passera par Caoubeich et le nord de Pène Nère, mais de son propre aveu, c'était osé ! Vivement des conditions plus facile....
A35: 1 | B35: 1205 | C35: 45052 | O35: =O34+N35/60 -> 56.35 | Q35: Recyckage Biplaceurs Profil avec Laurent Pradères à la pente ecol de Moulis.
A36: 1 | B36: 1206 | C36: 45054 | D36: BGD Dual 40 | E36: Pyrénées | F36: Relais | G36: Navette | H36: 350 | I36: Arbas | J36: Local | M36: 0.47916667 | N36: 4 | O36: =O35+N36/60 -> 56.416667 | Q36: Le plafond restant désepéremment bas, on décide de décoller du Relais. Juste un peu d'air. Je lache mes avants trop tôt, pas de de tempo. Attéro assez bien, mais avec les commandes prisent en poiognée, impossible de "percer" et d'arreyter complétement le bi
A37: 1 | B37: 1207 | C37: 45054 | D37: BGD Dual 40 | E37: Pyrénées | F37: Planot | G37: Navette | H37: 700 | I37: Arbas | J37: Local | M37: 0.54166667 | N37: 11 | O37: =O36+N37/60 -> 56.6 | Q37: Un peu mieux coté accompagnement des avants, mais pas de tempo. Quelques exrcicespour Quentin. Attéro impeccable
A38: 1 | B38: 1208 | C38: 45054 | D38: BGD Dual 40 | E38: Pyrénées | F38: Planot | G38: Navette | H38: 700 | I38: Arbas | J38: Local | M38: 0.58333333 | N38: 67 | O38: =O37+N38/60 -> 57.716667 | Q38: Déco, mieux, mais toujours pas vraiment de tempo/contrôle. Vol thermique dot une partie par Quentin. Attéro impeccable…. Au moins ça je maitrise.
A39: 1 | B39: 1209 | C39: 45072 | D39: Sigma 11 | E39: Pyrénées | F39: Planot | I39: Arbas | J39: Local | M39: 0.51875 | N39: 179 | O39: =O38+N39/60 -> 60.7
A40: 1 | B40: 1210 | C40: 45072 | D40: Gin Fuse | E40: Pyrénées | F40: Planot | G40: Navette | I40: Arbas | J40: Local | M40: 0.69444444 | N40: 34 | O40: =O39+N40/60 -> 61.266667 | Q40: Prise en main Fuse avec Sophie
A41: 1 | B41: 1211 | C41: 45073 | D41: Gin Fuse | E41: Pyrénées | F41: Planot | G41: Navette | I41: Arbas | J41: Local | M41: 0.53472222 | N41: 47 | O41: =O40+N41/60 -> 62.05 | Q41: Pas une grande réussite ce bi avec Sophie, on a pas réussi à s'extraire, les conditions etaient maigrichonnes
A42: 1 | B42: 1212 | C42: 45079 | D42: Sigma 11 | E42: Pyrénées | F42: Planot | G42: Navette | I42: Arbas | J42: Local | M42: 0.42708333 | N42: 116 | O42: =O41+N42/60 -> 63.983333
A43: 1 | B43: 1213 | C43: 45080 | D43: Sigma 11 | E43: Pyrénées | F43: Planot | G43: Navette | I43: Arbas | J43: Local | M43: 0.45833333 | N43: 71 | O43: =O42+N43/60 -> 65.166667
A44: 1 | B44: 1214 | C44: 45081 | D44: Sigma 11 | E44: Pyrénées | F44: Planot | G44: Navette | I44: Arbas | J44: Local | M44: 0.48611111 | N44: 65 | O44: =O43+N44/60 -> 66.25
A45: 1 | B45: 1215 | C45: 45082 | D45: Sigma 11 | E45: Pyrénées | F45: Planot | G45: Navette | I45: Arbas | J45: Local | M45: 0.42777778 | N45: 103 | O45: =O44+N45/60 -> 67.966667 | Q45: Parti avec Denis, on se jette un peu n'importe comment vers le col de Larrieu, il pose assez rapidement. De mon coté, sortie épique depuis le bout de la crête du Toas coté Rouède. Un grand moment de plaisir de pilotage à gratter dans du pas grand-chose.
A46: 1 | B46: 1216 | C46: 45093 | D46: Sigma 11 | E46: Pyrénées | F46: Planot | G46: Navette | I46: Arbas | J46: Local | M46: 0.51388889 | N46: 119 | O46: =O45+N46/60 -> 69.95
A47: 1 | B47: 1217 | C47: 45094 | D47: BGD Dual 40 | E47: Pyrénées | F47: Planot | G47: Navette | I47: Arbas | J47: Local | M47: 0.54861111 | N47: 60 | O47: =O46+N47/60 -> 70.95
A48: 1 | B48: 1218 | C48: 45100 | D48: Sigma 11 | E48: Pyrénées | F48: Planot | G48: Navette | I48: Arbas | J48: Local | L48: 1284 | M48: 0.52083333 | N48: 67 | O48: =O47+N48/60 -> 72.066667 | Q48: Toujours des conditions maigrelettes. Parti quasi en dernier du groupe et vu la couverture nuageuse sur Bourrusse/Soulan, je pars directement vers les Irrigaudes. Bien m'en prend puisque j'arrive à m'en sortir et je vais vers Mane puisque seule la plaine est ensoleillée. Je butte contre trop de brise du coté de la pente école de Thierry à Castelbiague. J'arrive une pau par miracle à revenir vers le relief qui va jusqu'au relais et je glisse peu à peu vers Arbas. Je me pose juste avant le village il me manquait qques dizaines de mètres. Vol déprimant !
A49: 1 | B49: 1219 | C49: 45105 | D49: Sigma 11 | E49: Pyrénées | F49: Planot | G49: Rando | H49: 700 | I49: Lacave | J49: Cross | L49: 1450 | M49: 0.51388889 | N49: 147 | O49: =O48+N49/60 -> 74.516667 | P49: 32 | Q49: D'avoir raté mon 1er déco, je suis parti au bon moment. En effet, en sortant du déco, j'ai vu Bourrus tout à l'ombre et Fred qui galéré et qui d'ailleurs est allé se poser. Du coup, je suis parti vers l'Est et j'ai trouvé une ascendance sympa au dessus de Labaderque. J'ai filé vers les seuls endroits encore un peu au soleil, Càd Les Irriguades et j'ai de nouveau trouvé de quoi monter. Sentant une tendance Ouest assez prononcée, je suis parti vers l'Estelas. Bien m'en a pris, j'ai retrouvé quelque chose et après un passage au dessu du déco de Cazavet, j'ai commencé à me rapprocher de la plaine. J'ai fini quasi au dessus de l'aérodrome d'Antichan. J'ai alors commencé une espèce de retour, face au vent de NO. Dur !!! A perine 25/30 kmh et des thermiques bien couchés. J'ai quand même "survécu" comme ça jusqu'à Lacave, entre Prat Bonrepeau et His. Finalement ça m'a fait un bien joli vol et une belle expérience en plaine face au vent.
A50: 1 | B50: 1220 | C50: 45114 | D50: Sigma 11 | E50: Pyrénées | F50: Cornudère | G50: Rando | H50: 400 | I50: Arbas | J50: Local | M50: 0.51319444 | N50: 103 | O50: =O49+N50/60 -> 76.233333
A51: 1 | B51: 1221 | C51: 45115 | D51: Sigma 11 | E51: Pyrénées | F51: Planot | G51: Navette | I51: Urau | J51: Local | L51: 1627 | M51: 0.53958333 | N51: 105 | O51: =O50+N51/60 -> 77.983333
A52: 1 | B52: 1222 | C52: 45121 | D52: BGD Dual 40 | E52: Pyrénées | F52: Planot | G52: Navette | I52: Arbas | J52: Local | M52: 0.49166667 | N52: 10 | O52: =O51+N52/60 -> 78.15 | Q52: Avec Max, fils de Yann Aubertin
A53: 1 | B53: 1223 | C53: 45121 | D53: BGD Dual 40 | E53: Pyrénées | F53: Planot | G53: Navette | I53: Arbas | J53: Local | L53: 1307 | M53: 0.57638889 | N53: 60 | O53: =O52+N53/60 -> 79.15 | Q53: Avec Quentin
A54: 1 | B54: 1224 | C54: 45124 | D54: BGD Dual 40 | E54: Pyrénées | F54: Planot | G54: Navette | I54: Arbas | J54: Local | L54: 1421 | M54: 0.52569444 | N54: 40 | O54: =O53+N54/60 -> 79.816667 | Q54: Avec Quentin
A55: 1 | B55: 1225 | C55: 45129 | D55: Sigma 11 | E55: Pyrénées | F55: Planot | G55: Navette | I55: Montgaillard | J55: Cross | L55: 1448 | M55: 0.50763889 | N55: 108 | O55: =O54+N55/60 -> 81.616667 | Q55: Enfin un peu de plaine au départ du Planot vers Mane. Dommage que je ne fasse pas mieux !
A56: 1 | B56: 1226 | C56: 45130 | D56: Sigma 11 | E56: Pyrénées | F56: Planot | G56: Navette | I56: Arbas | J56: Local | M56: 0.45138889 | N56: 30 | O56: =O55+N56/60 -> 82.116667 | Q56: Avec Quentin qui enroule de son coté à Bourrus alors que je vais un A/R à Soulan.
A57: 1 | B57: 1227 | C57: 45130 | D57: BGD Dual 40 | E57: Pyrénées | F57: Planot | G57: Navette | I57: Arbas | J57: Local | M57: 0.52083333 | N57: 67 | O57: =O56+N57/60 -> 83.233333
A58: 1 | B58: 1228 | C58: 45133 | D58: BGD Dual 40 | E58: Pyrénées | F58: Val Louron | G58: Navette | I58: Loudenvielle | J58: Local | L58: 2588 | M58: 0.52430556 | N58: 90 | O58: =O57+N58/60 -> 84.733333 | Q58: Quentin a fait 2 vols avant, du 300 et du 600. On sort facilement un petit A/R sur la crête vers Arreau, On repasse par le déco pour aller vers la station et le rocher des vautours. On tente et arrête une transition vers Peyragude, on revient vers le déco, mais il est trop tard et la brise a pris le dessus, plus moyen de sortir.
A59: 1 | B59: 1229 | C59: 45134 | D59: Sigma 11 | E59: Pyrénées | F59: Planot | G59: Navette | I59: Arbas | J59: Local | M59: 0.54930556 | N59: 62 | O59: =O58+N59/60 -> 85.766667
A60: 1 | B60: 1230 | C60: 45135 | D60: Sigma 11 | E60: Pyrénées | F60: Planot | G60: Navette | I60: Arbas | J60: Local | M60: 0.56458333 | N60: 21 | O60: =O59+N60/60 -> 86.116667
A61: 1 | B61: 1231 | C61: 45145 | D61: Sigma 11 | E61: Pyrénées | F61: Planot | G61: Navette | I61: Arbas | J61: Cross | L61: 1670 | M61: 0.54166667 | N61: 210 | O61: =O60+N61/60 -> 89.616667 | P61: 32 | Q61: Enfin un beau vol cette année. Arrivé tard pour cause de rdV medcical de Réjane, je décolle finalement a bon moment quand les nuages se dispersent. Des A/R d'un coté à l'autre, Pène Nère, Herbes Blanches, et pour la 1re fois je vais presque à Mane, Poetrie Clarous, et retour.
A62: 1 | B62: 1232 | C62: 45146 | D62: Sigma 11 | E62: Pyrénées | F62: Planot | G62: Rando | H62: 700 | I62: Arbas | J62: Cross | L62: 1350 | M62: 0.51527778 | N62: 204 | O62: =O61+N62/60 -> 93.016667
A63: 1 | B63: 1233 | C63: 45149 | D63: Sigma 11 | E63: Pyrénées | F63: Planot | I63: Arbas | J63: Local | M63: 0.55555556 | N63: 24 | O63: =O62+N63/60 -> 93.416667 | Q63: Vol écourté pour aller débrancher Cédric sous Bourrusse.
A64: 1 | B64: 1234 | C64: 45150 | D64: Sigma 11 | E64: Pyrénées | F64: Planot | G64: Navette | I64: Arbas | J64: Local | M64: 0.45555556 | N64: 33 | O64: =O63+N64/60 -> 93.966667 | Q64: 360 à -8
A65: 1 | B65: 1235 | C65: 45150 | D65: Sigma 11 | E65: Pyrénées | F65: Planot | G65: Navette | I65: Arbas | J65: Local | M65: 0.53888889 | N65: 23 | O65: =O64+N65/60 -> 94.35
A66: 1 | B66: 1236 | C66: 45150 | D66: Sigma 11 | E66: Pyrénées | F66: Planot | G66: Navette | I66: Arbas | J66: Local | M66: 0.61041667 | N66: 11 | O66: =O65+N66/60 -> 94.533333
A67: 1 | B67: 1237 | C67: 45151 | D67: Sigma 11 | E67: Pyrénées | F67: Planot | G67: Navette | I67: Arbas | J67: Local | M67: 0.59097222 | N67: 10 | O67: =O66+N67/60 -> 94.7 | Q67: Wings pluot bien appuyés.
A68: 1 | B68: 1238 | C68: 45151 | D68: Sigma 11 | E68: Pyrénées | F68: Planot | G68: Navette | I68: Arbas | J68: Local | M68: 0.64305556 | N68: 8 | O68: =O67+N68/60 -> 94.833333 | Q68: Essai de fermeture asymétrique, droite et gauche, maintenu à gauche. La voile est très facile à géfrer elle dérive, glisse vers le coté ouvert.
A69: 1 | B69: 1239 | C69: 45152 | D69: BGD Dual 40 | E69: Pyrénées | F69: Planot | G69: Navette | I69: Arbas | J69: Local | M69: 0.49166667 | N69: 16 | O69: =O68+N69/60 -> 95.1 | Q69: Avec Charlotte, ex belle sœur de Ricau et donc tante de Lucia
A70: 1 | B70: 1240 | C70: 45152 | D70: BGD Dual 40 | E70: Pyrénées | F70: Planot | G70: Navette | I70: Arbas | J70: Local | M70: 0.54652778 | N70: 17 | O70: =O69+N70/60 -> 95.383333 | Q70: Avec Sophie
A71: 1 | B71: 1241 | C71: 45157 | D71: Sigma 11 | E71: Pyrénées | F71: M. Bellaygues | G71: Rando | H71: 200 | I71: Arbas | J71: Local | M71: 0.79791667 | N71: 20 | O71: =O70+N71/60 -> 95.716667
A72: 1 | B72: 1242 | C72: 45158 | D72: Sigma 11 | E72: Pyrénées | F72: Planot | G72: Navette | I72: Arbas | J72: Local | M72: 0.53333333 | N72: 126 | O72: =O71+N72/60 -> 97.816667
A73: 1 | B73: 1243 | C73: 45159 | D73: Sigma 11 | E73: Pyrénées | F73: Val Louron | G73: Navette | I73: Loudenvielle | J73: Cross | L73: 3300 | M73: 0.54305556 | N73: 161 | O73: =O72+N73/60 -> 100.5 | P73: 45 | Q73: Sortie rapide et vue le plaf, 3800, je pars directement vers Espiaube ou je reprenbds peu à peu vers le Pic d'Arrouye
A74: 1 | B74: 1244 | C74: 45161 | D74: Sigma 11 | E74: Pyrénées | F74: Val Louron | G74: Navette | I74: Loudenvielle | J74: Cross | L74: 4265 | M74: 0.51180556 | N74: 186 | O74: =O73+N74/60 -> 103.6 | P74: 50 | Q74: Plus à l'aise que le vol précédent, mais que d'engagements sur ces vols en montagne. Mais perché à plus de 4000 au dessus du Perdiguères, la vie à une sacrée saveur.
A75: 1 | B75: 1245 | C75: 45162 | D75: Sigma 11 | E75: Pyrénées | F75: Planot | G75: Navette | I75: Arbas | J75: Local | L75: 1900 | M75: 0.58333333 | N75: 115 | O75: =O74+N75/60 -> 105.51667 | Q75: Retour de Val Louron ou le sud rentre. Vol assez difficile au début et de plus en plus facile au point qu'inquiet des cumulus au sud, je préfère aller poser
A76: 1 | B76: 1246 | C76: 45169 | D76: Sigma 11 | E76: Pyrénées | F76: Planot | G76: Navette | I76: Arbas | J76: Cross | L76: 1600 | M76: 0.52083333 | N76: 185 | O76: =O75+N76/60 -> 108.6 | Q76: Une tendance NO et pas mal d'instabilité donne un vol assez mouvementé, disons 2/4 dans mon échelle. Passage sympa à la Husse avec le tour de Pène Nère. Et après un passage au relais, cap l'Estelas depuis Herbes Blanches. Beau plaf qui me permet de rentrer plutot bien placé, du coté du hameau à l'Est du relais.
A77: 1 | B77: 1247 | C77: 45170 | D77: Sigma 11 | E77: Pyrénées | F77: Cornudère | G77: Rando | H77: 500 | I77: Arbas | J77: Local | L77: 1624 | M77: 0.53125 | N77: 30 | O77: =O76+N77/60 -> 109.1 | Q77: Avec Jan-Seb on apu décoller en face sud, mais pas de quoi sortir. Et coté nord c'était la panade.
A78: 1 | B78: 1248 | C78: 45175 | D78: Sigma 11 | E78: Pyrénées | F78: Planot | G78: Rando | H78: 700 | I78: Arbas | J78: Cross | L78: 1664 | M78: 0.58194444 | N78: 146 | O78: =O77+N78/60 -> 111.53333 | Q78: Après une sortie difficile de Bourrus, beau tour de bocal + A/R à l'Estelas avc un retour par Herbes Blanches.
A79: 1 | B79: 1249 | C79: 45176 | D79: Sigma 11 | E79: Pyrénées | F79: Planot | G79: Rando | H79: 700 | I79: Arbas | J79: Cross | L79: 1711 | M79: 0.5375 | N79: 66 | O79: =O78+N79/60 -> 112.63333 | Q79: A 1700 à la Husse, je tente le Cagire, suivi par Samy et Victor, mais nous n'arrrvions pas à sortir de Plaède. Je tnet le tour du relief et peut-être qu'au dessus de Juzet c'est jouable. A réessayer.
A80: 1 | B80: 1250 | C80: 45177 | D80: Sigma 11 | E80: Pyrénées | F80: Planot | G80: Navette | I80: Milhas | J80: Cross | L80: 1830 | M80: 0.53611111 | N80: 186 | O80: =O79+N80/60 -> 115.73333 | Q80: Difiicile tout le long, en particulier au pied du Cagire ou Mitch ne ressort pas, et surtout au retour ou après avoir été longtemps planté au Picon, j'échoue d'un rien devant le Col de la Husse. Après débrieffing avec Syvlain Gatini, j'ai visé la mauvais passage, j'aurai du aller sous le vent du Pic de la Husse, je ne lme serai pas fais enterré. Tant pis, une fois la frustration passée, ça reste un sacré beau vol
A81: 7 | B81: 1257 | C81: 45178 | D81: BGD Dual 40 | E81: Pyrénées | F81: Planot | G81: Navette | I81: Arbas | J81: Local | N81: 128 | O81: =O80+N81/60 -> 117.86667 | Q81: Fête du club Profil
A82: 6 | B82: 1263 | C82: 45179 | D82: BGD Dual 40 | E82: Pyrénées | F82: Planot | G82: Navette | I82: Arbas | J82: Local | N82: 133 | O82: =O81+N82/60 -> 120.08333 | Q82: Fête du club Profil : Natha, Je t’avais emmené voler en parapente il y a quelques années, je ne savais pas, Tu n’es pas un garçon ordinaire, en fait je ne sais pas grand-chose de toi. Hier soir, je t’ai vu et je t’ai proposé de voler de nouveau. Tu m’as répondu, oui. On a fixé le programme, décoller, monter, se donner des sensations, peut-être 10 minutes, peut-être plus, on était d’accord. On s’est élancé, avec un peu de chance on est monté, au plus ça bougeait, au plus tu aimais. On est allé où c’était pas gagné, on s’est fait un peu secouer, à chaque fois que je t’ai demandé si ça allait, tu m’as répondu « Oui ». Juste : Oui J’ai aimé cette simplicité, oui, non, je connais, j’aime, ou pas … Pas de filtre, pas de faux semblant. Une forme de pureté. On aurait pu passer le reste de notre vie, à monter, descendre, se faire secouer, se déplacer, voler. On est pourtant revenu sur terre, non sans nous donner le maximum de sensations que je pouvais. A droite, à gauche, plus haut, plus fort, plus puissant, rien ne te gênait, tu appréciais tout. Si j’avais su le faire, nous nous serions offert des figures, plus fortes, plus extrêmes, plus violentes. Je ne suis qu’un pilote normal, j’ai fait tout ce que je pouvais. Je devais aussi te ramener à ceux qui t’aiment, j’ai fait ce que je savais faire, pas plus, pardon. Nata, tu m’as donné mon plus beau vol en biplace, autant d’émotions je n’en avais pas connu. J’espère que tu as eu aussi du plaisir, en fait j’aimerai que tu es eu beaucoup, immensément de plaisir, je ne le saurai jamais, pas grave, j’ai fait tout ce que j’ai pu, j’ai respecté notre plan de vol, décoller, monter, se donner des sensations. Merci Natha, à bientôt.
A83: 1 | B83: 1264 | C83: 45183 | D83: Sigma 11 | E83: Pyrénées | F83: Planot | G83: Navette | I83: Arbas | J83: Local | M83: 0.55069444 | N83: 51 | O83: =O82+N83/60 -> 120.93333
A84: 1 | B84: 1265 | C84: 45184 | D84: Sigma 11 | E84: Pyrénées | F84: Planot | G84: Navette | I84: Arbas | J84: Local | M84: 0.54305556 | N84: 34 | O84: =O83+N84/60 -> 121.5
A85: 1 | B85: 1266 | C85: 45185 | D85: BGD Dual 40 | E85: Pyrénées | F85: Planot | G85: Navette | I85: Arbas | J85: Local | M85: 0.53055556 | N85: 15 | O85: =O84+N85/60 -> 121.75 | Q85: Avec Quentin, impossible de tenir à Bourrus, alosr on s'envoie quelques figures;
A86: 1 | B86: 1267 | C86: 45185 | D86: Sigma 11 | E86: Pyrénées | F86: Planot | G86: Navette | I86: Arbas | J86: Local | M86: 0.57361111 | N86: 124 | O86: =O85+N86/60 -> 123.81667
A87: 1 | B87: 1268 | C87: 45186 | D87: Sigma 11 | E87: Pyrénées | F87: Planot | G87: Navette | I87: Arbas | J87: Local | M87: 0.52430556 | N87: 20 | O87: =O86+N87/60 -> 124.15 | Q87: C'était pas plus mal que ça ne tienne pas, vers 15h une belle entrée de sud à l'attéro.
A88: 1 | B88: 1269 | C88: 45187 | D88: Sigma 11 | E88: Pyrénées | F88: Planot | G88: Navette | I88: Arbas | J88: Cross | L88: 1780 | M88: 0.52291667 | N88: 115 | O88: =O87+N88/60 -> 126.06667 | P88: 24 | Q88: Pas facile sous 1100m, dynamique et un peu agité au dessus, pas de Sud, plutot du NO jusqu'au plaf à environ 1750. Beau passage entre le Relais, l'Estelas et retour.
A89: 1 | B89: 1270 | C89: 45188 | D89: Sigma 11 | E89: Pyrénées | F89: Planot | G89: Rando | H89: 700 | I89: Arbas | J89: Cross | L89: 15 | M89: 0.52430556 | N89: 70 | O89: =O88+N89/60 -> 127.23333 | P89: 20 | Q89: Efficace et rapide, passage à la Husse, Moutagnat, Erigade, encore un cum sur la colline au dessus de la pente école, et puis plus rien jusqu'à la Poertie Clarous.
A90: 1 | B90: 1271 | C90: 45195 | D90: Sigma 11 | E90: Pyrénées | F90: Planot | I90: Arbas | N90: 19 | O90: =O89+N90/60 -> 127.55
A91: 1 | B91: 1272 | C91: 45197 | D91: Sigma 11 | E91: Pyrénées | F91: Val Louron | I91: Genos | J91: Cross | L91: 2865 | M91: 0.52430556 | N91: 136 | O91: =O90+N91/60 -> 129.81667 | P91: 30 | Q91: Flux de sud rendant le vol désagréable, limite malsain.
A92: 1 | B92: 1273 | C92: 45199 | D92: Sigma 11 | E92: Pyrénées | F92: Planot | G92: Rando | H92: 700 | I92: Arbas | N92: 144 | O92: =O91+N92/60 -> 132.21667 | Q92: En compagnis de Quentin.
A93: 1 | B93: 1274 | C93: 45201 | D93: Sigma 11 | E93: Pyrénées | F93: Val Louron | I93: Genos | J93: Cross | L93: 3715 | M93: 0.52083333 | N93: 255 | O93: =O92+N93/60 -> 136.46667 | P93: 70 | Q93: Enfin de belles conditions qui permettent un très beau cross de 70 km, le triangle FAI de Michel D. par Espiaube - Grand Quayrat - Mt Né. Un grand régal en compagnie de Gd Mitch qui fait mieux que moi de qque centaines de mètres, de Jean-Marc que j'aide bien et qui me quitte au dessus du Val d'Aube, de Sophie qui reste plus dans le bocal mais qu'on retrouve perchée à 3200 au cap des Hittes, de Pascal Caunègre, d'Hervé Belloc ... vraiment un super vol.
A94: 1 | B94: 1275 | C94: 45204 | D94: Névada 2 -24 | E94: Pyrénées | F94: Planot | G94: Rando | H94: 700 | I94: Arbas | J94: Cross | L94: 1580 | M94: 0.56597222 | N94: 145 | O94: =O93+N94/60 -> 138.88333 | P94: 20 | Q94: Pas facile de reprendre la Névada, elle bouge dans tout les sens. Mais au bout de peut-être 1h, ça allait mieux et j'ai même réussi à aller à l'Estelas et … revenir. C'est la 1ere fois que je reviens si bas. En plus ça bougeait pas mal !
A95: 1 | B95: 1276 | C95: 45205 | D95: Névada 2 -24 | E95: Pyrénées | F95: Planot | I95: Arbas | J95: Local | M95: 0.53055556 | N95: 113 | O95: =O94+N95/60 -> 140.76667
A96: 1 | B96: 1277 | C96: 45206 | D96: Névada 2 -24 | E96: Pyrénées | F96: Cornudère | G96: Rando | H96: 400 | I96: Arbas | J96: Local | M96: 0.57638889 | N96: 79 | O96: =O95+N96/60 -> 142.08333
A97: 1 | B97: 1278 | C97: 45207 | D97: Névada 2 -24 | E97: Pyrénées | F97: M. Bellaygues | G97: Rando | H97: 200 | I97: Arbas | J97: Local | M97: 0.6 | N97: 70 | O97: =O96+N97/60 -> 143.25
A98: 1 | B98: 1279 | C98: 45209 | D98: Névada 2 -24 | E98: Pyrénées | F98: Planot | G98: Navette | I98: Arbas | J98: Cross | L98: 1873 | M98: 0.53958333 | N98: 183 | O98: =O97+N98/60 -> 146.3 | P98: 25
A99: 1 | B99: 1280 | C99: 45210 | D99: Névada 2 -24 | E99: Pyrénées | F99: Planot | G99: Navette | I99: Arbas | J99: Local | M99: 0.53819444 | N99: 107 | O99: =O98+N99/60 -> 148.08333
A100: 1 | B100: 1281 | C100: 45214 | D100: Névada 2 -24 | E100: Espagne Algodonales | F100: Poniente | G100: Navette | I100: Poniente | J100: Local | M100: 0.54722222 | N100: 31 | O100: =O99+N100/60 -> 148.6
...

Sheet 2022
A1: Compt | B1: N° Vol | C1: Date | D1: Voile | E1: Région | F1: Déco | G1: Acc. | H1: Dén. | I1: Attéro | J1: Type de vol | K1: Météo | L1: A1 max | M1: Heure décollage (locale) | N1: Durée | O1: Durée cumulée | P1: Dist | Q1: Rmq
A2: 1 | C2: 44598 | D2: Nevada 2 - 24 | E2: Pyrénées | F2: Mancioux | Q2: Gonflage 1h
A3: 1 | B3: 1128 | C3: 44601 | D3: Nevada 2 - 24 | E3: Pyrénées | F3: Planot | G3: Navette | I3: Sengouagnet | J3: Cross | K3: Anticyclonique | L3: 1900 | M3: 0.45833333 | N3: 75 | O3: =(O2+N3/60) -> 1.25 | P3: 10 | Q3: J'étais parti pour un plouf de reprise et voolià que ça sort facilement devant le déco. Facile à La Husse aussi ou après un premier plaf à 1700 et une oincursion vers Caoubeich, je fais 1900. Tentative rapidement avortée vers le Cagire>. Je ne trouve rien de rien à Plaède. retour galèe avec une bonne dizaine de kms à pieds !*
A4: 1 | B4: 1129 | C4: 44602 | D4: Nevada 2 - 24 | E4: Pyrénées | F4: Cornudère | G4: Rando | H4: 400 | I4: Sengouagnet | J4: Cross | K4: Anticyclonique | L4: 2300 | M4: 0.48611111 | N4: 67 | O4: =(O3+N4/60) -> 2.3666667 | P4: 10 | Q4: On part à une dizaine de Cornudère faxce sud, d’où il est très facile de s'extraire. Je fais le plaf à Paloumère avec 2300 et j'arrive en face Est du Cagire. Mais rien. Un peu peu plus bas je me suis battu pendant une bonne demi heure à Plaède, mais ça n'etéiat pas assez fort pour moi. retour facile en 2 stop !
A5: 1 | B5: 1130 | C5: 44615 | D5: Nevada 2 - 24 | E5: Pyrénées | F5: Planot | G5: Rando | H5: 700 | I5: Arbas | J5: Local | L5: 1450 | M5: 0.52083333 | N5: 105 | O5: =(O4+N5/60) -> 4.1166667
A6: 1 | B6: 1131 | C6: 44629 | D6: Nevada 2 - 24 | E6: Pyrénées | F6: Planot | G6: Rando | H6: 700 | I6: Arbas | J6: Local | L6: 1660 | M6: 0.52083333 | N6: 93 | O6: =(O5+N6/60) -> 5.6666667
A7: 1 | B7: 1132 | C7: 44643 | D7: Nevada 2 - 24 | E7: Pyrénées | F7: Planot | G7: Navette | I7: Arbas | J7: Local | L7: 1600 | M7: 0.49305556 | N7: 129 | O7: =(O6+N7/60) -> 7.8166667
A8: 1 | B8: 1133 | C8: 44655 | D8: Nevada 2 - 24 | E8: Pyrénées | F8: Planot | G8: Rando | H8: 700 | I8: Arbas | J8: Local | M8: 12 | N8: 9 | O8: =(O7+N8/60) -> 7.9666667 | Q8: Temps couvert, très froid. Les autres réissieenet à tenir, mais pas longtemps à cause du froid, moi je ne trouve rien.
A9: 1 | B9: 1134 | C9: 44656 | D9: Nevada 2 - 24 | E9: Pyrénées | F9: Cornudère | G9: Rando | H9: 400 | I9: Arbas | J9: Local | L9: 1650 | M9: 0.52083333 | N9: 142 | O9: =(O8+N9/60) -> 10.333333 | Q9: On monte à Cornu avec denis, Déco fgace sud, ensuite ça passera nord. Beau vol malgré le frroid, bien cosatud à certains moments, 2 belles grosse fermetures avec début de dépaert en autorit !
A10: 1 | B10: 1135 | C10: 44666 | D10: Nevada 2 - 24 | E10: Pyrénées | F10: Planot | I10: Arbas | J10: Cross | L10: 1860 | M10: 0.5 | N10: 170 | O10: =(O9+N10/60) -> 13.166667 | P10: 20
A11: 1 | B11: 1136 | C11: 44690 | D11: Nevada 2 - 24 | E11: Pyrénées | F11: Planot | I11: Arbas | J11: Cross | L11: 2400 | M11: 0.47916667 | N11: 218 | O11: =(O10+N11/60) -> 16.8 | P11: 43 | Q11: A/R au Pic du Gar avec de l'Est qui m'a rendu compliqué le retour.
A12: 1 | B12: 1137 | C12: 44708 | D12: Nevada 2 - 24 | E12: Pyrénées | F12: Val Louron 700 | I12: Genos | J12: Cross | L12: 2933 | M12: 0.51388889 | N12: 147 | O12: =(O11+N12/60) -> 19.25 | P12: 21 | Q12: Du vent de NE rend les conditions désagréable. Passage à l'Estos, puis Station Peyragude, Mont et retour.
A13: 1 | B13: 1138 | C13: 44709 | D13: Rook 3 MS | E13: Pyrénées | F13: Val Louron 700 | I13: Genos | J13: Cross | L13: 3245 | M13: 0.52083333 | N13: 187 | O13: =(O12+N13/60) -> 22.366667 | P13: 35 | Q13: Très beau vol, conditions parfaites, voile remarquable. Passage par le Pic de Sarrouye, puis Estos, transition vers la face nord de Pichadère, et après un passge bas du coté du Val d'Esquierry, passage par le Hourgade, ensuite plus classique, et retour par le Pic du Lyon.
A14: 1 | B14: 1139 | C14: 44710 | D14: Nevada 2 - 24 | E14: Pyrénées | F14: Val Louron 700 | I14: Genos | J14: Cross | L14: 2667 | M14: 0.49652778 | N14: 124 | O14: =(O13+N14/60) -> 24.433333 | P14: 17 | Q14: Sortie très facile, mais plaf un peu limite. Je renoue avec les photos. Grand moment avec un vautour. Passage à l'Estos par la face nord, quand même engagé, pas trop le droit à l'erreur ! Par contre, c'est grandiose de se coltiner avec cette face.
A15: 1 | B15: 1140 | C15: 44719 | D15: BGD Dual 40 | E15: Pyrénées | F15: Planot | I15: Arbas | J15: Local | N15: 42 | O15: =(O14+N15/60) -> 25.133333 | Q15: biplace
A16: 1 | B16: 1141 | C16: 44729 | D16: BGD Dual 40 | E16: Pyrénées | F16: Planot | I16: Arbas | J16: Local | N16: 11 | O16: =(O15+N16/60) -> 25.316667 | Q16: biplace
A17: 1 | B17: 1142 | C17: 44736 | D17: Nevada 2 - 24 | E17: Pyrénées | F17: Planot | I17: Arbas | J17: Local | N17: 80 | O17: =(O16+N17/60) -> 26.65
A18: 1 | B18: 1143 | C18: 44740 | D18: Sigma 11 - 24 | E18: Pyrénées | F18: Planot | I18: Arbas | J18: Local | N18: 51 | O18: =(O17+N18/60) -> 27.5 | Q18: Essai 1 Sigma 11
A19: 1 | B19: 1144 | C19: 44741 | D19: BGD Dual 40 | E19: Pyrénées | F19: Planot | I19: Arbas | J19: Local | N19: 46 | O19: =(O18+N19/60) -> 28.266667 | Q19: Biplace
A20: 1 | B20: 1145 | C20: 44750 | D20: Sigma 11 - 24 | E20: Pyrénées | F20: Planot | I20: Arbas | J20: Local | N20: 57 | O20: =(O19+N20/60) -> 29.216667 | Q20: Essai 2 Sigma11
A21: 1 | B21: 1146 | C21: 44750 | D21: BGD Dual 40 | E21: Pyrénées | F21: Planot | I21: Arbas | J21: Local | N21: 57 | O21: =(O20+N21/60) -> 30.166667 | Q21: Biplace
A22: 1 | B22: 1147 | C22: 44797 | D22: Nevada 2 - 24 | E22: Pyrénées | F22: Planot | I22: Arbas | J22: Local | L22: 1600 | M22: 0.52083333 | N22: 157 | O22: =(O21+N22/60) -> 32.783333 | Q22: Reprise … encor une ! Sans vario qu'il va bien falloir changer ! Des hats et des bas dans des conditions un peu toniques. Mais globalement bon vol !
A23: 1 | B23: 1148 | C23: 44808 | D23: BGD Dual 40 | E23: Pyrénées | F23: Planot | I23: Arbas | J23: Local | M23: 0.4375 | N23: 15 | O23: =(O22+N23/60) -> 33.033333 | Q23: Bi avec Quentin
A24: 1 | B24: 1149 | C24: 44808 | D24: BGD Dual 40 | E24: Pyrénées | F24: Planot | I24: Arbas | J24: Local | M24: 0.5 | N24: 15 | O24: =(O23+N24/60) -> 33.283333 | Q24: Bi avec Quentin
A25: 1 | B25: 1150 | C25: 44808 | D25: BGD Dual 40 | E25: Pyrénées | F25: Planot | I25: Arbas | J25: Local | M25: 0.5625 | N25: 15 | O25: =(O24+N25/60) -> 33.533333 | Q25: Bi avec Quentin
A26: 1 | B26: 1151 | C26: 44808 | D26: BGD Dual 40 | E26: Pyrénées | F26: Herran | I26: Arbas | J26: Local | M26: 0.75 | N26: 15 | O26: =(O25+N26/60) -> 33.783333 | Q26: Bi avec Quentin depuis Herran à l'occasion de la commémoration de Michel Belaygues
A27: 1 | B27: 1152 | C27: 44809 | D27: Sigma 11 - 24 | E27: Pyrénées | F27: Planot | I27: Arbas | J27: Local | K27: Sud-ouest fort en altitude, quasi pas d'ascendence | M27: 0.5625 | N27: 17 | O27: =(O26+N27/60) -> 34.066667
A28: 1 | B28: 1153 | C28: 44810 | D28: Sigma 11 - 24 | E28: Pyrénées | F28: Planot | I28: Arbas | J28: Local | K28: Sud-ouest léger en altitude, tout Arbas donne super bien. | M28: 0.52083333 | N28: 204 | O28: =(O27+N28/60) -> 37.466667 | Q28: 1er vol de référence avec la Sigma11 qui est … parfaite. Jene lui trouve aucun défaut. Du coup je vais l'acheter à Thierry.
A29: 5 | B29: 1154 | C29: 44814 | D29: BGD Dual 40 | E29: Pyrénées | F29: Planot | I29: Arbas | J29: Local | N29: 100 | O29: =(O28+N29/60) -> 39.133333 | Q29: Fête du club,
A30: 6 | B30: 1155 | C30: 44815 | D30: BGD Dual 40 | E30: Pyrénées | F30: Planot | I30: Arbas | J30: Local | N30: 60 | O30: =(O29+N30/60) -> 40.133333 | Q30: Fête du club,
A31: 1 | B31: 1156 | C31: 44818 | D31: BGD Dual 40 | E31: Pyrénées | F31: Planot | I31: Arbas | J31: Local | L31: 1700 | M31: 0.58333333 | N31: 57 | O31: =(O30+N31/60) -> 41.083333 | Q31: Avec Quentin, juste après un fort coup de sud de 3 jours, le matin il y avait encore 30/40 de sud à Cornu.
A32: 1 | B32: 1157 | C32: 44819 | D32: Sigma 11 - 24 | E32: Pyrénées | F32: Planot | G32: Navette | I32: Arbas | J32: Local | M32: 0.41666667 | N32: 13 | O32: =(O31+N32/60) -> 41.3 | Q32: Je vole juste après Quentin dont c'est le 1er vol. Même pas vraiment d'émotion, aucun stress, comme quoi la confiance…
A33: 1 | B33: 1158 | C33: 44819 | D33: Sigma 11 - 24 | E33: Pyrénées | F33: Planot | G33: Navette | I33: Arbas | J33: Local | L33: 1800 | M33: 0.48611111 | N33: 97 | O33: =(O32+N33/60) -> 42.916667 | Q33: Joli balade avec un peu de turbulences, va falloir s'en occuper de la Sigma11 ! Mais qu'est-ce que ça vole !
A34: 1 | B34: 1159 | C34: 44823 | D34: Sigma 11 - 24 | E34: Pyrénées | F34: Planot | G34: Rando | H34: 700 | I34: Arbas | J34: Local | L34: 1580 | M34: 0.55 | N34: 143 | O34: =(O33+N34/60) -> 45.3 | Q34: Bon choix pour le creneau de decollage, comme quoi les prévis, ça a du bon. Cette Sigma 11 est étonnante, certes ça vie et il faut s'en occuper, mais que de belles qualités de vol. Après la Husse un peu sous le vent, je raccroche aux Iriguades et peu à peu je remoonte jusqu'à Herbes Blanches, sûr que je n'aurai pas réussi avec la Névada. Ensuite d enouveau un tout en plaine du coté de Chein Dessus où miracle je trouve une ascendence.Cette Sigma 11 m'pouvre de nouveau horizons. Super !!!
A35: 1 | B35: 1160 | C35: 44825 | D35: Sigma 11 - 24 | E35: Pyrénées | F35: Planot | I35: Arbas | J35: Local | L35: 1732 | M35: 0.57430556 | N35: 127 | O35: =(O34+N35/60) -> 47.416667
A36: 1 | B36: 1161 | C36: 44826 | D36: Sigma 11 - 24 | E36: Pyrénées | F36: Planot | G36: Rando | H36: 700 | I36: Arbas | J36: Cross | L36: 1512 | M36: 0.55555556 | N36: 164 | O36: =(O35+N36/60) -> 50.15 | P36: 25 | Q36: Mponté à pieds avant le vol en 1h05, la forme revient. Je profite de l'expérience d'hier et après un passage à la Husse, puis le Mountagnat, je transite vace la crête Relais/Herbes blanches. Bien m'en prend, peu à peu je rejoins Hrbes Blan,ches. Les conditions sont propoices à tenter l'Estelas, que j'atteins après un thermique dans la combe Ouest du massif. et que je retrouve après un A/R jusqu'au relais. Le retour est facile, même si je n'arrive pas à faire les beaux plafs que d'autres font au relais.
A37: 1 | B37: 1162 | C37: 44839 | E37: Pyrénées | I37: Arbas | J37: Local | N37: 25 | O37: =(O36+N37/60) -> 50.566667
A38: 1 | B38: 1163 | C38: 44844 | E38: Pyrénées | F38: Planot | G38: Rando | H38: 700 | I38: Arbas | J38: Local | N38: 22 | O38: =(O37+N38/60) -> 50.933333
A39: 1 | B39: 1164 | C39: 44849 | D39: Sigma 11 - 24 | E39: Pyrénées | F39: Cornudère | G39: Rando | H39: 1100 | I39: Arbas | J39: Local | N39: 93 | O39: =(O38+N39/60) -> 52.483333 | Q39: Quand je suis arrivé s'était Nord contrairement aux préis qui me faiaient espérer décoller en Sud. Du temps de me préparer, il y a eu 2 passage scoté Sud. Du coup j'y suis allé. Mal m'en pris, après un déco raté qui a failli tourner mal, du temps de remonter vers ma voile, un dust a pris ma voile et je me suis fait trainer sur 3/4 m, juste de quoi taper du genou dans un rocher. Momralité, j'ai eu de la chance, beaucoup de chance !*
A40: 1 | B40: 1165 | C40: 44850 | D40: Sigma 11 - 24 | E40: Pyrénées | F40: Planot | G40: Navette | I40: Arbas | J40: Local | N40: 29 | O40: =(O39+N40/60) -> 52.966667
A41: 1 | B41: 1166 | C41: 44851 | D41: Sigma 11 - 24 | E41: Espagne Nord | F41: Ager - Gabriello | G41: Navette | I41: Ager | J41: Local | K41: Flux de Sud Est | L41: 1980 | M41: 0.71527778 | N41: 127 | O41: =(O40+N41/60) -> 55.083333 | Q41: Ce sera le vol de l'année. Décollage du Gabriello dans des conditions un peu marginale avec une forte tendance est, je commence par merder avec un gros point bas parceque je me bagarre avec mon matos, vario éteint au déco… Ensuite je réussi à rejoindre le gros de la troupe et coup de chance, quand je les rejoins, l'ascendance s'arréte et en décallant un peu sur l'arrière j'arrive à raccorcher de petits thermiques qui me font peu àpeu rejoindre jean et Thierry sur la barre rocheuse supérieure. Là trop facile, même si contré par 10/15 d'Est, on va jusqu'au bout de la Sierra, ascendance jusqu'au nuage, même un peu dedans.... on revient à trois, on refait un A/R en attendant les parapotes qui reviennent au Gabriello pour un second vol, photos, vautours, coucher de soleil, tout y est pour un vol grandiose>.
A42: 1 | B42: 1167 | C42: 44852 | D42: Sigma 11 - 24 | E42: Espagne Nord | F42: ager - Mt Elis | G42: Navette | I42: Ager | J42: Local | K42: Flux de Sud Est | L42: 1780 | M42: 0.83680556 | N42: 111 | O42: =(O41+N42/60) -> 56.933333 | Q42: Un peu holdup celui là de vol, en sortant du déco de St Elis, je me colle au relief à gauche et un peu contrée mais suffisamment serien, je chemine vers l'Est. Ca monte doucement tout le temps, jusqu'au bout de la Sierra, souvcent un peu bas et proche des falaises pour etre vraiment serein, mais ça va et pas de mauvaise surprise. Des vautours partout et la sarisfactiobn d'être le seul du jour à faire ce vol. La Sigma y est pour beaucoup dans cette réussite, plané, finesse, vitesse, solidité, confiance, quel bon choix.
A43: 1 | B43: 1168 | C43: 44852 | D43: Sigma 11 - 24 | E43: Espagne Nord | F43: Ager - Gabriello | G43: Navette | I43: Ager | J43: Local | K43: Flux de Sud Est | N43: 18 | O43: =(O42+N43/60) -> 57.233333
A44: 1 | B44: 1169 | C44: 44853 | D44: Sigma 11 - 24 | E44: Espagne Nord | F44: ager -g | G44: Navette | I44: Ager | J44: Local | K44: Arrivée de la perturbation par le SO | N44: 9 | O44: =(O43+N44/60) -> 57.383333
A45: 1 | B45: 1170 | C45: 44853 | D45: Sigma 11 - 24 | E45: Espagne Nord | F45: Ager - Gabriello | G45: Navette | I45: Ager | J45: Local | K45: Arrivée de la perturbation par le SO | N45: 8 | O45: =(O44+N45/60) -> 57.516667
A46: 1 | B46: 1171 | C46: 44881 | D46: Nevada 2 - 24 | E46: Pyrénées | F46: Cornudère | G46: Rando | H46: 1100 | I46: Arbas | J46: Local | K46: Sud Ouest en altitude | L46: 2087 | M46: 0.54861111 | N46: 54 | O46: =(O45+N46/60) -> 58.416667 | Q46: Enfin une vraie montée rando depuis l'attéro jusqu'à Cornu … avec un sac léger et sans secours…. Début difficile poyr se réaclimater avec la sellette et la Névada. En fait j'ai enfilé la sellette à l'envers du coup, j'étais tout coincé. En A/R sur la crête sud de cornu, puis route jusqu'à Herbes Blanches par la face sud qui redonne régulièrement, plus de 1800 depuis Piscatel . C'est la 1ere fois que j'ai cette vue sur la vallée de Castillon. Ca donne envie de continuer, mais entre l'incofort de la selletrte, le son du vario qui m'agresse et le froid, je préfère aller posé. J'ai du faire le bon chgois, Olivier Grimoux n'a pas réussi à revenir de l'Estelas.
A47: 1 | B47: 1172 | C47: 44976 | D47: Nevada 2 - 24 | E47: Pyrénées | F47: Cornudère | G47: Rando | H47: 1100 | I47: Arbas | J47: Local | N47: 15 | O47: =(O46+N47/60) -> 58.666667 | Q47: Finalement il y avait un voile qui a rédit le vol à un plouf, tout de douceurs.

Sheet 2021
A1: Compt | B1: N° Vol | C1: Date | D1: Voile | E1: Région | F1: Déco | G1: Acc. | H1: Dén. | I1: Attéro | J1: Type de vol | K1: Météo | L1: A1 max | M1: Heure décollage (locale) | N1: Durée | O1: Durée cumulée | P1: Dist | Q1: Rmq
A2: 0 | C2: 44230 | D2: Nevada 2 - 24 | F2: La Ramée | J2: Gonflage | K2: Nord super 17 kmh à Blagnac | Q2: 30
A3: 1 | B3: 1075 | C3: 44231 | D3: Nevada 2 - 24 | E3: Pyrénées | F3: Planot | G3: Rando | H3: 700 | I3: Arbas | J3: Local | M3: 0.54166667 | N3: 8 | O3: =(O2+N3/60) -> 0.13333333 | Q3: Venu à Arabs pour voir le montage du carbu de la tondeuse, finalement je monte la voile en C15, redescend, remonte à pied 1h10 environ et fais le 1er vol de l'année. Ouf…
A4: 1 | B4: 1076 | C4: 44231 | D4: Nevada 2 - 24 | E4: Pyrénées | F4: Planot | G4: Navette | I4: Arbas | J4: Local | M4: 0.5625 | N4: 8 | O4: =(O3+N4/60) -> 0.26666667 | Q4: Frace à Ivan et sa femme, je peux faire un 2ièmle vol.
A5: 1 | B5: 1077 | C5: 44250 | D5: Nevada 2 - 24 | E5: Pyrénées | F5: Cornudère | G5: Rando | H5: 1100 | I5: Arbas | J5: Local | K5: Flux de sud | L5: 1670 | M5: 0.52083333 | N5: 100 | O5: =(O4+N5/60) -> 1.9333333 | Q5: Sacré plaisir à retrouver la moontée à Cornudère. Le saxc sur le dos uniquement depuis la pkg de la fontaine de l'ours. En haut un peu de sud, genre 10/15 kmh et des ascendances bizarres sur la face sud. Du coup je ne traine pas et je bascule vers Soulan ou il y avait de quoi jouer un bon moment.
A6: 1 | B6: 1078 | C6: 44251 | D6: Nevada 2 - 24 | E6: Pyrénées | F6: Planot | G6: Navette | I6: Arbas | J6: Local | K6: Flux de sud | L6: 1000 | M6: 0.54166667 | N6: 70 | O6: =(O5+N6/60) -> 3.1 | Q6: Trop mal partout pour remarcher, du coup je fais soft et j'abandonne assez rapidement Soulan, plaf trop faible et trops de monde. Quelques exercices habituels, bien en tangage;
A7: 1 | B7: 1079 | C7: 44252 | D7: Nevada 2 - 24 | E7: Pyrénées | F7: Planot | G7: Navette | I7: Arbas | J7: Local | K7: Flux de NO | M7: 0.52083333 | N7: 15 | O7: =(O6+N7/60) -> 3.35 | Q7: Décollé trop tot, avec Michel et son Exos on ne reussi pas à tenir à Soulan.
A8: 1 | B8: 1080 | C8: 44252 | D8: Nevada 2 - 24 | E8: Pyrénées | F8: Planot | G8: Navette | I8: Arbas | J8: Local | K8: Flux de NO | L8: 1400 | M8: 0.5625 | N8: 90 | O8: =(O7+N8/60) -> 4.85 | Q8: Par contre cette fois c'est mieux, rien à Bourrus ou Michel Delahuerta se fait enterré alors qu;à Soulan ça fonctionne plutot bien. Remontée jusqu'à la Husse, moi je talonne un peu, mais 2 voiles basculent vers Paloumère. Le plus beau et sympa des ces premiers vols de l'année.
A9: 1 | B9: 1081 | C9: 44258 | D9: Nevada 2 - 24 | E9: Pyrénées | F9: Planot | G9: Rando | H9: 700 | I9: Arbas | J9: Local | N9: 15 | O9: =(O8+N9/60) -> 5.1 | Q9: Le ciel était baché, du coup je suis monté à pied et j'ai décollé après tout le monde, je n'ai pas su exploiter les maigres ascendences, alors que d'autre ont volé jusqu'à 2 heures… la prochaine fois …
A10: 1 | B10: 1082 | C10: 44259 | D10: Nevada 2 - 24 | E10: Pyrénées | F10: Cornudère | G10: Rando | H10: 400 | I10: Arbas | J10: Local | L10: 1980 | M10: 0.5625 | N10: 150 | O10: =(O9+N10/60) -> 7.6 | Q10: On pensais tenter notre chance faces sud de Cornu, mais il y avait un vrai flux de N, NE qui s'est renforcé dans l'après midi. Du coup décollage nord. Au début la vallée d'arbas est à l'ombre et ça ne tient qu'au moutagnat. Ensuite ça c'est ouvert; Je fais le nuage à l'Husse. Passage à Herbe Blanches et au bout de la crête au NE du relais. Bref un grand tour du bocal bien sympa.
A11: 1 | B11: 1083 | C11: 44278 | D11: BGD Dual 40 | E11: Pyrénées | F11: Planot | G11: Navette | I11: Arbas | J11: Local | N11: 11 | O11: =(O10+N11/60) -> 7.7833333 | Q11: Reprise du bi. Trop de stress et d'oublies, dont la non vérification du réglage des trims. Trim dont la poignée de commende casse. L'essentiel est sauvagarder, déco correct et attéro idem, même si arrondi tardif
A12: 1 | B12: 1084 | C12: 44279 | D12: Nevada 2 - 24 | E12: Pyrénées | F12: Planot | G12: Navette | I12: Arbas | J12: Local | N12: 12 | O12: =(O11+N12/60) -> 7.9833333
A13: 1 | B13: 1085 | C13: 44279 | D13: Nevada 2 - 24 | E13: Pyrénées | F13: Planot | G13: Navette | I13: Arbas | J13: Local | K13: Flux de No | N13: 90 | O13: =(O12+N13/60) -> 9.4833333 | Q13: Du froid, un peu de vent, un secours face sud de cornu me font abandonner rapidement.
A14: 1 | B14: 1086 | C14: 44285 | D14: Nevada 2 - 24 | E14: Pyrénées | F14: Planot | G14: Navette | I14: Arbas | J14: Cross | K14: Flux de So | L14: 2200 | M14: 11 | N14: 52 | O14: =(O13+N14/60) -> 10.35 | P14: 15 | Q14: Bon début et joli plaf à la Husse. Contré en SO, j'arrive bien placé à Plaède, mais je ne trouve rien. Je tente les faces NO au dessus de Juzet, mais rien. Michel Delahuerta est comme moi.
A15: 1 | B15: 1087 | C15: 44288 | D15: Nevada 2 - 24 | E15: Pyrénées | F15: Planot | G15: Rando | H15: 700 | I15: Arbas | J15: Local | K15: Flux de SE | N15: 20 | O15: =(O14+N15/60) -> 10.683333 | Q15: Conditions de nSE que je ne connaissais pas. Je décolle avec le voile et ne trouve pas grand-chose. Bourrus n'est pas sain. Vince ecourtera son vol. Par contre je remonte à pied en grand forme, je coupe le grand A/R sur le nord du bas de Bourrus et je monte en moins d'1h. Mon record
A16: 1 | B16: 1088 | C16: 44293 | D16: Nevada 2 - 24 | E16: Pyrénées | F16: Planot | G16: Rando | H16: 700 | I16: Arbas | J16: Local | K16: Tendance NE | L16: 1800 | M16: 0.47916667 | N16: 63 | O16: =(O15+N16/60) -> 11.733333 | Q16: Conditions de merde. Un froid de cabnard, probablement 0° à 1500 m.Vent de Est ou NE, très désagréable. Je fais l'effort de durer pour atteeindre l'heure de vol.
A17: 1 | B17: 1089 | C17: 44294 | D17: Nevada 2 - 24 | E17: Pyrénées | F17: Planot | I17: Arbas | J17: Local | K17: Tendance NE | M17: 0.4375 | N17: 11 | O17: =(O16+N17/60) -> 11.916667
A18: 1 | B18: 1090 | C18: 44294 | D18: Nevada 2 - 24 | E18: Pyrénées | F18: Planot | G18: Rando | H18: 700 | I18: Arbas | J18: Local | K18: Tendance NE | L18: 1400 | M18: 0.51736111 | N18: 92 | O18: =(O17+N18/60) -> 13.45
A19: 1 | B19: 1091 | C19: 44336 | D19: Nevada 2 - 24 | E19: Pyrénées | F19: Planot | G19: Navette | I19: Arbas | J19: Local | M19: 0.5 | N19: 13 | O19: =(O18+N19/60) -> 13.666667 | Q19: Plutot merdique dont une approche au radada des arbres et un posé en virage…. Bouhhhhh…
A20: 1 | B20: 1092 | C20: 44336 | D20: Nevada 2 - 24 | E20: Pyrénées | F20: Planot | G20: Navette | I20: Arbas | J20: Local | L20: 1450 | M20: 0.54166667 | N20: 97 | O20: =(O19+N20/60) -> 15.283333 | Q20: Mieux de bout en bout. Des bons thermiques des bonnes senstations de belle vues sur les reliefs tout vert … berf beaucoup de plaisir.
A21: 1 | B21: 1093 | C21: 44343 | D21: Nevada 2 - 24 | E21: Pyrénées | F21: Planot | G21: Rando | I21: Arbas | J21: Local | O21: =(O20+N21/60) -> 15.283333
A22: 1 | B22: 1094 | C22: 44344 | D22: Nevada 2 - 24 | E22: Pyrénées | F22: Planot | G22: Rando | I22: Arbas | J22: Local | M22: 0.52083333 | N22: 140 | O22: =(O21+N22/60) -> 17.616667
A23: 1 | B23: 1095 | C23: 44350 | D23: Nevada 2 - 24 | E23: Pyrénées | F23: Planot | G23: Navette | I23: Arbas | J23: Local | M23: 0.58333333 | N23: 10 | O23: =(O22+N23/60) -> 17.783333
A24: 1 | B24: 1096 | C24: 44355 | D24: Nevada 2 - 24 | E24: Pyrénées | F24: Planot | G24: Rando | H24: 700 | I24: Arbas | J24: Local | L24: 2150 | M24: 0.51041667 | N24: 120 | O24: =(O23+N24/60) -> 19.783333 | Q24: Super vol, thermique en sortie de déco, François me montre la voie pour l'optimiser, il part de la husse pour le Cagire, je reste dans le bocal. Bon choix, je me refais bien sur la crête derrière Pène Blanque, je trouve la porte de sortie au dessus de RocetPy, ce qui me permet de prendre les thermiques face sud, génial. ensuite Toute la crête facile jusqu'à Herbes Blanches, en insistant un peu je trouve le thermique pour rentrer par le Relais. Que du bon. Youpiii.
A25: 1 | B25: 1097 | C25: 44357 | D25: Nevada 2 - 24 | E25: Pyrénées | F25: Planot | G25: Navette | I25: Arbas | J25: Local | K25: Flux de NE 10 kmh | L25: 1750 | M25: 0.51041667 | N25: 195 | O25: =(O24+N25/60) -> 23.033333 | Q25: J'espérais mieux , mais finalement je m'en sors plutot bien vu les conditions. Les cums des faces sud débordant dans la bocal, de nombreuses zones d'ombres ont un peu gachés la journée. Pas si grave, vol bien maitrisé malgrés quelques cisaillements et turbulences.
A26: 1 | B26: 1098 | C26: 44360 | D26: BGD Dual 40 | E26: Pyrénées | F26: Planot | G26: Rando | H26: 700 | I26: Arbas | J26: Local | L26: 2050 | M26: 0.54166667 | N26: 75 | O26: =(O25+N26/60) -> 24.283333 | Q26: Dommafge que Quentin est le mal de l'air, on était parti pour le cagire. Pas grave, le point de vue à 2000 au dessus de la Husse valait le déplacement. Super retout par la crête paloumère Cornudère.
A27: 1 | B27: 1099 | C27: 44361 | D27: Nevada 2 - 24 | E27: Pyrénées | F27: Planot | G27: Navette | I27: Arbas | J27: Cross | K27: Flux de Nord 10 kmh | L27: 2200 | M27: 0.51041667 | N27: 175 | O27: =(O26+N27/60) -> 27.2 | P27: 45 | Q27: Ahhh ça faisait longtemps que je n'avais pas fait un vol comme clui là. Jamais facile mais avec de belles conditions. Beaucoup de mal à sortir au Cagire à l'aller, je zone du coté de la crête nord aux environs de 1400, je finis par sortir en décallant vers le NO. Je pense que les thermiques étaient soufflés en NO dans cette zone. Ensuite beuaocup plus facile, je reprends juste un thermique au Pic de Gar, le retour vers le Cagire est un peu compliquée, heureusement je me refait au thermique de la carrière. Au retour, je raccroché sous Paloumère, c'est plus facile ! Ensuite je passe avec chance au Sud de la cabanne de Rocépi. Le plateau est sous le vent !!! La fin est top facile, 1800 à herbes blanche, relais ....
A28: 1 | B28: 1100 | C28: 44368 | D28: Nevada 2 - 24 | E28: Pyrénées | F28: Planot | I28: Arbas | J28: Local | N28: 30 | O28: =(O27+N28/60) -> 27.7
A29: 1 | B29: 1101 | C29: 44378 | D29: Nevada 2 - 24 | E29: Pyrénées | F29: Planot | G29: Rando | H29: 700 | I29: Arbas | J29: Local | N29: 148 | O29: =(O28+N29/60) -> 30.166667 | Q29: Long passage d'un voile d'altitude qui me fait rester à Soulan, mais avec beaucoup deplaisir car beaucoup de vautours, a un moment j'enroule avec une bonne vingtaine d'entre eux. C'est la première fois que je vole avec autant d'oiseaux et aussi près.
A30: 1 | B30: 1102 | C30: 44382 | D30: Nevada 2 - 24 | E30: Pyrénées | F30: Planot | G30: Navette | I30: Arbas | J30: Local | K30: Retour d'Est | L30: 1500 | M30: 0.50347222 | N30: 185 | O30: =(O29+N30/60) -> 33.25 | Q30: Décidemment ce vent d'Est est agacant; De belles ascendences quand même.
A31: 1 | B31: 1103 | C31: 44394 | D31: BGD Dual 40 | E31: Pyrénées | F31: Herran | G31: Rando | H31: 150 | I31: Arbas | J31: Local | N31: 50 | O31: =(O30+N31/60) -> 34.083333 | Q31: Décidemment après 45' environ, Quentin ne sent pas bien. Pas grave, on était scotché entre Herran et Piscatel, rien de génial
A32: 1 | B32: 1104 | C32: 44396 | D32: Nevada 2 - 24 | E32: Pyrénées | F32: Planot | G32: Navette | I32: Arbas | J32: Local | K32: vent de ord | L32: 2000 | M32: 0.57986111 | N32: 126 | O32: =(O31+N32/60) -> 36.183333 | Q32: Début difficile à Bourrus, mais je finis pas réussir à sortir, direction La Husse pour le plaf du jour. Passage par Rocépy, Cornu, un 1er passage raté à Piscatel, reprise difficile au Mountagnat sous le vent, finalement ça monte très devant et Herbe blanche est une formalité.Par contre aller jusqu'au Relais n'est pas facile, bien contré. Condtions plutot turbulentes.
A33: 1 | B33: 1105 | C33: 44397 | D33: BGD Dual 40 | E33: Pyrénées | F33: Planot | G33: Navette | I33: Arbas | J33: Local | N33: 60 | O33: =(O32+N33/60) -> 37.183333
A34: 1 | B34: 1106 | C34: 44398 | D34: Nevada 2 - 24 | E34: Pyrénées | F34: Planot | G34: Rando | H34: 700 | I34: Arbas | J34: Local | N34: 105 | O34: =(O33+N34/60) -> 38.933333
A35: 1 | B35: 1107 | C35: 44417 | D35: Nevada 2 - 24 | E35: Pyrénées | F35: Planot | G35: Navette | I35: Arbas | J35: Local | N35: 155 | O35: =(O34+N35/60) -> 41.516667
A36: 1 | B36: 1108 | C36: 44418 | D36: Nevada 2 - 24 | E36: Pyrénées | F36: Cornudère | G36: Rando | H36: 400 | I36: Arbas | J36: Local | N36: 78 | O36: =(O35+N36/60) -> 42.816667
A37: 1 | B37: 1109 | C37: 44428 | D37: Nevada 2 - 24 | E37: Pyrénées | F37: Planot | G37: Navette | N37: 21 | O37: =(O36+N37/60) -> 43.166667
A38: 1 | B38: 1110 | C38: 44432 | D38: Nevada 2 - 24 | E38: Pyrénées | F38: Cornudère | G38: Rando | H38: 700 | I38: Ural | J38: Cross | K38: Vent de Nord | L38: 2000 | M38: 0.54166667 | N38: 71 | O38: =(O37+N38/60) -> 44.35 | P38: 18 | Q38: Le piémont se couvrant rapidement depuis le sud, je suis monté à Corbudère depuis le Planot pour accroché Soulan. En effet ça a fonctionné. Mais ensuite plus grand-chose, jusquà un bon thermique presque à l'attéro. Je fis 2000 à Herran du coup je pars vers l'est. Demi tour à Saleich, et posé à Ural. Retour à pieds.
A39: 1 | B39: 1111 | C39: 44433 | D39: Nevada 2 - 24 | E39: Pyrénées | F39: Planot | G39: Navette | I39: Arbas | J39: Local | K39: Vent d'Est léger | L39: 1720 | M39: 0.51736111 | N39: 215 | O39: =(O38+N39/60) -> 47.933333 | Q39: Enfin un beau vol. De belles ascendances, un peu de vent d'Esty qui complique les choses, beaucoup de plaisir !!
A40: 5 | B40: 1116 | C40: 44443 | D40: BGD Dual 40 | E40: Pyrénées | F40: Planot | G40: Navette | I40: Arbas | J40: Local | N40: 50 | O40: =(O39+N40/60) -> 48.766667 | Q40: Fête du club. Laura Sanchez 50kg Heidi Rivera 60kg Michel Girodo 80kg Patricia Camilleri 55kg Mélodie Rouch 70kg
A41: 6 | B41: 1122 | C41: 44444 | D41: BGD Dual 40 | E41: Pyrénées | F41: Planot | G41: Navette | I41: Arbas | J41: Local | N41: 60 | O41: =(O40+N41/60) -> 49.766667 | Q41: Lana Chotard 35kg Cedrine Rouch 20kg Erine Bibas 65kg Patrice Matray 74kg Elina Nedjari 60kg Isaline Bech 67kg
A42: 1 | B42: 1123 | C42: 44451 | D42: Nevada 2 - 24 | E42: Pyrénées | F42: Planot | G42: Navette | I42: Arbas | J42: Local | N42: 130 | O42: =(O41+N42/60) -> 51.933333
A43: 1 | B43: 1124 | C43: 44456 | D43: Nevada 2 - 24 | E43: Pyrénées | F43: Planot | G43: Rando | H43: 700 | I43: Arbas | J43: Local | N43: 112 | O43: =(O42+N43/60) -> 53.8
A44: 1 | B44: 1125 | C44: 44470 | D44: Nevada 2 - 24 | E44: Pyrénées | F44: Planot | G44: Navette | I44: Arbas | J44: Local | N44: 10 | O44: =(O43+N44/60) -> 53.966667
A45: 1 | B45: 1126 | C45: 44470 | D45: Nevada 2 - 24 | E45: Pyrénées | F45: Planot | G45: Rando | H45: 700 | I45: Arbas | J45: Local | N45: 10 | O45: =(O44+N45/60) -> 54.133333
A46: 1 | B46: 1127 | C46: 44481 | D46: Nevada 2 - 24 | E46: Pyrénées | F46: Planot | G46: Rando | H46: 800 | I46: Arbas | J46: Local | N46: 47 | O46: =(O45+N46/60) -> 54.916667
A47: 1 | B47: 1128 | C47: 44482 | D47: Nevada 2 - 24 | E47: Pyrénées | F47: Planot | G47: Navette | I47: Arbas | J47: Local | N47: 34 | O47: =(O46+N47/60) -> 55.483333

Sheet 2020
A1: Compt | B1: N° Vol | C1: Date | D1: Voile | E1: Région | F1: Déco | G1: Acc. | H1: Dén. | I1: Attéro | J1: Type de vol | K1: Météo | L1: A1 max | M1: Heure décollage (locale) | N1: Durée | O1: Durée cumulée | P1: Dist | Q1: Rmq
A2: 1 | C2: 43849 | D2: Nevada 2 - 24 | F2: La Ramée | J2: Gonflage | K2: Nord forcissant | Q2: 30
A3: 1 | B3: 1012 | C3: 43853 | D3: Nevada 2 - 24 | E3: Pyrénées | F3: Cornudère | G3: Rando | H3: 1100 | I3: Arbas | J3: Local | K3: Flux de sud | L3: 1700 | M3: 13h | N3: 62 | O3: =(O2+N3/60) -> 1.0333333
A4: 1 | B4: 1013 | C4: 43864 | D4: Nevada 2 - 24 | E4: Pyrénées | F4: Herran | G4: Rando | H4: 250 | I4: Arbas | J4: Local | L4: 1400 | M4: 12h40 | N4: 105 | O4: =(O3+N4/60) -> 2.7833333 | Q4: Je pensais qu'il y aurait de l'ouest alors je suis allé à Herran. Petite brisounette de NE au déco. Directeion la ppe à Cham qui eatait bien anémique au début. J'ai fini par trouvé une bonne pompe qui m'a monté à 1350, du coup j'ai rejoins le troupeau qui était installé à Soulan. Ou ça n'tait pas si bon. Du coup retour au Mountagnat via un plein à Bourrus. Super thermique comme ça faisait longtemps pour le plaf du jour 1400. Diection Les Irigades ou je trouve un thermqiue sous le vent et bien couché en Est. Etonnant. Je tente de suivre La Zéno de Philou, mais là ou il raccroche au Moutnagant, je suis obligé de controurné le relief par le nord, j'arrive sous la crête et je n'arrive pas à sortir. Beau vol, serein, sans pensée parasite. Bien !!!
A5: 1 | B5: 1014 | C5: 43866 | D5: Nevada 2 - 24 | E5: Pyrénées | F5: Planot | I5: Arbas | J5: Local | N5: 210 | O5: =(O4+N5/60) -> 6.2833333
A6: 1 | B6: 1015 | C6: 43867 | D6: Nevada 2 - 24 | E6: Pyrénées | F6: Herran | G6: Rando | H6: 1300 | I6: Arbas | J6: Local | N6: 12 | O6: =(O5+N6/60) -> 6.4833333
A7: 1 | B7: 1016 | C7: 43885 | D7: Nevada 2 - 24 | E7: Pyrénées | F7: Planot | I7: Arbas | J7: Local | N7: 9 | O7: =(O6+N7/60) -> 6.6333333
A8: 1 | B8: 1017 | C8: 43885 | D8: Nevada 2 - 24 | E8: Pyrénées | F8: Planot | I8: Arbas | J8: Local | N8: 30 | O8: =(O7+N8/60) -> 7.1333333
A9: 1 | C9: 43897 | D9: Nevada 2 - 24 | F9: La Ramée | J9: Gonflage | K9: Ouest 15 à Blagnac | O9: =(O8+N9/60) -> 7.1333333 | Q9: 90
A10: 1 | B10: 1018 | C10: 43905 | D10: Nevada 2 - 24 | E10: Pyrénées | F10: Planot | H10: 700 | I10: Arbas | J10: Local | N10: 13 | O10: =(O9+N10/60) -> 7.35 | Q10: Conditions trop petites pour moi.
A11: 1 | B11: 1019 | C11: 43905 | D11: Nevada 2 - 24 | E11: Pyrénées | F11: Planot | I11: Arbas | J11: Local | N11: 66 | O11: =(O10+N11/60) -> 8.45 | Q11: Toujours de petites conditions, trop bu hier soir, ça me rend malade, une bonne 1/2 heure pour m'en remettre à l'attéro.
A12: 1 | B12: 1020 | C12: 43969 | D12: Nevada 2 - 24 | E12: Pyrénées | F12: Planot | H12: 700 | I12: Arbas | J12: Local | N12: 105 | O12: =(O11+N12/60) -> 10.2
A13: 1 | B13: 1021 | C13: 43971 | D13: Nevada 2 - 24 | E13: Pyrénées | F13: Planot | H13: 700 | I13: Arbas | J13: Local | N13: 31 | O13: =(O12+N13/60) -> 10.716667 | Q13: Total incompréhension de la masse d'air, complétement à coté de la plaque, alors que tout le monde vol bien et loin (Cagire), je reste planté en local.
A14: 1 | B14: 1022 | C14: 43971 | D14: Nevada 2 - 24 | E14: Pyrénées | F14: Planot | I14: Arbas | J14: Local | N14: 11 | O14: =(O13+N14/60) -> 10.9 | Q14: Idem, Quelle frustration !
A15: 1 | B15: 1023 | C15: 43972 | D15: Nevada 2 - 24 | E15: Pyrénées | F15: Cornudère | H15: 1100 | I15: Arbas | J15: Local | N15: 74 | O15: =(O14+N15/60) -> 12.133333 | Q15: Un peu moins bien que la veille, au moins je réussi à rester un peu en l'air. Je m'énerve contre un suiveur ce qui me fait fuir trop tot vers le relais.
A16: 1 | B16: 1024 | C16: 43972 | D16: Nevada 2 - 24 | E16: Pyrénées | F16: Herran | H16: 800 | I16: Arbas | J16: Local | N16: 56 | O16: =(O15+N16/60) -> 13.066667 | Q16: Après 1900 m de dénivelé dans la journéée dont 700 avec le sac, un vol un peu plus apaisé
A17: 1 | B17: 1025 | C17: 43973 | D17: Nevada 2 - 24 | E17: Pyrénées | F17: Cornudère | H17: 1100 | I17: Arbas | J17: Local | N17: 109 | O17: =(O16+N17/60) -> 14.883333 | Q17: Le 1er vol à peu près normal de la semaine, un peu court, mais en revenat du trelais vers le mountagnat je suis un peu bas et je ne me bats pas assez sous le vent de la brise dans le thermique à Cham.
A18: 1 | B18: 1026 | C18: 43977 | D18: Nevada 2 - 24 | E18: Pyrénées | F18: Planot | I18: Cornudère | J18: Local | M18: 0.47916667 | N18: 50 | O18: =(O17+N18/60) -> 15.716667 | Q18: Plafonds trop bas, pour partir vers le Cagire, après un beau thermique au dessus du déco, je vais me poser à Cornu
A19: 1 | B19: 1027 | C19: 43977 | D19: Nevada 2 - 24 | E19: Pyrénées | F19: Cornudère | I19: Arbas | J19: Cross | L19: 1950 | M19: 0.51041667 | N19: 110 | O19: =(O18+N19/60) -> 17.55 | Q19: Dcéo de cornu avec pas mal de vent, cette fois je pars de la Husse à 1850 vers le Cagire, je raccorhce miraculeusement sous plaède. Beau passage au Cagire, A/R assez facile au Pic de Gar. Par contre de retour vers 1800 en face NO du Cagire, alors que jcherche à grapiller le plaf pour assurer ma transition, en quelques minutes, plus rien, je perds tout et me pose àa la vierge de sengougnet. Quelle rage !
A20: 1 | B20: 1028 | C20: 43978 | D20: Nevada 2 - 24 | E20: Pyrénées | F20: Planot | G20: Rando | H20: 700 | I20: Arbas | J20: Local | L20: 1900 | M20: 12 | N20: 142 | O20: =(O19+N20/60) -> 19.916667 | Q20: Enfin un vol correct, même si je me fais beaucopup balader sous la voile…. Mais de beaux thermiques, un beau passage à Corbudère, une belle sortie à Herbe blanche .. Vol sans erreurs, ni stress. Ouf. Je sais encore faire….
A21: 1 | B21: 1029 | C21: 43979 | D21: Nevada 2 - 24 | E21: Pyrénées | F21: Planot | I21: Rocépie | J21: Cross | L21: 2200 | M21: 0.53125 | N21: 160 | O21: =(O20+N21/60) -> 22.583333 | Q21: Et voilà un vol de référence. Malgès 1500 m de plafond sur Arbas, je réussi à prendre 1950 sur la bordure Ouest du nuage à la Husse. Du coup raccrochage facile à Plaède, montée ay Cagire sans problème. En partant vers l'Ouest, beau thermique pour le plaf du jour 2200m. Je pense que c'est la pompe à Richard. Plus dur sur la face nord du Gar, mais je réussi facilement l'A/R. Bon ticket de sortie coté est mais pour une transition difficile vers le parking de ? (Pour monter au Cagire face nord). Thermique atomique probablement un peu sous le vent pour 2000m. Faces Ouest du Cagire j'ai un pau de mal, je ne retrouve pas le plaf et ja pars vers le Picon à2050. J'arrive au dessus du Picon, je fais un A/R au ras des arbres jusqu'au sous paloumère qui me ramène sous le Picon environ 1000m. Là enfin un bon thermique qui me permets de décaler sur la crête direction paloumère. Dans un passage au soleirl je réussi à prendre 1650, je m'en contente et je vais me poser sous Rocépie pour récupérer la voiture au Planot. De toutes façons ce n'était pas suffisant pour passer serenement....
A22: 1 | B22: 1030 | C22: 43980 | D22: GIN Fuse 2 | E22: Pyrénées | F22: Herran | I22: Arbas | J22: Biplace | N22: 30 | O22: =(O21+N22/60) -> 23.083333 | Q22: Avec Louis, un bel A/R à herbes Blanches dans une restitution bien sympa
A23: 1 | B23: 1031 | C23: 43981 | D23: GIN Fuse 2 | E23: Pyrénées | F23: Planot | I23: Arbas | J23: Biplace | N23: 30 | O23: =(O22+N23/60) -> 23.583333 | Q23: Avec Quentin, pas réussi à sortir de Bourrus
A24: 1 | B24: 1032 | C24: 43981 | D24: GIN Fuse 2 | E24: Pyrénées | F24: Planot | I24: Arbas | J24: Biplace | N24: 66 | O24: =(O23+N24/60) -> 24.683333 | Q24: Avec Quentin, cette fois on sort à Bourrus dans un thermique très couché quasi à nous ramener au Planot, la suite plus facile mais Quentin était malade. Le Fuse 2 a trops de mouvement de lacet / roulis
A25: 1 | B25: 1033 | C25: 43981 | D25: GIN Fuse 2 | E25: Pyrénées | F25: Herran | I25: Arbas | J25: Biplace | N25: 20 | O25: =(O24+N25/60) -> 25.016667 | Q25: Vol du soir avec Quentin, trop d'hombre, mais passage sous Bourrus / Pène Blanque bien sympa
A26: 1 | B26: 1034 | C26: 43982 | D26: Bi Golden 4 42 | E26: Pyrénées | F26: Planot | I26: Arbas | J26: Biplace | N26: 120 | O26: =(O25+N26/60) -> 27.016667 | Q26: Avec Quentin et le bi de Thierry. Rien à voir en confort, en plsu avec la sellette Supair Passager du Club, un régal pour la passager. Un peu physique pour moi, Mais machine rassurante, plus facile pour centrer les thermiques, même si peut-être un peu moins perf que le Fuse.
A27: 1 | B27: 1035 | C27: 43997 | D27: Nevada 2 - 24 | E27: Pyrénées | F27: Planot | G27: Rando | H27: 700 | I27: Arbas | J27: Local | N27: 10 | O27: =(O26+N27/60) -> 27.183333 | Q27: Montée à pired, sac en haut, plus personne en haut à midi quand j'arrive et lee voile nuageux se renforce. 9a port bien en l'air mais je ne trouve pas les ascendances que les autres ont trouvés en décollant à 11h30.
A28: 1 | B28: 1036 | C28: 43997 | D28: Nevada 2 - 24 | E28: Pyrénées | F28: Gensac | H28: 80 | I28: Gensac | J28: Local | N28: 2 | O28: =(O27+N28/60) -> 27.216667 | Q28: Sur le retou, mini vole à Gensac où c'est trop faible.
A29: 1 | B29: 1037 | C29: 44003 | D29: Nevada 2 - 24 | E29: Pyrénées | F29: Planot | I29: Arbas | J29: Local | N29: 86 | O29: =(O28+N29/60) -> 28.65 | Q29: vent d'O NO désagréable
A30: 1 | B30: 1038 | C30: 44005 | D30: Nevada 2 - 24 | E30: Pyrénées | F30: Val Louron 700 | I30: Val Louron | J30: Local | L30: 2600 | N30: 118 | O30: =(O29+N30/60) -> 30.616667 | Q30: plafond un peu bas pour profiter vraiment, mais c'est bien sympa de retrouver la montagne
A31: 1 | B31: 1039 | C31: 44006 | D31: GIN Fuse 2 | E31: Pyrénées | F31: Planot | I31: Arbas | J31: Biplace | L31: 2280 | N31: 180 | O31: =(O30+N31/60) -> 33.616667 | Q31: Magnifique vol avec Malika, A/R au Cagire, passage délicat au retour par Paloumère, Herbes blanches.
A32: 1 | B32: 1040 | C32: 44008 | D32: Nevada 2 - 24 | E32: Pyrénées | F32: Planot | I32: Arbas | J32: Local | N32: 21 | O32: =(O31+N32/60) -> 33.966667
A33: 1 | B33: 1041 | C33: 44008 | D33: Nevada 2 - 24 | E33: Pyrénées | F33: Planot | I33: Arbas | J33: Local | N33: 100 | O33: =(O32+N33/60) -> 35.633333
A34: 1 | B34: 1042 | C34: 44016 | D34: BGD Dual 40 | E34: Pyrénées | F34: Herran | I34: Arbas | J34: Biplace | N34: 53 | O34: =(O33+N34/60) -> 36.516667 | Q34: 1er vol avec le Dual de Mumu. Il fait froid, du coup on abrège le vol.
A35: 1 | B35: 1043 | C35: 44017 | D35: BGD Dual 40 | E35: Pyrénées | F35: Planot | I35: Arbas | J35: Biplace | N35: 10 | O35: =(O34+N35/60) -> 36.683333 | Q35: Plouf tranquille avec Louis
A36: 1 | B36: 1044 | C36: 44017 | D36: BGD Dual 40 | E36: Pyrénées | F36: Planot | I36: Arbas | J36: Biplace | N36: 62 | O36: =(O35+N36/60) -> 37.716667 | Q36: Petites conditions hachées, avec Quentin. On abandonne par manque de plaisir.
A37: 1 | B37: 1045 | C37: 44024 | D37: Nevada 2 - 24 | E37: Pyrénées | F37: Planot | I37: Arbas | J37: Local | N37: 15 | O37: =(O36+N37/60) -> 37.966667
A38: 1 | B38: 1046 | C38: 44048 | D38: Nevada 2 - 24 | E38: Pyrénées | F38: Val Louron 700 | G38: Rando | H38: 700 | I38: Val Louron | J38: Cross | K38: Anticyclonique | L38: 2300 | M38: 0.56944444 | N38: 68 | O38: =(O37+N38/60) -> 39.1 | P38: 10
A39: 1 | B39: 1047 | C39: 44049 | D39: Nevada 2 - 24 | E39: Pyrénées | F39: Val Louron 700 | I39: Val Louron | J39: Cross | K39: Anticyclonique flux de sud | L39: 3960 | M39: 0.55208333 | N39: 205 | O39: =(O38+N39/60) -> 42.516667 | P39: 40 | Q39: Après un A/R sur la crête vers Arreau, je retrouve Vince au nord de l'Estos. Ensuite je le suis jusqu'au Spigeolles. On se reperd de vue ensuite. Passage au Pic du Lion et retour.
A40: 1 | B40: 1048 | C40: 44050 | D40: Nevada 2 - 24 | E40: Pyrénées | F40: Val Louron 700 | I40: Val Louron | J40: Cross | K40: Anticyclonique flux de sud | L40: 4100 | M40: 0.52083333 | N40: 246 | O40: =(O39+N40/60) -> 46.616667 | P40: 68 | Q40: Triangle FAI en suivant Michel Delahuerta, facile à l'aller jusqu'à d'Espiaube, transition très chaotique pour revenir à Val louron. Sortie facile du rocher des aigles puis de l'Estos. Transition facile jusqu'au Grand Quayrat. Retour compliqué face à 10/15 d'Ouest. Plus facile pour moi en passant par les pics de Nère et Arrouge, plus difficile pour Michel qui vise directement le Val d'Aube. Retour par le Pic du Lion, toujours aussi peu acceuillant dans son coté sous le vent (Sud)
A41: 1 | B41: 1049 | C41: 44051 | D41: Nevada 2 - 24 | E41: Pyrénées | F41: Cornudère | G41: Rando | H41: 400 | I41: Arbas | J41: Local | L41: 1800 | M41: 0.54166667 | N41: 55 | O41: =(O40+N41/60) -> 47.533333 | Q41: On monte avec Michel bellegarde à Cornu depuis le parking de la fontainie de l'ours. Bien nous en a pris, la face sud donne, mais trop choatique pour rester longtemps.
A42: 1 | B42: 1050 | C42: 44051 | D42: BGD Dual 40 | E42: Pyrénées | F42: Planot | I42: Arbas | J42: Biplace | M42: 0.64583333 | N42: 20 | O42: =(O41+N42/60) -> 47.866667 | Q42: On décolle un peu trop tard, on ne trouve plus rien
A43: 1 | B43: 1051 | C43: 44052 | D43: BGD Dual 40 | E43: Pyrénées | F43: Planot | I43: Arbas | J43: Biplace | M43: 0.48958333 | N43: 10 | O43: =(O42+N43/60) -> 48.033333 | Q43: Cett fois c'est trop tot.
A44: 1 | B44: 1052 | C44: 44052 | D44: BGD Dual 40 | E44: Pyrénées | F44: Planot | I44: Arbas | J44: Biplace | M44: 0.55208333 | N44: 30 | O44: =(O43+N44/60) -> 48.533333 | Q44: Et cette fois, l'activité orgaeuse menace, ça mont trop facilement, nous préférons aller nous poser.
A45: 1 | B45: 1053 | C45: 44054 | D45: Nevada 2 - 24 | E45: Pyrénées | F45: Cornudère | G45: Rando | I45: Arbas | J45: Local | M45: 0.54166667 | N45: 10 | O45: =(O44+N45/60) -> 48.7 | Q45: Rencontre de Steven un Hollandais qui passe quelque jours à Arbas. La veille nous avons fait, Attéro/Déco d'Herran/Planot et descent en stop à cause de la pluis qui arrive. Cette fois, on tente Cornu et on décolle en est… un peu osé, mais ça marche. Il faut du vent, au moins 10 kmh.
A46: 1 | B46: 1054 | C46: 44057 | D46: Nevada 2 - 24 | E46: Pyrénées | F46: Planot | I46: Arbas | J46: Local | N46: 25 | O46: =(O45+N46/60) -> 49.116667
A47: 1 | B47: 1055 | C47: 44058 | D47: Nevada 2 - 24 | E47: Pyrénées | F47: Planot | I47: Arbas | J47: Local | N47: 10 | O47: =(O46+N47/60) -> 49.283333
A48: 1 | B48: 1056 | C48: 44058 | D48: Diamir 2 | E48: Pyrénées | F48: Planot | I48: Arbas | J48: Local | L48: 2000 | N48: 14 | O48: =(O47+N48/60) -> 49.516667 | Q48: 1er vol d'essai avec la Diamir 2 Ex Vincent. A priori RAS
A49: 1 | B49: 1057 | C49: 44068 | D49: Diamir 2 | E49: Pyrénées | F49: Planot | I49: Arbas | J49: Cross | N49: 95 | O49: =(O48+N49/60) -> 51.1 | P49: 20 | Q49: 2nd vol, confirmation de mes impressions de vol des essais de 2017; C'est une super voile, plus amorti et facile à piloter que la Névada. Attention aux basses vitesses.
A50: 1 | B50: 1058 | C50: 44068 | D50: Diamir 2 | E50: Pyrénées | F50: Herran | G50: Rando | H50: 400 | I50: Arbas | J50: Local | N50: 45 | O50: =(O49+N50/60) -> 51.85
A51: 1 | B51: 1059 | C51: 44069 | D51: Nevada 2 - 24 | E51: Pyrénées | F51: Planot | I51: Arbas | J51: Local | N51: 175 | O51: =(O50+N51/60) -> 54.766667
A52: 1 | B52: 1060 | C52: 44070 | D52: Nevada 2 - 24 | E52: Pyrénées | F52: Planot | G52: Rando | H52: 700 | I52: Arbas | J52: Local | K52: Avant l'arrivée d'un front orageux d'Ouest | N52: 180 | O52: =(O51+N52/60) -> 57.766667 | Q52: Des conditions plutot pourries, limite dangeureuse. Des thermiques explosifs mais qui talonne aux alentours de 13000m. Du vent plutot est en début de vol, puis ouest en fin. 3/4 heures après être posé, le vent d'ouest est bien présent et piège 2pilotes aux décos tardifs mais sans conséquence pour eux.
A53: 1 | B53: 1061 | C53: 44075 | D53: Nevada 2 - 24 | E53: Pyrénées | F53: Planot | G53: Rando | H53: 700 | I53: Arbas | J53: Local | K53: Voile d'altitude en SO | L53: 1600 | M53: 0.47916667 | N53: 60 | O53: =(O52+N53/60) -> 58.766667 | Q53: Etrange d'être tout seul au déco, faut dire que la météo n'était pas très optimiste. Finalement v'était plutot dynamique jusqu'à l'arrivée d'un gros voiel nuageux.
B54: 1062 | C54: 44077 | D54: Nevada 2 - 24 | E54: Pyrénées | F54: Planot | I54: Arbas | J54: Local | L54: 1450 | M54: 0.48958333 | N54: 215 | O54: =(O53+N54/60) -> 62.35
B55: 1063 | C55: 44078 | D55: Nevada 2 - 24 | E55: Pyrénées | F55: Planot | I55: Arbas | J55: Local | M55: 0.52083333 | N55: 240 | O55: =(O54+N55/60) -> 66.35
B56: 1064 | C56: 44079 | D56: Nevada 2 - 24 | E56: Pyrénées | F56: Planot | I56: Arbas | J56: Local | M56: 0.57638889 | N56: 70 | O56: =(O55+N56/60) -> 67.516667
B57: 1065 | C57: 44082 | D57: Nevada 2 - 24 | E57: Pyrénées | F57: Planot | I57: Arbas | J57: Local | M57: 0.49305556 | N57: 160 | O57: =(O56+N57/60) -> 70.183333
B58: 1066 | C58: 44084 | D58: Nevada 2 - 24 | E58: Pyrénées | F58: Cornudère | G58: Rando | H58: 1100 | I58: Arbas | J58: Local | M58: 0.60416667 | N58: 40 | O58: =(O57+N58/60) -> 70.85 | Q58: Flux de NO avec beaucoup de vent, attéro limite
B59: 1067 | C59: 44085 | D59: Nevada 2 - 24 | E59: Pyrénées | F59: Planot | I59: Arbas | J59: Local | M59: 0.47916667 | N59: 70 | O59: =(O58+N59/60) -> 72.016667 | Q59: Décollé tôt les conditions sont fumantes mais avec 1700 à la Husse je ne pars pas vers le cagire. Passage au Thoas, puis au relais ou je ne trouve rien,
B60: 1068 | C60: 44086 | D60: BGD Dual 40 | E60: Pyrénées | F60: Planot | I60: Arbas | J60: Local | N60: 127 | O60: =(O59+N60/60) -> 74.133333 | Q60: Les prévisions étaient parfaites, la réalité tout autre. En plus on décolle trop tot, du coup on semmerde à Soulan à se renrdre malade. Ensuite tour du bocal mais l'envie n'y était plus.
B61: 1069 | C61: 44086 | D61: BGD Dual 40 | E61: Pyrénées | F61: Planot | I61: Arbas | J61: Local | N61: 25 | O61: =(O60+N61/60) -> 74.55 | Q61: Vol de découvert avec Claire 65 kg. Premier gonfflage raté pour une énorme clé pas vu au démélage. Second déco raté parceque je contrôle mal la voile et ensuite notre course d'élan est trop hératique alors je stoppe tout. 3ième déco face voile Ok.
B62: 1070 | C62: 44086 | D62: BGD Dual 40 | E62: Pyrénées | F62: Herran | G62: Rando | H62: 100 | I62: Arbas | J62: Local | N62: 45 | O62: =(O61+N62/60) -> 75.3 | Q62: Vol de découverte avec léna 45 kg
B63: 1071 | C63: 44087 | D63: BGD Dual 40 | E63: Pyrénées | F63: Planot | I63: Arbas | J63: Local | N63: 125 | O63: =(O62+N63/60) -> 77.383333 | Q63: En gros le même vol que la veille mais dans des conditions beaucoup plus softe du coup beaucoup plus de plaisir.
B64: 1072 | C64: 44104 | D64: Nevada 2 - 24 | E64: Pyrénées | F64: Planot | G64: Rando | H64: 700 | I64: Arbas | J64: Local | M64: 0.5625 | N64: 140 | O64: =(O63+N64/60) -> 79.716667 | Q64: Un vol comme je les aime, et même si au début je me suis fait bougé, du temps de retrouver mes repères et e,suite, dans des thermiques puissants mais plafonnant au mieux à 1400, je vais un peu partout dans le bocal. Un régal.
B65: 1073 | C65: 44128 | D65: Nevada 2 - 24 | E65: Pyrénées | F65: Cornudère | G65: E | H65: 1100 | I65: Arbas | J65: Local | M65: 0.5625 | N65: 90 | O65: =(O64+N65/60) -> 81.216667 | Q65: Monté en 2 temps. Je pensais être un peu juste pour partir de l'attéro, du coup j'ai laissé la C15 à Herran. Cç monte bien à Cornu sans trop de mal. 1h30 enviuron. Après un vol sympa, posé à Arbas bien sûr, je suis remonté chercher la voiture, toujours avec le sac (selette montagne) en peut-être 1h. La boucle est bouclée. Yooupiii.
B66: 1074 | C66: 44133 | D66: Nevada 2 - 24 | E66: Pyrénées | F66: Cornudère | G66: Rando | H66: 1100 | I66: Arbas | J66: Local | M66: 0.58333333 | N66: 90 | O66: =(O65+N66/60) -> 82.716667 | Q66: De nouveau montée en 2 temps, mais cette fois je laisse le C15 au pkg de la fontaine de l'ours et je monte avec le sac "site". Vol agréable pour le dernier avant le ocnfinemant je pouvais pas espérer mieux.

Sheet Cal 2020
B1: janvier | D1: février | G1: mars | I1: avril | K1: mai | N1: juin | Q1: juillet | S1: août | U1: septembre | X1: octobre | Z1: novembre | AB1: décembre
A2: M | B2: 40179 | C2: S | D2: 40210 | F2: D | G2: 40238 | H2: M | I2: 40269 | J2: V | K2: 40299 | M2: L | N2: 40330 | P2: M | Q2: 40360 | R2: S | S2: 40391 | T2: M | U2: 40422 | W2: J | X2: 40452 | Y2: D | Z2: 40483 | AA2: M | AB2: 40513
A3: J | B3: 40180 | C3: D | D3: 40211 | F3: L | G3: 40239 | H3: J | I3: 40270 | J3: S | K3: 40300 | M3: M | N3: 40331 | P3: J | Q3: 40361 | R3: D | S3: 40392 | T3: M | U3: 40423 | W3: V | X3: 40453 | Y3: L | Z3: 40484 | AA3: M | AB3: 40514
A4: V | B4: 40181 | C4: L | D4: 40212 | F4: M | G4: 40240 | H4: V | I4: 40271 | J4: D | K4: 40301 | M4: M | N4: 40332 | P4: V | Q4: 40362 | R4: L | S4: 40393 | T4: J | U4: 40424 | W4: S | X4: 40454 | Y4: M | Z4: 40485 | AA4: J | AB4: 40515
A5: S | B5: 40182 | C5: M | D5: 40213 | F5: M | G5: 40241 | H5: S | I5: 40272 | J5: L | K5: 40302 | M5: J | N5: 40333 | P5: S | Q5: 40363 | R5: M | S5: 40394 | T5: V | U5: 40425 | W5: D | X5: 40455 | Y5: M | Z5: 40486 | AA5: V | AB5: 40516
A6: D | B6: 40183 | C6: M | D6: 40214 | F6: J | G6: 40242 | H6: D | I6: 40273 | J6: M | K6: 40303 | M6: V | N6: 40334 | P6: D | Q6: 40364 | R6: M | S6: 40395 | T6: S | U6: 40426 | W6: L | X6: 40456 | Y6: J | Z6: 40487 | AA6: S | AB6: 40517
A7: L | B7: 40184 | C7: J | D7: 40215 | F7: V | G7: 40243 | H7: L | I7: 40274 | J7: M | K7: 40304 | M7: S | N7: 40335 | P7: L | Q7: 40365 | R7: J | S7: 40396 | T7: D | U7: 40427 | W7: M | X7: 40457 | Y7: V | Z7: 40488 | AA7: D | AB7: 40518
A8: M | B8: 40185 | C8: V | D8: 40216 | F8: S | G8: 40244 | H8: M | I8: 40275 | J8: J | K8: 40305 | M8: D | N8: 40336 | P8: M | Q8: 40366 | R8: V | S8: 40397 | T8: L | U8: 40428 | W8: M | X8: 40458 | Y8: S | Z8: 40489 | AA8: L | AB8: 40519
A9: M | B9: 40186 | C9: S | D9: 40217 | F9: D | G9: 40245 | H9: M | I9: 40276 | J9: V | K9: 40306 | M9: L | N9: 40337 | P9: M | Q9: 40367 | R9: S | S9: 40398 | T9: M | U9: 40429 | W9: J | X9: 40459 | Y9: D | Z9: 40490 | AA9: M | AB9: 40520
A10: J | B10: 40187 | C10: D | D10: 40218 | F10: L | G10: 40246 | H10: J | I10: 40277 | J10: S | K10: 40307 | M10: M | N10: 40338 | P10: J | Q10: 40368 | R10: D | S10: 40399 | T10: M | U10: 40430 | W10: V | X10: 40460 | Y10: L | Z10: 40491 | AA10: M | AB10: 40521
A11: V | B11: 40188 | C11: L | D11: 40219 | F11: M | G11: 40247 | H11: V | I11: 40278 | J11: D | K11: 40308 | M11: M | N11: 40339 | P11: V | Q11: 40369 | R11: L | S11: 40400 | T11: J | U11: 40431 | W11: S | X11: 40461 | Y11: M | Z11: 40492 | AA11: J | AB11: 40522
A12: S | B12: 40189 | C12: M | D12: 40220 | F12: M | G12: 40248 | H12: S | I12: 40279 | J12: L | K12: 40309 | M12: J | N12: 40340 | P12: S | Q12: 40370 | R12: M | S12: 40401 | T12: V | U12: 40432 | W12: D | X12: 40462 | Y12: M | Z12: 40493 | AA12: V | AB12: 40523
A13: D | B13: 40190 | C13: M | D13: 40221 | F13: J | G13: 40249 | H13: D | I13: 40280 | J13: M | K13: 40310 | M13: V | N13: 40341 | P13: D | Q13: 40371 | R13: M | S13: 40402 | T13: S | U13: 40433 | V13: Biplaces Profil | W13: L | X13: 40463 | Y13: J | Z13: 40494 | AA13: S | AB13: 40524
A14: L | B14: 40191 | C14: J | D14: 40222 | F14: V | G14: 40250 | H14: L | I14: 40281 | J14: M | K14: 40311 | M14: S | N14: 40342 | P14: L | Q14: 40372 | R14: J | S14: 40403 | T14: D | U14: 40434 | V14: Biplaces Profil | W14: M | X14: 40464 | Y14: V | Z14: 40495 | AA14: D | AB14: 40525
A15: M | B15: 40192 | C15: V | D15: 40223 | F15: S | G15: 40251 | H15: M | I15: 40282 | J15: J | K15: 40312 | M15: D | N15: 40343 | P15: M | Q15: 40373 | R15: V | S15: 40404 | T15: L | U15: 40435 | W15: M | X15: 40465 | Y15: S | Z15: 40496 | AA15: L | AB15: 40526
A16: M | B16: 40193 | C16: S | D16: 40224 | F16: D | G16: 40252 | H16: M | I16: 40283 | J16: V | K16: 40313 | M16: L | N16: 40344 | P16: M | Q16: 40374 | R16: S | S16: 40405 | T16: M | U16: 40436 | W16: J | X16: 40466 | Y16: D | Z16: 40497 | AA16: M | AB16: 40527
A17: J | B17: 40194 | C17: D | D17: 40225 | F17: L | G17: 40253 | H17: J | I17: 40284 | J17: S | K17: 40314 | L17: Compet Arbas | M17: M | N17: 40345 | P17: J | Q17: 40375 | R17: D | S17: 40406 | T17: M | U17: 40437 | W17: V | X17: 40467 | Y17: L | Z17: 40498 | AA17: M | AB17: 40528
A18: V | B18: 40195 | C18: L | D18: 40226 | F18: M | G18: 40254 | H18: V | I18: 40285 | J18: D | K18: 40315 | M18: M | N18: 40346 | P18: V | Q18: 40376 | R18: L | S18: 40407 | T18: J | U18: 40438 | W18: S | X18: 40468 | Y18: M | Z18: 40499 | AA18: J | AB18: 40529
A19: S | B19: 40196 | C19: M | D19: 40227 | F19: M | G19: 40255 | H19: S | I19: 40286 | J19: L | K19: 40316 | M19: J | N19: 40347 | P19: S | Q19: 40377 | R19: M | S19: 40408 | T19: V | U19: 40439 | W19: D | X19: 40469 | Y19: M | Z19: 40500 | AA19: V | AB19: 40530
A20: D | B20: 40197 | C20: M | D20: 40228 | F20: J | G20: 40256 | H20: D | I20: 40287 | J20: M | K20: 40317 | M20: V | N20: 40348 | P20: D | Q20: 40378 | R20: M | S20: 40409 | T20: S | U20: 40440 | W20: L | X20: 40470 | Y20: J | Z20: 40501 | AA20: S | AB20: 40531
A21: L | B21: 40198 | C21: J | D21: 40229 | F21: V | G21: 40257 | H21: L | I21: 40288 | J21: M | K21: 40318 | M21: S | N21: 40349 | P21: L | Q21: 40379 | R21: J | S21: 40410 | T21: D | U21: 40441 | W21: M | X21: 40471 | Y21: V | Z21: 40502 | AA21: D | AB21: 40532
A22: M | B22: 40199 | C22: V | D22: 40230 | F22: S | G22: 40258 | H22: M | I22: 40289 | J22: J | K22: 40319 | M22: D | N22: 40350 | P22: M | Q22: 40380 | R22: V | S22: 40411 | T22: L | U22: 40442 | W22: M | X22: 40472 | Y22: S | Z22: 40503 | AA22: L | AB22: 40533
A23: M | B23: 40200 | C23: S | D23: 40231 | F23: D | G23: 40259 | H23: M | I23: 40290 | J23: V | K23: 40320 | M23: L | N23: 40351 | P23: M | Q23: 40381 | R23: S | S23: 40412 | T23: M | U23: 40443 | W23: J | X23: 40473 | Y23: D | Z23: 40504 | AA23: M | AB23: 40534
A24: J | B24: 40201 | C24: D | D24: 40232 | F24: L | G24: 40260 | H24: J | I24: 40291 | J24: S | K24: 40321 | M24: M | N24: 40352 | O24: Départ X-Pyr | P24: J | Q24: 40382 | R24: D | S24: 40413 | T24: M | U24: 40444 | W24: V | X24: 40474 | Y24: L | Z24: 40505 | AA24: M | AB24: 40535
A25: V | B25: 40202 | C25: L | D25: 40233 | F25: M | G25: 40261 | H25: V | I25: 40292 | J25: D | K25: 40322 | M25: M | N25: 40353 | P25: V | Q25: 40383 | R25: L | S25: 40414 | T25: J | U25: 40445 | W25: S | X25: 40475 | Y25: M | Z25: 40506 | AA25: J | AB25: 40536
A26: S | B26: 40203 | C26: M | D26: 40234 | F26: M | G26: 40262 | H26: S | I26: 40293 | J26: L | K26: 40323 | M26: J | N26: 40354 | P26: S | Q26: 40384 | R26: M | S26: 40415 | T26: V | U26: 40446 | W26: D | X26: 40476 | Y26: M | Z26: 40507 | AA26: V | AB26: 40537
A27: D | B27: 40204 | C27: M | D27: 40235 | F27: J | G27: 40263 | H27: D | I27: 40294 | J27: M | K27: 40324 | M27: V | N27: 40355 | P27: D | Q27: 40385 | R27: M | S27: 40416 | T27: S | U27: 40447 | W27: L | X27: 40477 | Y27: J | Z27: 40508 | AA27: S | AB27: 40538
A28: L | B28: 40205 | C28: J | D28: 40236 | F28: V | G28: 40264 | H28: L | I28: 40295 | J28: M | K28: 40325 | M28: S | N28: 40356 | P28: L | Q28: 40386 | R28: J | S28: 40417 | T28: D | U28: 40448 | W28: M | X28: 40478 | Y28: V | Z28: 40509 | AA28: D | AB28: 40539
A29: M | B29: 40206 | C29: V | D29: 43889 | F29: S | G29: 40265 | H29: M | I29: 40296 | J29: J | K29: 40326 | M29: D | N29: 40357 | P29: M | Q29: 40387 | R29: V | S29: 40418 | T29: L | U29: 40449 | W29: M | X29: 40479 | Y29: S | Z29: 40510 | AA29: L | AB29: 40540
A30: M | B30: 40207 | C30: S | D30: 43890 | E30: Route du Vol "Hivernale" | F30: D | G30: 40266 | H30: M | I30: 40297 | J30: V | K30: 40327 | M30: L | N30: 40358 | P30: M | Q30: 40388 | R30: S | S30: 40419 | T30: M | U30: 40450 | W30: J | X30: 40480 | Y30: D | Z30: 40511 | AA30: M | AB30: 40541
A31: J | B31: 40208 | E31: Soaring | F31: L | G31: 40267 | H31: J | I31: 40298 | J31: S | K31: 40328 | L31: report Arbas | M31: M | N31: 40359 | P31: J | Q31: 40389 | R31: D | S31: 40420 | T31: M | U31: 40451 | W31: V | X31: 40481 | Y31: L | Z31: 40512 | AA31: M | AB31: 40542
A32: V | B32: 40209 | F32: M | G32: 40268 | J32: D | K32: 40329 | P32: V | Q32: 40390 | R32: L | S32: 40421 | W32: S | X32: 40482 | AA32: J | AB32: 40543
B34: 16 | D34: 14 | G34: 13 | I34: 13 | K34: 13 | N34: 0 | Q34: 0 | S34: 31 | U34: 0 | X34: 0 | Z34: 0 | AB34: 0 | AC34: =SUM(A34:AB34) -> 100
B35: 15 | D35: 15 | G35: 18 | I35: 17 | K35: 16 | N35: 0 | Q35: 28 | S35: 0 | U35: 0 | X35: 0 | Z35: 0 | AB35: 0 | AC35: =SUM(A35:AB35) -> 109

Sheet 2019
A1: Compt | B1: N° Vol | C1: Date | D1: Voile | E1: Région | F1: Déco | G1: Acc. | H1: Dén. | I1: Attéro | J1: Type de vol | K1: Météo | L1: A1 max | M1: Heure décollage (locale) | N1: Durée | O1: Durée cumulée | P1: Dist | Q1: Description, vol et atterrissage ou Exercices | R1: Exercices
A2: 1 | B2: 935 | C2: 43480 | D2: Nevada 2 - 24 | E2: Pyrénées | F2: Sous Pic Noir | H2: 800 | I2: Appy | J2: Rando | M2: 0.58333333 | N2: 15
A3: 1 | B3: 936 | C3: 43505 | D3: Nevada 2 - 24 | E3: Colombie | F3: Aqua Panela | G3: navette | J3: Cross | L3: 2580 | M3: 0.5 | N3: 227 | O3: =(O2+N3/60) -> 3.7833333 | P3: 43
A4: 1 | B4: 937 | C4: 43506 | D4: Nevada 2 - 24 | E4: Colombie | F4: Aqua Panela | G4: navette | J4: Cross | L4: 2800 | M4: 0.47222222 | N4: 235 | O4: =(O3+N4/60) -> 7.7 | P4: 65
A5: 1 | B5: 938 | C5: 43507 | D5: Nevada 2 - 24 | E5: Colombie | F5: Aqua Panela | G5: navette | J5: Cross | L5: 2590 | M5: 0.4375 | N5: 130 | O5: =(O4+N5/60) -> 9.8666667 | P5: 39
A6: 1 | B6: 939 | C6: 43508 | D6: Nevada 2 - 24 | E6: Colombie | F6: Aqua Panela | G6: navette | J6: Cross | L6: 2660 | M6: 0.48333333 | N6: 225 | O6: =(O5+N6/60) -> 13.616667 | P6: 47
A7: 1 | B7: 940 | C7: 43509 | D7: Nevada 2 - 24 | E7: Colombie | F7: Aqua Panela | G7: navette | J7: Cross | L7: 2730 | M7: 0.41875 | N7: 285 | O7: =(O6+N7/60) -> 18.366667 | P7: 64
A8: 1 | B8: 941 | C8: 43545 | D8: Nevada 2 - 24 | E8: Pyrénées | F8: Cornudère | G8: rando | H8: 400 | I8: Arbas | J8: Cross | K8: Instable en basse couche, sudouest en altitude, retour d'Est. | L8: 1880 | M8: 0.5 | N8: 131 | O8: =(O7+N8/60) -> 20.55 | P8: 25
A9: 1 | B9: 942 | C9: 43546 | D9: Nevada 2 - 24 | E9: Pyrénées | F9: Planot | G9: navette | I9: Arbas | J9: Cross | L9: 1680 | M9: 0.5125 | N9: 136 | O9: =(O8+N9/60) -> 22.816667
A10: 1 | B10: 943 | C10: 43547 | D10: Nevada 2 - 24 | E10: Pyrénées | F10: Planot | G10: navette | I10: Galié (Garonne) | J10: Cross | K10: NE 10-15 kmh | L10: 1960 | M10: 0.49791667 | N10: 105 | O10: =(O9+N10/60) -> 24.566667 | P10: 26
A11: 1 | B11: 944 | C11: 43550 | D11: Queen 2 - MS | E11: Pyrénées | F11: Planot | G11: navette | I11: Arbas | J11: Cross | K11: NE 10-15 kmh | L11: 1800 | M11: 0.48611111 | N11: 165 | O11: =(O10+N11/60) -> 27.316667 | P11: 25 | Q11: 1er vrai vol avec la Queen dans des conditions délicates car avec du vent, plutot NE. Evidemment beaucoup d'appréhension. Difficulté à m'installer dans le cocon dont la partie inférieure de coince au dessus du plateau. La voile est vraiemnt à la hauteur de mes espérences en termes de perf, de vitresse de pénétartion dans le vent, un auutre monde par rapport à la Névada. Les commandes me semblent un peu physique, pais les conditions n'tatéient pas facile et demandées de tenir la voile comme il faut. Pas d'incident notable. Elle est facile à coler accéléré au 1er barreau, semble perdre beaucoup de tau de chutre au second. Une belle machine.Reste à l'apprivoiser sur la durée.
A12: 1 | B12: 945 | C12: 43551 | D12: Queen 2 - MS | E12: Pyrénées | F12: Planot | G12: navette | I12: Fougaron | L12: 1800 | M12: 0.50208333 | N12: 78 | O12: =(O11+N12/60) -> 28.616667 | Q12: On pensait avec La Tachte partir vers l'Ouest mais trop de vent à la Husse nous fait faire demi tour. Je me vois beau et transit directement vers le col d'Arbas, 1ere erreur, je ne truve rien. En tentant de trouver une ascendance je remont la crête vers le sud, 2ième erreur, toujours rien, je me retrouve sur les faces sud de Berteille et me pose miteux à fougaron. Que de conneries
A13: 1 | B13: 946 | C13: 43552 | D13: Nevada 2 - 24 | E13: Pyrénées | F13: Cornudère | G13: rando | H13: 1100 | I13: Arbas | J13: Cross | K13: NO | L13: 1850 | M13: 0.52083333 | N13: 145 | O13: =(O12+N13/60) -> 31.033333 | Q13: parti de l'attéro df'arbas à pied, je recupère ma voile au pkg de la fontaine de l'ours poru Cornudère. Bon vent de N pour bien décoller. Après un passage à la husse pour constater qu'il y a toujours de l'ouest, je pars vers Cornudère puis les crêtes jusuqu'à Herbes Blanches. Je retrouve une bonne ascendance en compagnie de PPa et sa Zeno, et Tim avec sa M6. Je les suis vers l'Esteals dont ils sortent rapidement. Je gakère un bout de temps avant de trouver la bonne solution et de 1800 j'ai de la peine à rentrer au relais. Mais au moins je boucle proprement.
A14: 1 | B14: 947 | C14: 43554 | D14: BiGolden2 - 38 | E14: Pyrénées | F14: Planot | G14: navette | I14: Arbas | M14: 0.47916667 | N14: 10 | O14: =(O13+N14/60) -> 31.2 | Q14: Plouf du matin avec Louis pour éviter les trubulences
A15: 1 | B15: 948 | C15: 43554 | D15: BiGolden2 - 38 | E15: Pyrénées | F15: Planot | G15: navette | I15: Arbas | M15: 0.52083333 | N15: 10 | O15: =(O14+N15/60) -> 31.366667 | Q15: On rate le thermique en sortie de déco
A16: 1 | B16: 949 | C16: 43554 | D16: BiGolden2 - 38 | E16: Pyrénées | F16: Planot | G16: navette | I16: Arbas | M16: 0.5625 | N16: 65 | O16: =(O15+N16/60) -> 32.45 | Q16: 2d vol avec uentin, cette fois, on prend un thermique en allant vers Bourrusse. On ne le lache pas en dérivant jusqu'à la crête de Cornu. Ensuite La Husse, Mountagnat, Relais. Quentin content de poser car on se faisait quand même un pêu secouer !!!
A17: 1 | B17: 950 | C17: 43575 | D17: Nevada 2 - 24 | E17: Alpes nord | F17: Serpaton | G17: Scoot | I17: Grisail | J17: Cross | K17: Nord en altitide | L17: 2950 | M17: 0.46180556 | N17: 160 | O17: =(O16+N17/60) -> 35.116667 | P17: 65 | Q17: Monté au Serpaton en scooter, je décole dans les derniers. Ca monte tout seul devant le déco. Direction Sud, passage au Gd Veymont ou j'emplafonne les 300m/sol du parc du Vercors, dommage, je savais pâs, j'aurai du me renseigner avant. Le Sys Evo me la signaler, mais du temps de comprendre. Pas facile cet outil. Ensuite duirect Nord jusqu'à la pointe au dessu de Grenoble, puis retour. Dommage que je me fasse enterré sur la fin, qui est un peu misérable.
A18: 1 | B18: 951 | C18: 43577 | D18: Queen 2 - MS | E18: Alpes nord | F18: St Hilaire | G18: Scoot | H18: 700 | J18: Cross | K18: Crash | N18: 60 | O18: =(O17+N18/60) -> 36.116667 | Q18: Le vol qu'il ne fallait pas faire. Déco de St Hilaire, branche jusqu'au fort de St Eynard, cacsades d'incidents et secours un peu après le début du retour au niveau de la Sappey en Chartreuse. Aucun bobo, fin dans un arbre, descendu seul et récup de la voile le lendemain en coupant 2 arbres. Ajout réflexion en fin d'année. Suite réunion sécu CDVL 31, en particulier sur le fonctionnement cérébrale, je suis presque sur d'avoir subi une phase de viscosité mentale, heureusement qu'il y avait assez de hatuteur sol pour que je réagisse (aidé aussi par un parapentiste à proximité qui m'a crié "Secours") et que le secours fasse éffet. Finalement, j'ai fait ce qu'il fallait, dans une situation qui ne me serait probablement pas arrivé sous la Névada. Depuis, j'ai vendu la vario Syride Evo et la sellette cocon. Dommage que la voile n'est pas été vendu... (finalement vendue 1600 euros)
A19: 1 | B19: 952 | C19: 43586 | D19: Nevada 2 - 24 | E19: Alpes nord | F19: Entrevernes | G19: rando | H19: 400 | I19: Doussard | N19: 20 | O19: =(O18+N19/60) -> 36.45
A20: 1 | B20: 953 | C20: 43601 | D20: Nevada 2 - 24 | E20: Pyrénées | F20: Cornudère | G20: rando | H20: 1100 | I20: Arbas | J20: Local | L20: 160 | M20: 0.52083333 | N20: 40 | O20: =(O19+N20/60) -> 37.116667 | Q20: 2h20 pour monter, avec le matos montagne dont maintenant un secours ! Pourtant je l'ai eu dure sur la fin. Vol sans interet, j'ai trouvé que ça bougeait pas mal pour pas grand-chose…
A21: 1 | B21: 954 | C21: 43607 | D21: Nevada 2 - 24 | E21: Pyrénées | F21: Planot | G21: rando | H21: 700 | I21: Arbas | J21: Local | L21: 1640 | M21: 0.47222222 | N21: 109 | O21: =(O20+N21/60) -> 38.933333 | Q21: Montée à pied, le sac déjà en haut. Vol correct avec un beau passage du coté de Piscatel.
A22: 1 | B22: 955 | C22: 43622 | D22: Nevada 2 - 24 | E22: Pyrénées | F22: Planot | G22: rando | H22: 700 | I22: Arbas | J22: Local | K22: Flux d'Est | M22: 0.5 | N22: 70 | O22: =(O21+N22/60) -> 40.1 | Q22: Voile laissée au déco en voiture et remontée à pied. Turbulent avec le flux d'Est 10/15kmh. D'ailleu j'étais le seul en l'air. Attéro déliact et turbulent.
A23: 1 | B23: 956 | C23: 43628 | D23: Nevada 2 - 24 | E23: Pyrénées | F23: Planot | G23: rando | H23: 700 | I23: Arbas | J23: Local | K23: Flux d'Ouest | L23: 1800 | M23: 0.48611111 | N23: 140 | O23: =(O22+N23/60) -> 42.433333 | Q23: Comme jeudi dernier mais avce le flux inverse. Donc montée à pied avec la voile en haut, thermiques un peu partout mais turbulents. Cette fois du monde en l'air!
